Workbook
Name Acumulación: '[1]Entrevista Balance'!$D$17
Name Acumulación: 'Entrevista Balance'!$D$17
Name Afore: '[1]Entrevista Balance'!$D$24
Name Afore: 'Entrevista Balance'!$D$24
Name CapacidaddeAhorro: '[1]Entrevista Balance'!$G$28
Name CapacidaddeAhorro: 'Entrevista Balance'!$G$28
Name CapitalHumanoPotencialVF: 'Cálculos y Supuestos Balance'!$C$25
Name CapitalHumanoPotencialVP: 'Cálculos y Supuestos Balance'!$C$24
Name CapRatePropiedades: 'Cálculos y Supuestos Balance'!$C$5
Name CoberturaCortoPlazo: 'Cálculos y Supuestos Balance'!$I$5
Name CostoSegurodeVidaporMillón: 'Cálculos y Supuestos Balance'!$C$6
Name DependientesEconómicos: 'Entrevista Balance'!$D$10
Name EdadActual: 'Entrevista Balance'!$D$6
Name EdadActual: 'Entrevista Balance'!$D$6
Name EdadActual: 'Entrevista Balance'!$D$6
Name EdadActual: 'Cálculos y Supuestos Edo.Res'!$C$7
Name EdadActual2: 'Cálculos y Supuestos Edo.Res'!$C$7
Name EdaddeDefunción: '[1]Cálculos y Supuestos Balance'!$C$4
Name EdaddeDefunción: 'Cálculos y Supuestos Balance'!$C$4
Name EdaddeRetiro: '[1]Entrevista Balance'!$D$34
Name EdaddeRetiro: 'Entrevista Balance'!$D$34
Name FinRecursos: '[1]Cálculos y Supuestos Edo.Res'!$C$9
Name FinRecursos: 'Cálculos y Supuestos Edo.Res'!$C$9
Name IngresosPrincipales: 'Cálculos y Supuestos Balance'!$C$9
Name InicioDesacumulacion: '[1]Cálculos y Supuestos Edo.Res'!$C$8
Name InicioDesacumulacion: 'Cálculos y Supuestos Edo.Res'!$C$8
Name MensualidaddeseadaenelRetiro: '[1]Entrevista Balance'!$D$36
Name MensualidaddeseadaenelRetiro: 'Entrevista Balance'!$D$36
Name MiNivel: 'Cálculos y Supuestos Balance'!$I$22
Name MLey73: '[1]Entrevista Balance'!$D$32
Name MLey73: 'Entrevista Balance'!$D$32
Name Montoaproximadodeinversión: '[1]Cálculos y Supuestos Balance'!$T$21
Name Montoaproximadodeinversión: 'Cálculos y Supuestos Balance'!$T$21
Name Númerodeperiodosacumulación: '[1]Cálculos y Supuestos Balance'!$C$23
Name Númerodeperiodosacumulación: 'Cálculos y Supuestos Balance'!$C$23
Name Númerodeperiodosdesacumulación: 'Cálculos y Supuestos Balance'!$C$20
Name OtrosIngresos: '[1]Entrevista Balance'!$G$32
Name OtrosIngresos: 'Entrevista Balance'!$G$32
Name OtrosPlanesdeSegurosparaRetiro: '[1]Entrevista Balance'!$D$30
Name OtrosPlanesdeSegurosparaRetiro: 'Entrevista Balance'!$D$30
Name PatrimonioFinancieroActualTotal: '[1]Cálculos y Supuestos Balance'!$C$22
Name PatrimonioFinancieroActualTotal: 'Cálculos y Supuestos Balance'!$C$22
Name PatrimonioFinancieroActualTotalVF: '[1]Cálculos y Supuestos Balance'!$C$34
Name PatrimonioFinancieroActualTotalVF: 'Cálculos y Supuestos Balance'!$C$34
Name PlanesdeSeguroAcumulación1: '[1]Entrevista Balance'!$D$19
Name PlanesdeSeguroAcumulación1: 'Entrevista Balance'!$D$19
Name PlanPrivadodePensión: '[1]Entrevista Balance'!$D$28
Name PlanPrivadodePensión: 'Entrevista Balance'!$D$28
Name Plazo2: 'Entrevista Balance'!$D$22
Name PPR: '[1]Entrevista Balance'!$D$26
Name PPR: 'Entrevista Balance'!$D$26
Name Rentas: '[1]Entrevista Balance'!$G$30
Name Rentas: 'Entrevista Balance'!$G$30
Name ReservaCortoPlazo: '[1]Entrevista Balance'!$D$15
Name ReservaCortoPlazo: 'Entrevista Balance'!$D$15
Name Saldoenesquemasderetiro: 'Cálculos y Supuestos Balance'!$C$10
Name SumaAseguradadeSegurodeVida: 'Cálculos y Supuestos Balance'!$C$81
Name TasaReal: 'Cálculos y Supuestos Balance'!$C$3
Name TasaReal: 'Cálculos y Supuestos Balance'!$C$3
Name TasaReal: '[1]Cálculos y Supuestos Edo.Res'!$C$4

Sheet Entrevista Patrimonio F.
O2: =TODAY() -> 46083
C3: Asesor:
C5: GENERALES DE CLIENTE
D7: Nombre o alias: | E7: JUAN PEREZ | L7: ID Cliente/Prospecto:
L8: *Llenado por el asesor
D9: Edad actual: | E9: 50 | G9: Género: | I9: Hombre
G11: Ocupación actual: | I11: Asalariado
C15: La siguiente información es necesaria para calcular tu fortaleza financiera.
C17: INGRESOS MENSUALES | K17: OBLIGACIONES MENSUALES
D19: ¿Cuál es tu capacidad de Ahorro? | I19: 50000 | L19: ¿A cuánto ascienden tus gastos básicos mensuales? | P19: 40000
L20: Alimentos, servicios, transporte, ropa, entretenimiento, pago de renta
D21: ¿Tienes ingresos mensuales por propiedades en rentas? | I21: 10000 | L21: ¿A cuánto ascienden tus obligaciones mensuales? | P21: 20000
L22: Colegiaturas, seguros, manutención, impuestos. *Sin considerar créditos | R22: Institución:
D23: ¿Cuál es el monto mensual de otros ingresos? | I23: 0 | L23: ¿A cuánto ascienden créditos? | P23: 0
C27: PATRIMONIO FINANCIERO
N28: Institución:
D29: ¿Cuál es el monto de tus los ahorros de los que puedes disponer de forma inmediata? | L29: 200000
D30: Saldo en cuentas de débito o instrumentos de liquidez inmediata
D31: ¿A cuánto asciende tu saldo en otras inversiones financieras? | L31: 2000000
D32: Inversiones financieras no líquidas
D33: ¿Cuál es el saldo otros planes de seguro de acumulación? | L33: 100000
D34: Dotales
D36: ¿A qué edad planeas retirarte? | G36: 60 | L36: ESQUEMAS DE RETIRO
R37: Institución:
D38: ¿Cuánto deseas percibir mensualmente en tu edad de retiro? | I38: 50000 | L38: ¿Cuál es el saldo de tu cuenta de Afore? | P38: 1000000
L40: ¿Cuál es el saldo en tu PPR? | P40: 0
L42: ¿Cuál es el saldo en Plan privado de pensión? | P42: 0
L44: ¿Cuál es el saldo otros planes de seguro para el retiro? | P44: 0
L46: ¿Cuál es tu mensualidad aproximada por la Ley 73? | P46: 35000
L47: Solo para mayores de 46 años que cotizaron antes del 1o de julio de 1997. Aplica Ley 73
C50: La siguiente información es necesaria para diagnosticar el valor de tu patrimonio en riesgo.
C52: PROTECCIÓN PATRIMONIAL
Y53: =IF(Y52<>"",IF(Y52+1>80,"",Y52+1),"")
D54: ¿Tienes dependientes económicos? | G54: Sí | Y54: =IF(Y53<>"",IF(Y53+1>80,"",Y53+1),"")
Y55: =IF(Y54<>"",IF(Y54+1>80,"",Y54+1),"")
D56: ¿Tus propiedades están aseguradas? | G56: No | Y56: =IF(Y55<>"",IF(Y55+1>80,"",Y55+1),"")
Y57: =IF(Y56<>"",IF(Y56+1>80,"",Y56+1),"")

Sheet Cálculos y Supuestos Edo.Res
W2: Regla del 72
W3: Total | X3: ='Entrevista Patrimonio F.'!L29+'Entrevista Patrimonio F.'!L31 -> 2200000
B4: Tasa Real | C4: 0.01
M5: =(72/M6)/100 -> 9 | N5: =(72/N6)/100 -> 6 | O5: =(72/O6)/100 -> 5.1428571
B6: Información General | F6: Análisis Ingreso/Gasto | L6: Periodo | M6: 0.08 | N6: 0.12 | O6: 0.14 | R6: Años | S6: 0.08 | T6: 0.12 | U6: 0.14 | X6: 0.08 | Y6: 0.12 | Z6: 0.14
B7: Edad | C7: ='Entrevista Patrimonio F.'!E9 -> 50 | L7: 1 | M7: =ROUND(M$5*$L7,0) -> 9 | N7: =ROUND(N$5*$L7,0) -> 6 | O7: =ROUND(O$5*$L7,0) -> 5 | P7: =L7 -> 1 | R7: 0 | S7: =MAX(IFERROR(VLOOKUP($R7,$M$7:$P$17,4,0),0)+1,S6) -> 1 | T7: =MAX(IFERROR(VLOOKUP($R7,$N$7:$P$17,3,0),0)+1,T6) -> 1 | U7: =MAX(IFERROR(VLOOKUP($R7,$O$7:$P$17,2,0),0)+1,U6) -> 1 | W7: 0 | X7: =1*$X$3 -> 2200000 | Y7: =1*$X$3 -> 2200000 | Z7: =1*$X$3 -> 2200000
B8: Edad de Retiro | C8: ='Entrevista Patrimonio F.'!G36 -> 60 | F8: Output 1 | L8: 2 | M8: =ROUND(M$5*$L8,0) -> 18 | N8: =ROUND(N$5*$L8,0) -> 12 | O8: =ROUND(O$5*$L8,0) -> 10 | P8: =L8 -> 2 | R8: =R7+1 -> 1 | S8: =MAX(IFERROR(VLOOKUP($R8,$M$7:$P$17,4,0),0)+1,S7) -> 1 | T8: =MAX(IFERROR(VLOOKUP($R8,$N$7:$P$17,3,0),0)+1,T7) -> 1 | U8: =MAX(IFERROR(VLOOKUP($R8,$O$7:$P$17,2,0),0)+1,U7) -> 1 | W8: =W7+1 -> 1
B9: Longevidad recursos (Edad Individuo) | C9: 90 | L9: 3 | M9: =ROUND(M$5*$L9,0) -> 27 | N9: =ROUND(N$5*$L9,0) -> 18 | O9: =ROUND(O$5*$L9,0) -> 15 | P9: =L9 -> 3 | R9: =R8+1 -> 2 | S9: =MAX(IFERROR(VLOOKUP($R9,$M$7:$P$17,4,0),0)+1,S8) -> 1 | T9: =MAX(IFERROR(VLOOKUP($R9,$N$7:$P$17,3,0),0)+1,T8) -> 1 | U9: =MAX(IFERROR(VLOOKUP($R9,$O$7:$P$17,2,0),0)+1,U8) -> 1 | W9: =W8+1 -> 2
B10: Genero | C10: ='Entrevista Patrimonio F.'!I9 -> Hombre | F10: Capacidad de Ahorro | G10: ='Entrevista Patrimonio F.'!I19 -> 50000 | H10: =G10/$C$19 -> 0.45454545 | L10: 4 | M10: =ROUND(M$5*$L10,0) -> 36 | N10: =ROUND(N$5*$L10,0) -> 24 | O10: =ROUND(O$5*$L10,0) -> 21 | P10: =L10 -> 4 | R10: =R9+1 -> 3 | S10: =MAX(IFERROR(VLOOKUP($R10,$M$7:$P$17,4,0),0)+1,S9) -> 1 | T10: =MAX(IFERROR(VLOOKUP($R10,$N$7:$P$17,3,0),0)+1,T9) -> 1 | U10: =MAX(IFERROR(VLOOKUP($R10,$O$7:$P$17,2,0),0)+1,U9) -> 1 | W10: =W9+1 -> 3
B11: Dependientes Economicos | C11: ='Entrevista Patrimonio F.'!G54 -> Sí | F11: Capacidad de Ahorro Anual | G11: =G10*12 -> 600000 | L11: 5 | M11: =ROUND(M$5*$L11,0) -> 45 | N11: =ROUND(N$5*$L11,0) -> 30 | O11: =ROUND(O$5*$L11,0) -> 26 | P11: =L11 -> 5 | R11: =R10+1 -> 4 | S11: =MAX(IFERROR(VLOOKUP($R11,$M$7:$P$17,4,0),0)+1,S10) -> 1 | T11: =MAX(IFERROR(VLOOKUP($R11,$N$7:$P$17,3,0),0)+1,T10) -> 1 | U11: =MAX(IFERROR(VLOOKUP($R11,$O$7:$P$17,2,0),0)+1,U10) -> 1 | W11: =W10+1 -> 4
B12: Profesion Actual | C12: ='Entrevista Patrimonio F.'!I11 -> Asalariado | F12: Output 2 | L12: 6 | M12: =ROUND(M$5*$L12,0) -> 54 | N12: =ROUND(N$5*$L12,0) -> 36 | O12: =ROUND(O$5*$L12,0) -> 31 | P12: =L12 -> 6 | R12: =R11+1 -> 5 | S12: =MAX(IFERROR(VLOOKUP($R12,$M$7:$P$17,4,0),0)+1,S11) -> 1 | T12: =MAX(IFERROR(VLOOKUP($R12,$N$7:$P$17,3,0),0)+1,T11) -> 1 | U12: =MAX(IFERROR(VLOOKUP($R12,$O$7:$P$17,2,0),0)+1,U11) -> 2 | W12: =W11+1 -> 5 | Z12: =2*$X$3 -> 4400000
B13: Calidad de Vida Retiro | C13: ='Entrevista Patrimonio F.'!I38 -> 50000 | F13: Benchmark Reserva CP | G13: 3 | H13: Gastos Básicos | L13: 7 | N13: =ROUND(N$5*$L13,0) -> 42 | O13: =ROUND(O$5*$L13,0) -> 36 | P13: =L13 -> 7 | R13: =R12+1 -> 6 | S13: =MAX(IFERROR(VLOOKUP($R13,$M$7:$P$17,4,0),0)+1,S12) -> 1 | T13: =MAX(IFERROR(VLOOKUP($R13,$N$7:$P$17,3,0),0)+1,T12) -> 2 | U13: =MAX(IFERROR(VLOOKUP($R13,$O$7:$P$17,2,0),0)+1,U12) -> 2 | W13: =W12+1 -> 6 | Y13: =2*$X$3 -> 4400000
F14: Reserva Deseada CP | G14: =C22*G13 -> 120000 | L14: 8 | N14: =ROUND(N$5*$L14,0) -> 48 | O14: =ROUND(O$5*$L14,0) -> 41 | P14: =L14 -> 8 | R14: =R13+1 -> 7 | S14: =MAX(IFERROR(VLOOKUP($R14,$M$7:$P$17,4,0),0)+1,S13) -> 1 | T14: =MAX(IFERROR(VLOOKUP($R14,$N$7:$P$17,3,0),0)+1,T13) -> 2 | U14: =MAX(IFERROR(VLOOKUP($R14,$O$7:$P$17,2,0),0)+1,U13) -> 2 | W14: =W13+1 -> 7
B15: Ingresos | F15: Meses de Reserva CP | G15: =C29/C22 -> 5 | L15: 9 | N15: =ROUND(N$5*$L15,0) -> 54 | O15: =ROUND(O$5*$L15,0) -> 46 | P15: =L15 -> 9 | R15: =R14+1 -> 8 | S15: =MAX(IFERROR(VLOOKUP($R15,$M$7:$P$17,4,0),0)+1,S14) -> 1 | T15: =MAX(IFERROR(VLOOKUP($R15,$N$7:$P$17,3,0),0)+1,T14) -> 2 | U15: =MAX(IFERROR(VLOOKUP($R15,$O$7:$P$17,2,0),0)+1,U14) -> 2 | W15: =W14+1 -> 8
B16: Ingresos Básicos | C16: ='Entrevista Patrimonio F.'!P19+'Entrevista Patrimonio F.'!P21+'Entrevista Patrimonio F.'!P23+'Entrevista Patrimonio F.'!I19-'Entrevista Patrimonio F.'!I21-'Entrevista Patrimonio F.'!I23 -> 100000 | F16: Resultado | G16: =IF(G15>=G13,"Excedido","Insuficiente") -> Excedido | L16: 10 | O16: =ROUND(O$5*$L16,0) -> 51 | P16: =L16 -> 10 | R16: =R15+1 -> 9 | S16: =MAX(IFERROR(VLOOKUP($R16,$M$7:$P$17,4,0),0)+1,S15) -> 2 | T16: =MAX(IFERROR(VLOOKUP($R16,$N$7:$P$17,3,0),0)+1,T15) -> 2 | U16: =MAX(IFERROR(VLOOKUP($R16,$O$7:$P$17,2,0),0)+1,U15) -> 2 | W16: =W15+1 -> 9 | X16: =2*$X$3 -> 4400000
B17: Propiedades en Renta | C17: ='Entrevista Patrimonio F.'!I21 -> 10000 | F17: Pendiente por Ahorrar | G17: =IF(G16="Insuficiente",G14-C29,0) -> 0 | L17: 11 | P17: =L17 -> 11 | R17: =R16+1 -> 10 | S17: =MAX(IFERROR(VLOOKUP($R17,$M$7:$P$17,4,0),0)+1,S16) -> 2 | T17: =MAX(IFERROR(VLOOKUP($R17,$N$7:$P$17,3,0),0)+1,T16) -> 2 | U17: =MAX(IFERROR(VLOOKUP($R17,$O$7:$P$17,2,0),0)+1,U16) -> 3 | W17: =W16+1 -> 10 | Z17: =4*$X$3 -> 8800000
B18: Otros Ingresos | C18: ='Entrevista Patrimonio F.'!I23 -> 0 | F18: Meses para cubrir CP | G18: =IFERROR(IF(G17=0,0,(G17/G10)),0) -> 0 | R18: =R17+1 -> 11 | S18: =MAX(IFERROR(VLOOKUP($R18,$M$7:$P$17,4,0),0)+1,S17) -> 2 | T18: =MAX(IFERROR(VLOOKUP($R18,$N$7:$P$17,3,0),0)+1,T17) -> 2 | U18: =MAX(IFERROR(VLOOKUP($R18,$O$7:$P$17,2,0),0)+1,U17) -> 3 | W18: =W17+1 -> 11
B19: Ingresos Totales | C19: =SUM(C16:C18) -> 110000 | F19: Remanente para otros objetivos | G19: =MAX(G10*(1-G18),0) -> 50000 | R19: =R18+1 -> 12 | S19: =MAX(IFERROR(VLOOKUP($R19,$M$7:$P$17,4,0),0)+1,S18) -> 2 | T19: =MAX(IFERROR(VLOOKUP($R19,$N$7:$P$17,3,0),0)+1,T18) -> 3 | U19: =MAX(IFERROR(VLOOKUP($R19,$O$7:$P$17,2,0),0)+1,U18) -> 3 | W19: =W18+1 -> 12 | Y19: =4*$X$3 -> 8800000
R20: =R19+1 -> 13 | S20: =MAX(IFERROR(VLOOKUP($R20,$M$7:$P$17,4,0),0)+1,S19) -> 2 | T20: =MAX(IFERROR(VLOOKUP($R20,$N$7:$P$17,3,0),0)+1,T19) -> 3 | U20: =MAX(IFERROR(VLOOKUP($R20,$O$7:$P$17,2,0),0)+1,U19) -> 3 | W20: =W19+1 -> 13
B21: Gastos Básicos + Obligaciones | F21: Output 3 | R21: =R20+1 -> 14 | S21: =MAX(IFERROR(VLOOKUP($R21,$M$7:$P$17,4,0),0)+1,S20) -> 2 | T21: =MAX(IFERROR(VLOOKUP($R21,$N$7:$P$17,3,0),0)+1,T20) -> 3 | U21: =MAX(IFERROR(VLOOKUP($R21,$O$7:$P$17,2,0),0)+1,U20) -> 3 | W21: =W20+1 -> 14
B22: Gastos Básicos | C22: ='Entrevista Patrimonio F.'!P19 -> 40000 | F22: Saldo Acumulación | G22: =(C30+C35) -> 2100000 | R22: =R21+1 -> 15 | S22: =MAX(IFERROR(VLOOKUP($R22,$M$7:$P$17,4,0),0)+1,S21) -> 2 | T22: =MAX(IFERROR(VLOOKUP($R22,$N$7:$P$17,3,0),0)+1,T21) -> 3 | U22: =MAX(IFERROR(VLOOKUP($R22,$O$7:$P$17,2,0),0)+1,U21) -> 4 | W22: =W21+1 -> 15 | Z22: =8*$X$3 -> 17600000
B23: Gastos Básicos | C23: =C22 -> 40000 | D23: =C23/$C$19 -> 0.36363636 | F23: Meses de Reserva Acumulación | G23: =(G22/C26)/12 -> 2.9166667 | R23: =R22+1 -> 16 | S23: =MAX(IFERROR(VLOOKUP($R23,$M$7:$P$17,4,0),0)+1,S22) -> 2 | T23: =MAX(IFERROR(VLOOKUP($R23,$N$7:$P$17,3,0),0)+1,T22) -> 3 | U23: =MAX(IFERROR(VLOOKUP($R23,$O$7:$P$17,2,0),0)+1,U22) -> 4 | W23: =W22+1 -> 16
B24: Obligaciones Mensuales | C24: ='Entrevista Patrimonio F.'!P21+'Entrevista Patrimonio F.'!P23 -> 20000 | F24: Resultado | G24: =IF(G23>=1,"Excedido","Insuficiente") -> Excedido | R24: =R23+1 -> 17 | S24: =MAX(IFERROR(VLOOKUP($R24,$M$7:$P$17,4,0),0)+1,S23) -> 2 | T24: =MAX(IFERROR(VLOOKUP($R24,$N$7:$P$17,3,0),0)+1,T23) -> 3 | U24: =MAX(IFERROR(VLOOKUP($R24,$O$7:$P$17,2,0),0)+1,U23) -> 4 | W24: =W23+1 -> 17
B25: Obligaciones Totales | C25: =C24 -> 20000 | D25: =C25/$C$19 -> 0.18181818 | F25: Pendiente por Ahorrar | G25: =IF(G24="Insuficiente",(C26*12)-G22,0) -> 0 | R25: =R24+1 -> 18 | S25: =MAX(IFERROR(VLOOKUP($R25,$M$7:$P$17,4,0),0)+1,S24) -> 3 | T25: =MAX(IFERROR(VLOOKUP($R25,$N$7:$P$17,3,0),0)+1,T24) -> 4 | U25: =MAX(IFERROR(VLOOKUP($R25,$O$7:$P$17,2,0),0)+1,U24) -> 4 | W25: =W24+1 -> 18 | X25: =4*$X$3 -> 8800000 | Y25: =8*$X$3 -> 17600000
B26: Gastos Totales | C26: =C23+C25 -> 60000 | F26: Remanente para otros objetivos | G26: 0 | R26: =R25+1 -> 19 | S26: =MAX(IFERROR(VLOOKUP($R26,$M$7:$P$17,4,0),0)+1,S25) -> 3 | T26: =MAX(IFERROR(VLOOKUP($R26,$N$7:$P$17,3,0),0)+1,T25) -> 4 | U26: =MAX(IFERROR(VLOOKUP($R26,$O$7:$P$17,2,0),0)+1,U25) -> 4 | W26: =W25+1 -> 19
F27: Longevidad | G27: =C7+G23 -> 52.916667 | R27: =R26+1 -> 20 | S27: =MAX(IFERROR(VLOOKUP($R27,$M$7:$P$17,4,0),0)+1,S26) -> 3 | T27: =MAX(IFERROR(VLOOKUP($R27,$N$7:$P$17,3,0),0)+1,T26) -> 4 | U27: =MAX(IFERROR(VLOOKUP($R27,$O$7:$P$17,2,0),0)+1,U26) -> 4 | W27: =W26+1 -> 20
B28: Activos Financieros | R28: =R27+1 -> 21 | S28: =MAX(IFERROR(VLOOKUP($R28,$M$7:$P$17,4,0),0)+1,S27) -> 3 | T28: =MAX(IFERROR(VLOOKUP($R28,$N$7:$P$17,3,0),0)+1,T27) -> 4 | U28: =MAX(IFERROR(VLOOKUP($R28,$O$7:$P$17,2,0),0)+1,U27) -> 5 | W28: =W27+1 -> 21 | Z28: =16*$X$3 -> 35200000
B29: Saldo Débito e Inversiones Líquidas | C29: ='Entrevista Patrimonio F.'!L29 -> 200000 | F29: Output 4 (Pensión con Ahorro Financiero para retiro) | R29: =R28+1 -> 22 | S29: =MAX(IFERROR(VLOOKUP($R29,$M$7:$P$17,4,0),0)+1,S28) -> 3 | T29: =MAX(IFERROR(VLOOKUP($R29,$N$7:$P$17,3,0),0)+1,T28) -> 4 | U29: =MAX(IFERROR(VLOOKUP($R29,$O$7:$P$17,2,0),0)+1,U28) -> 5 | W29: =W28+1 -> 22
B30: Saldo otras Inversiones | C30: ='Entrevista Patrimonio F.'!L31 -> 2000000 | F30: Mensualidad Afore | G30: =PMT(1%/12,(FinRecursos-InicioDesacumulacion)*12,((C31*(1+1%/12)^((InicioDesacumulacion-EdadActual)*12))),0,1)*-1 -> 3551.5588 | R30: =R29+1 -> 23 | S30: =MAX(IFERROR(VLOOKUP($R30,$M$7:$P$17,4,0),0)+1,S29) -> 3 | T30: =MAX(IFERROR(VLOOKUP($R30,$N$7:$P$17,3,0),0)+1,T29) -> 4 | U30: =MAX(IFERROR(VLOOKUP($R30,$O$7:$P$17,2,0),0)+1,U29) -> 5 | W30: =W29+1 -> 23
B31: Saldo Afore | C31: ='Entrevista Patrimonio F.'!P38 -> 1000000 | F31: Mensualidad Pensión Voluntaria | G31: =PMT(1%/12,(FinRecursos-InicioDesacumulacion)*12,((SUM(C32:C34)*(1+1%/12)^((InicioDesacumulacion-EdadActual)*12))),0,1)*-1 -> 0 | R31: =R30+1 -> 24 | S31: =MAX(IFERROR(VLOOKUP($R31,$M$7:$P$17,4,0),0)+1,S30) -> 3 | T31: =MAX(IFERROR(VLOOKUP($R31,$N$7:$P$17,3,0),0)+1,T30) -> 5 | U31: =MAX(IFERROR(VLOOKUP($R31,$O$7:$P$17,2,0),0)+1,U30) -> 5 | W31: =W30+1 -> 24 | Y31: =16*$X$3 -> 35200000
B32: Saldo Plan Privado | C32: ='Entrevista Patrimonio F.'!P42 -> 0 | F32: Pension Estimada | G32: =C37 -> 35000 | R32: =R31+1 -> 25 | S32: =MAX(IFERROR(VLOOKUP($R32,$M$7:$P$17,4,0),0)+1,S31) -> 3 | T32: =MAX(IFERROR(VLOOKUP($R32,$N$7:$P$17,3,0),0)+1,T31) -> 5 | U32: =MAX(IFERROR(VLOOKUP($R32,$O$7:$P$17,2,0),0)+1,U31) -> 5 | W32: =W31+1 -> 25
B33: Saldo PPR | C33: ='Entrevista Patrimonio F.'!P40 -> 0 | F33: Mensualidad Actual | G33: =G30+G31+G32 -> 38551.559 | R33: =R32+1 -> 26 | S33: =MAX(IFERROR(VLOOKUP($R33,$M$7:$P$17,4,0),0)+1,S32) -> 3 | T33: =MAX(IFERROR(VLOOKUP($R33,$N$7:$P$17,3,0),0)+1,T32) -> 5 | U33: =MAX(IFERROR(VLOOKUP($R33,$O$7:$P$17,2,0),0)+1,U32) -> 6 | W33: =W32+1 -> 26 | Z33: =32*$X$3 -> 70400000
B34: Saldo en Plan de Seguros de Retiro | C34: ='Entrevista Patrimonio F.'!P44 -> 0 | F34: Grado de Avance | G34: =G33/C13 -> 0.77103118 | R34: =R33+1 -> 27 | S34: =MAX(IFERROR(VLOOKUP($R34,$M$7:$P$17,4,0),0)+1,S33) -> 4 | T34: =MAX(IFERROR(VLOOKUP($R34,$N$7:$P$17,3,0),0)+1,T33) -> 5 | U34: =MAX(IFERROR(VLOOKUP($R34,$O$7:$P$17,2,0),0)+1,U33) -> 6 | W34: =W33+1 -> 27 | X34: =8*$X$3 -> 17600000
B35: Saldo en Plan de Seguros de Acumulación | C35: ='Entrevista Patrimonio F.'!L33 -> 100000 | F35: Saldo en esquemas de retiro | G35: =SUM(C31:C34) -> 1000000 | R35: =R34+1 -> 28 | S35: =MAX(IFERROR(VLOOKUP($R35,$M$7:$P$17,4,0),0)+1,S34) -> 4 | T35: =MAX(IFERROR(VLOOKUP($R35,$N$7:$P$17,3,0),0)+1,T34) -> 5 | U35: =MAX(IFERROR(VLOOKUP($R35,$O$7:$P$17,2,0),0)+1,U34) -> 6 | W35: =W34+1 -> 28
B36: Activos Financieros Totales | C36: =SUM(C29:C35) -> 3300000 | F36: Edad en la que aplica Ley 73 | G36: =YEAR(TODAY())-1997+18 -> 47 | R36: =R35+1 -> 29 | S36: =MAX(IFERROR(VLOOKUP($R36,$M$7:$P$17,4,0),0)+1,S35) -> 4 | T36: =MAX(IFERROR(VLOOKUP($R36,$N$7:$P$17,3,0),0)+1,T35) -> 5 | U36: =MAX(IFERROR(VLOOKUP($R36,$O$7:$P$17,2,0),0)+1,U35) -> 6 | W36: =W35+1 -> 29
B37: Ley 73 | C37: ='Entrevista Patrimonio F.'!P46 -> 35000 | D37: Mensual | R37: =R36+1 -> 30 | S37: =MAX(IFERROR(VLOOKUP($R37,$M$7:$P$17,4,0),0)+1,S36) -> 4 | T37: =MAX(IFERROR(VLOOKUP($R37,$N$7:$P$17,3,0),0)+1,T36) -> 6 | U37: =MAX(IFERROR(VLOOKUP($R37,$O$7:$P$17,2,0),0)+1,U36) -> 6 | W37: =W36+1 -> 30 | Y37: =32*$X$3 -> 70400000
F38: Output 5 Integración fuentes de ingreso (Retiro) | R38: =R37+1 -> 31 | S38: =MAX(IFERROR(VLOOKUP($R38,$M$7:$P$17,4,0),0)+1,S37) -> 4 | T38: =MAX(IFERROR(VLOOKUP($R38,$N$7:$P$17,3,0),0)+1,T37) -> 6 | U38: =MAX(IFERROR(VLOOKUP($R38,$O$7:$P$17,2,0),0)+1,U37) -> 7 | W38: =W37+1 -> 31 | Z38: =64*$X$3 -> 140800000
B39: Ahorro Disponible | F39: Calidad de Vida Retiro | G39: =C13 -> 50000 | R39: =R38+1 -> 32 | S39: =MAX(IFERROR(VLOOKUP($R39,$M$7:$P$17,4,0),0)+1,S38) -> 4 | T39: =MAX(IFERROR(VLOOKUP($R39,$N$7:$P$17,3,0),0)+1,T38) -> 6 | U39: =MAX(IFERROR(VLOOKUP($R39,$O$7:$P$17,2,0),0)+1,U38) -> 7 | W39: =W38+1 -> 32
B40: Ahorro Disponible para el Retiro | C40: ='Patrimonio Financiero'!AI126 -> 0 | D40: Mensual | F40: Propiedades en Renta | G40: =C17 -> 10000 | H40: =G40/$G$39 -> 0.2 | R40: =R39+1 -> 33 | S40: =MAX(IFERROR(VLOOKUP($R40,$M$7:$P$17,4,0),0)+1,S39) -> 4 | T40: =MAX(IFERROR(VLOOKUP($R40,$N$7:$P$17,3,0),0)+1,T39) -> 6 | U40: =MAX(IFERROR(VLOOKUP($R40,$O$7:$P$17,2,0),0)+1,U39) -> 7 | W40: =W39+1 -> 33
F41: Negocio/Dividendos | G41: =C18 -> 0 | H41: =G41/$G$39 -> 0 | R41: =R40+1 -> 34 | S41: =MAX(IFERROR(VLOOKUP($R41,$M$7:$P$17,4,0),0)+1,S40) -> 4 | T41: =MAX(IFERROR(VLOOKUP($R41,$N$7:$P$17,3,0),0)+1,T40) -> 6 | U41: =MAX(IFERROR(VLOOKUP($R41,$O$7:$P$17,2,0),0)+1,U40) -> 7 | W41: =W40+1 -> 34
F42: Esquemas de Pensión | G42: =G33 -> 38551.559 | H42: =G42/$G$39 -> 0.77103118 | R42: =R41+1 -> 35 | S42: =MAX(IFERROR(VLOOKUP($R42,$M$7:$P$17,4,0),0)+1,S41) -> 4 | T42: =MAX(IFERROR(VLOOKUP($R42,$N$7:$P$17,3,0),0)+1,T41) -> 6 | U42: =MAX(IFERROR(VLOOKUP($R42,$O$7:$P$17,2,0),0)+1,U41) -> 7 | W42: =W41+1 -> 35
B43: Seguros | R43: =R42+1 -> 36 | S43: =MAX(IFERROR(VLOOKUP($R43,$M$7:$P$17,4,0),0)+1,S42) -> 5 | T43: =MAX(IFERROR(VLOOKUP($R43,$N$7:$P$17,3,0),0)+1,T42) -> 7 | U43: =MAX(IFERROR(VLOOKUP($R43,$O$7:$P$17,2,0),0)+1,U42) -> 8 | W43: =W42+1 -> 36 | X43: =16*$X$3 -> 35200000 | Y43: =64*$X$3 -> 140800000 | Z43: =128*$X$3 -> 281600000
B44: ¿Tienes seguro de vida actualmente? | C44: ='Entrevista Patrimonio F.'!G54 -> Sí | F44: Mensualidad Actual | G44: =SUM(G40:G42) -> 48551.559 | R44: =R43+1 -> 37 | S44: =MAX(IFERROR(VLOOKUP($R44,$M$7:$P$17,4,0),0)+1,S43) -> 5 | T44: =MAX(IFERROR(VLOOKUP($R44,$N$7:$P$17,3,0),0)+1,T43) -> 7 | U44: =MAX(IFERROR(VLOOKUP($R44,$O$7:$P$17,2,0),0)+1,U43) -> 8 | W44: =W43+1 -> 37
B45: Dependientes Economicos | C45: =IF(C11="No",0,1) -> 1 | F45: Resultado | G45: =IF(G44>=G39,"Excedido","Insuficiente") -> Insuficiente | R45: =R44+1 -> 38 | S45: =MAX(IFERROR(VLOOKUP($R45,$M$7:$P$17,4,0),0)+1,S44) -> 5 | T45: =MAX(IFERROR(VLOOKUP($R45,$N$7:$P$17,3,0),0)+1,T44) -> 7 | U45: =MAX(IFERROR(VLOOKUP($R45,$O$7:$P$17,2,0),0)+1,U44) -> 8 | W45: =W44+1 -> 38
B46: Mayor a 10% | C46: =IF(AND(H10>=0%,H10<=100%),1,0) -> 1 | F46: Pendiente | G46: =IF(G45="Insuficiente",G39-G44,0) -> 1448.4412 | H46: =G46/$G$39 -> 0.028968824 | R46: =R45+1 -> 39 | S46: =MAX(IFERROR(VLOOKUP($R46,$M$7:$P$17,4,0),0)+1,S45) -> 5 | T46: =MAX(IFERROR(VLOOKUP($R46,$N$7:$P$17,3,0),0)+1,T45) -> 7 | U46: =MAX(IFERROR(VLOOKUP($R46,$O$7:$P$17,2,0),0)+1,U45) -> 8 | W46: =W45+1 -> 39
B47: Nivel Riqueza | C47: =G23 -> 2.9166667 | R47: =R46+1 -> 40 | S47: =MAX(IFERROR(VLOOKUP($R47,$M$7:$P$17,4,0),0)+1,S46) -> 5 | T47: =MAX(IFERROR(VLOOKUP($R47,$N$7:$P$17,3,0),0)+1,T46) -> 7 | U47: =MAX(IFERROR(VLOOKUP($R47,$O$7:$P$17,2,0),0)+1,U46) -> 8 | W47: =W46+1 -> 40
B48: Seguro de Vida Costo Anual x Millon | C48: 7000 | F48: Output 6 Índice Patrimonial (Retiro) | G48: VP | H48: VF | R48: =R47+1 -> 41 | S48: =MAX(IFERROR(VLOOKUP($R48,$M$7:$P$17,4,0),0)+1,S47) -> 5 | T48: =MAX(IFERROR(VLOOKUP($R48,$N$7:$P$17,3,0),0)+1,T47) -> 7 | U48: =MAX(IFERROR(VLOOKUP($R48,$O$7:$P$17,2,0),0)+1,U47) -> 9 | W48: =W47+1 -> 41 | Z48: =256*$X$3 -> 563200000
B49: Seguro GMM | C49: No | F49: Pasivo del Retiro | G49: =PV(TasaReal/12,(InicioDesacumulacion-EdadActual)*12,,H49,1)*-1 -> 407492.96 | H49: =G46*(1-(1+TasaReal/12)^(-(FinRecursos-C8)*12))/(TasaReal/12) -> 450330.61 | R49: =R48+1 -> 42 | S49: =MAX(IFERROR(VLOOKUP($R49,$M$7:$P$17,4,0),0)+1,S48) -> 5 | T49: =MAX(IFERROR(VLOOKUP($R49,$N$7:$P$17,3,0),0)+1,T48) -> 8 | U49: =MAX(IFERROR(VLOOKUP($R49,$O$7:$P$17,2,0),0)+1,U48) -> 9 | W49: =W48+1 -> 42 | Y49: =128*$X$3 -> 281600000
B50: Menor a 65 años | C50: =IF(EdadActual<65,1,0) -> 1 | F50: Ahorro Disponible Retiro (Capital Humano) | G50: =PV(TasaReal/12,(InicioDesacumulacion-EdadActual)*12,,H50,1)*-1 -> 0 | H50: =FV(TasaReal/12,(C8-C7)*12,-C40,,0) -> 0 | R50: =R49+1 -> 43 | S50: =MAX(IFERROR(VLOOKUP($R50,$M$7:$P$17,4,0),0)+1,S49) -> 5 | T50: =MAX(IFERROR(VLOOKUP($R50,$N$7:$P$17,3,0),0)+1,T49) -> 8 | U50: =MAX(IFERROR(VLOOKUP($R50,$O$7:$P$17,2,0),0)+1,U49) -> 9 | W50: =W49+1 -> 43
B51: Nivel Riqueza | C51: =C47 -> 2.9166667 | F51: Patrimonio Financiero (Aumulación) | G51: =SUM(C29:C30,C35) -> 2300000 | H51: =(G51*(1+TasaReal/12)^((InicioDesacumulacion-EdadActual)*12)) -> 2541787.3 | R51: =R50+1 -> 44 | S51: =MAX(IFERROR(VLOOKUP($R51,$M$7:$P$17,4,0),0)+1,S50) -> 5 | T51: =MAX(IFERROR(VLOOKUP($R51,$N$7:$P$17,3,0),0)+1,T50) -> 8 | U51: =MAX(IFERROR(VLOOKUP($R51,$O$7:$P$17,2,0),0)+1,U50) -> 9 | W51: =W50+1 -> 44
B52: Cobertura Sugerida | C52: =IF(C51<3,3-C51,5)*C50 -> 0.083333333 | F52: Activos Financieros + Capital Humano | G52: =G50+G51 -> 2300000 | H52: =(G52*(1+TasaReal/12)^((InicioDesacumulacion-EdadActual)*12)) -> 2541787.3 | R52: =R51+1 -> 45 | S52: =MAX(IFERROR(VLOOKUP($R52,$M$7:$P$17,4,0),0)+1,S51) -> 6 | T52: =MAX(IFERROR(VLOOKUP($R52,$N$7:$P$17,3,0),0)+1,T51) -> 8 | U52: =MAX(IFERROR(VLOOKUP($R52,$O$7:$P$17,2,0),0)+1,U51) -> 9 | W52: =W51+1 -> 45 | X52: =32*$X$3 -> 70400000
B53: Monto Cobertura Sugerida | C53: =C52*C26*12 -> 60000 | F53: Deficit/Superavit | G53: =G52-G49 -> 1892507 | H53: =+H52-H49 -> 2091456.6 | R53: =R52+1 -> 46 | S53: =MAX(IFERROR(VLOOKUP($R53,$M$7:$P$17,4,0),0)+1,S52) -> 6 | T53: =MAX(IFERROR(VLOOKUP($R53,$N$7:$P$17,3,0),0)+1,T52) -> 8 | U53: =MAX(IFERROR(VLOOKUP($R53,$O$7:$P$17,2,0),0)+1,U52) -> 10 | W53: =W52+1 -> 46 | Z53: =512*$X$3 -> 1126400000
B54: Seguro de Propiedad | C54: ='Entrevista Patrimonio F.'!G56 -> No | F54: Ahorro mensual para cubrir deficit | G54: =IF(PMT((TasaReal/12),12*(C8-C7),G51*-1,H49,0)*-1<0,0,PMT((TasaReal/12),12*(C8-C7),G51*-1,H49,0)*-1) -> 0 | R54: =R53+1 -> 47 | S54: =MAX(IFERROR(VLOOKUP($R54,$M$7:$P$17,4,0),0)+1,S53) -> 6 | T54: =MAX(IFERROR(VLOOKUP($R54,$N$7:$P$17,3,0),0)+1,T53) -> 8 | U54: =MAX(IFERROR(VLOOKUP($R54,$O$7:$P$17,2,0),0)+1,U53) -> 10 | W54: =W53+1 -> 47
B55: Propiedades Aseguradas | C55: =IF(C54="Sí",0,1) -> 1 | R55: =R54+1 -> 48 | S55: =MAX(IFERROR(VLOOKUP($R55,$M$7:$P$17,4,0),0)+1,S54) -> 6 | T55: =MAX(IFERROR(VLOOKUP($R55,$N$7:$P$17,3,0),0)+1,T54) -> 9 | U55: =MAX(IFERROR(VLOOKUP($R55,$O$7:$P$17,2,0),0)+1,U54) -> 10 | W55: =W54+1 -> 48 | Y55: =256*$X$3 -> 563200000
F56: Output 5 Integración fuentes de ingreso (Retiro) | G56: =C13 -> 50000 | R56: =R55+1 -> 49 | S56: =MAX(IFERROR(VLOOKUP($R56,$M$7:$P$17,4,0),0)+1,S55) -> 6 | T56: =MAX(IFERROR(VLOOKUP($R56,$N$7:$P$17,3,0),0)+1,T55) -> 9 | U56: =MAX(IFERROR(VLOOKUP($R56,$O$7:$P$17,2,0),0)+1,U55) -> 10 | W56: =W55+1 -> 49
F57: Propiedades en Renta | G57: =C17 -> 10000 | H57: =G57/$G$39 -> 0.2 | R57: =R56+1 -> 50 | S57: =MAX(IFERROR(VLOOKUP($R57,$M$7:$P$17,4,0),0)+1,S56) -> 6 | T57: =MAX(IFERROR(VLOOKUP($R57,$N$7:$P$17,3,0),0)+1,T56) -> 9 | U57: =MAX(IFERROR(VLOOKUP($R57,$O$7:$P$17,2,0),0)+1,U56) -> 10 | W57: =W56+1 -> 50
F58: Negocio/Dividendos | G58: =C18 -> 0 | H58: =G58/$G$39 -> 0 | R58: =R57+1 -> 51 | S58: =MAX(IFERROR(VLOOKUP($R58,$M$7:$P$17,4,0),0)+1,S57) -> 6 | T58: =MAX(IFERROR(VLOOKUP($R58,$N$7:$P$17,3,0),0)+1,T57) -> 9 | U58: =MAX(IFERROR(VLOOKUP($R58,$O$7:$P$17,2,0),0)+1,U57) -> 11 | W58: =W57+1 -> 51 | Z58: =1024*$X$3 -> 2252800000
F59: Indice Patrimonial (Gastos basicos) | G59: =G44 -> 48551.559 | H59: =G59/$G$39 -> 0.97103118 | R59: =R58+1 -> 52 | S59: =MAX(IFERROR(VLOOKUP($R59,$M$7:$P$17,4,0),0)+1,S58) -> 6 | T59: =MAX(IFERROR(VLOOKUP($R59,$N$7:$P$17,3,0),0)+1,T58) -> 9 | U59: =MAX(IFERROR(VLOOKUP($R59,$O$7:$P$17,2,0),0)+1,U58) -> 11 | W59: =W58+1 -> 52
F60: Mensualidad Estimada | G60: =SUM(G57:G59) -> 58551.559 | R60: =R59+1 -> 53 | S60: =MAX(IFERROR(VLOOKUP($R60,$M$7:$P$17,4,0),0)+1,S59) -> 6 | T60: =MAX(IFERROR(VLOOKUP($R60,$N$7:$P$17,3,0),0)+1,T59) -> 9 | U60: =MAX(IFERROR(VLOOKUP($R60,$O$7:$P$17,2,0),0)+1,U59) -> 11 | W60: =W59+1 -> 53
F61: Resultado | G61: =IF(G60>=G56,"Excedido","Insuficiente") -> Excedido | R61: =R60+1 -> 54 | S61: =MAX(IFERROR(VLOOKUP($R61,$M$7:$P$17,4,0),0)+1,S60) -> 7 | T61: =MAX(IFERROR(VLOOKUP($R61,$N$7:$P$17,3,0),0)+1,T60) -> 10 | U61: =MAX(IFERROR(VLOOKUP($R61,$O$7:$P$17,2,0),0)+1,U60) -> 11 | W61: =W60+1 -> 54 | X61: =64*$X$3 -> 140800000 | Y61: =512*$X$3 -> 1126400000
F62: Pendiente | G62: =IF(G61="Insuficiente",G56-G60,0) -> 0 | H62: =G62/$G$39 -> 0 | R62: =R61+1 -> 55 | S62: =MAX(IFERROR(VLOOKUP($R62,$M$7:$P$17,4,0),0)+1,S61) -> 7 | T62: =MAX(IFERROR(VLOOKUP($R62,$N$7:$P$17,3,0),0)+1,T61) -> 10 | U62: =MAX(IFERROR(VLOOKUP($R62,$O$7:$P$17,2,0),0)+1,U61) -> 11 | W62: =W61+1 -> 55
F65: Output 7 Seguros
F66: Cobertura Sugerida | G66: =MAX(IF(C47<3,3-C47,5-C47)*C45*C46,0) -> 0.083333333 | H66: Gastos
F67: Monto de Cobertura Sugerido | G67: =G66*C26*12 -> 60000
F68: Seguro de Vida Costo Anual | G68: =(G67*C48)/1000000 -> 420 | H68: =IF(C44="No","Contratación","Extensión") -> Extensión
F69: SGMM | G69: TBD
F70: Seguro de Hogar | G70: =((100*C17/5)*12)*C55 -> 2400000 | H70: Suma Asegurada
F71: Dotal Salud | G71: =C60*2224556/10000 -> 0
F72: Aportación Mensual

Sheet Desacumulación
D2: Inputs | G2: Resultados
B3: Tasa | D3: ='Cálculos y Supuestos Edo.Res'!C4 -> 0.01 | G3: Ahorro Inicio de Aportaciones (M) | I3: =IF(D7=0,"N/A",SUMIFS(C20:AOP20,C17:AOP17,D8,C18:AOP18,1)) -> N/A
B4: Saldos Esquemas de Pensión Actual | D4: 0 | G4: Ahorro Inicio de Jubilación | I4: =SUMIFS(C20:AOP20,C17:AOP17,D9,C18:AOP18,1)+SUMIFS(C21:AOP21,C17:AOP17,D9,C18:AOP18,1) -> 2541787.3
B5: Saldos Patrimonio Actual | D5: ='Cálculos y Supuestos Edo.Res'!G51 -> 2300000 | G5: Años de Jubilación | I5: =(D10-D9) -> 30
B6: Edad Actual | D6: =EdadActual -> 50 | G6: Meses de Jubilación | I6: =I5*12 -> 360
B7: Aportaciones (M) | D7: ='Cálculos y Supuestos Edo.Res'!C40 -> 0 | E7: Azul si aportaciones = 0 | G7: Mensualidad Deseada | I7: ='Cálculos y Supuestos Edo.Res'!G46 -> 1448.4412
B8: Edad Inicio de Aportaciones (M) | D8: =EdadActual -> 50 | E8: Azul si aportaciones = 0 | G8: Mensualidades Retiro | I8: =PMT(($D$3/12),I6,I4,0,0)*-1 -> 8175.3924 | J8: Rojo < Mensualidad Deseada | Verde > Mensualidad Deseada
B9: Edad Inicio de Retiro | D9: =InicioDesacumulacion -> 60 | E9: Max = Edad de Defunción
B10: Edad Defunción | D10: =FinRecursos -> 90 | E10: Min = Edad de Retiro | Max = 90 | RC10: 40 | ADC10: .
B14: Aportación Inicial | C14: =IF(AND(C18=1,C17=$D$6),"Aportación Inicial","-") -> - | D14: =IF(AND(D18=1,D17=$D$6),"Aportación Inicial","-") -> - | E14: =IF(AND(E18=1,E17=$D$6),"Aportación Inicial","-") -> - | F14: =IF(AND(F18=1,F17=$D$6),"Aportación Inicial","-") -> - | G14: =IF(AND(G18=1,G17=$D$6),"Aportación Inicial","-") -> - | H14: =IF(AND(H18=1,H17=$D$6),"Aportación Inicial","-") -> - | I14: =IF(AND(I18=1,I17=$D$6),"Aportación Inicial","-") -> - | J14: =IF(AND(J18=1,J17=$D$6),"Aportación Inicial","-") -> - | ... AOP14: =IF(AND(AOP18=1,AOP17=$D$6),"Aportación Inicial","-") -> -
B15: Acumulación | C15: =IF(AND(IF(C17>=$D$8,1,0),IF(C17<$D$9,1,0)),"Acumulación","-") -> - | D15: =IF(AND(IF(D17>=$D$8,1,0),IF(D17<$D$9,1,0)),"Acumulación","-") -> - | E15: =IF(AND(IF(E17>=$D$8,1,0),IF(E17<$D$9,1,0)),"Acumulación","-") -> - | F15: =IF(AND(IF(F17>=$D$8,1,0),IF(F17<$D$9,1,0)),"Acumulación","-") -> - | G15: =IF(AND(IF(G17>=$D$8,1,0),IF(G17<$D$9,1,0)),"Acumulación","-") -> - | H15: =IF(AND(IF(H17>=$D$8,1,0),IF(H17<$D$9,1,0)),"Acumulación","-") -> - | I15: =IF(AND(IF(I17>=$D$8,1,0),IF(I17<$D$9,1,0)),"Acumulación","-") -> - | J15: =IF(AND(IF(J17>=$D$8,1,0),IF(J17<$D$9,1,0)),"Acumulación","-") -> - | ... AOP15: =IF(AND(IF(AOP17>=$D$8,1,0),IF(AOP17<$D$9,1,0)),"Acumulación","-") -> -
B16: Desacumulación | C16: =IF(AND(C17>=$D$9,C17<$D$10),"Desacumulación","-") -> - | D16: =IF(AND(D17>=$D$9,D17<$D$10),"Desacumulación","-") -> - | E16: =IF(AND(E17>=$D$9,E17<$D$10),"Desacumulación","-") -> - | F16: =IF(AND(F17>=$D$9,F17<$D$10),"Desacumulación","-") -> - | G16: =IF(AND(G17>=$D$9,G17<$D$10),"Desacumulación","-") -> - | H16: =IF(AND(H17>=$D$9,H17<$D$10),"Desacumulación","-") -> - | I16: =IF(AND(I17>=$D$9,I17<$D$10),"Desacumulación","-") -> - | J16: =IF(AND(J17>=$D$9,J17<$D$10),"Desacumulación","-") -> - | ... AOP16: =IF(AND(AOP17>=$D$9,AOP17<$D$10),"Desacumulación","-") -> -
B17: Edad | C17: 1 | D17: =C17 -> 1 | E17: =D17 -> 1 | F17: =E17 -> 1 | G17: =F17 -> 1 | H17: =G17 -> 1 | I17: =H17 -> 1 | J17: =I17 -> 1 | K17: =J17 -> 1 | ... N17: =M17 -> 1 | O17: =C17+1 -> 2 | P17: =D17+1 -> 2 | Q17: =E17+1 -> 2 | R17: =F17+1 -> 2 | S17: =G17+1 -> 2 | T17: =H17+1 -> 2 | U17: =I17+1 -> 2 | V17: =J17+1 -> 2 | ... AOP17: =AOD17+1 -> 90
B18: Mes | C18: 1 | D18: =C18+1 -> 2 | E18: =D18+1 -> 3 | F18: =E18+1 -> 4 | G18: =F18+1 -> 5 | H18: =G18+1 -> 6 | I18: =H18+1 -> 7 | J18: =I18+1 -> 8 | K18: =J18+1 -> 9 | ... N18: =M18+1 -> 12 | O18: =C18 -> 1 | P18: =D18 -> 2 | Q18: =E18 -> 3 | R18: =F18 -> 4 | S18: =G18 -> 5 | T18: =H18 -> 6 | U18: =I18 -> 7 | V18: =J18 -> 8 | ... AOP18: =AOD18 -> 12
B20: Saldo Inicial | C20: 0 | D20: =C25 -> 0 | E20: =D25 -> 0 | F20: =E25 -> 0 | G20: =F25 -> 0 | H20: =G25 -> 0 | I20: =H25 -> 0 | J20: =I25 -> 0 | K20: =J25 -> 0 | ... AOP20: =AOO25 -> 2848291.2
B21: Aportación Inicial | C21: =IF(C14="Aportación Inicial",$D$5+$D$4,0) -> 0 | D21: =IF(D14="Aportación Inicial",$D$5+$D$4,0) -> 0 | E21: =IF(E14="Aportación Inicial",$D$5+$D$4,0) -> 0 | F21: =IF(F14="Aportación Inicial",$D$5+$D$4,0) -> 0 | G21: =IF(G14="Aportación Inicial",$D$5+$D$4,0) -> 0 | H21: =IF(H14="Aportación Inicial",$D$5+$D$4,0) -> 0 | I21: =IF(I14="Aportación Inicial",$D$5+$D$4,0) -> 0 | J21: =IF(J14="Aportación Inicial",$D$5+$D$4,0) -> 0 | ... AOP21: =IF(AOP14="Aportación Inicial",$D$5+$D$4,0) -> 0
B22: Aportaciones Mensuales | C22: =IF(C15="Acumulación",$D$7,0) -> 0 | D22: =IF(D15="Acumulación",$D$7,0) -> 0 | E22: =IF(E15="Acumulación",$D$7,0) -> 0 | F22: =IF(F15="Acumulación",$D$7,0) -> 0 | G22: =IF(G15="Acumulación",$D$7,0) -> 0 | H22: =IF(H15="Acumulación",$D$7,0) -> 0 | I22: =IF(I15="Acumulación",$D$7,0) -> 0 | J22: =IF(J15="Acumulación",$D$7,0) -> 0 | ... AOP22: =IF(AOP15="Acumulación",$D$7,0) -> 0
B23: Mensualidad Retiro | C23: =IF(C16="Desacumulación",$I$7,0) -> 0 | D23: =IF(D16="Desacumulación",$I$7,0) -> 0 | E23: =IF(E16="Desacumulación",$I$7,0) -> 0 | F23: =IF(F16="Desacumulación",$I$7,0) -> 0 | G23: =IF(G16="Desacumulación",$I$7,0) -> 0 | H23: =IF(H16="Desacumulación",$I$7,0) -> 0 | I23: =IF(I16="Desacumulación",$I$7,0) -> 0 | J23: =IF(J16="Desacumulación",$I$7,0) -> 0 | ... AOP23: =IF(AOP16="Desacumulación",$I$7,0) -> 0
B24: Intereses | C24: =(C20+C21-C23)*($D$3/12) -> 0 | D24: =(D20+D21-D23)*($D$3/12) -> 0 | E24: =(E20+E21-E23)*($D$3/12) -> 0 | F24: =(F20+F21-F23)*($D$3/12) -> 0 | G24: =(G20+G21-G23)*($D$3/12) -> 0 | H24: =(H20+H21-H23)*($D$3/12) -> 0 | I24: =(I20+I21-I23)*($D$3/12) -> 0 | J24: =(J20+J21-J23)*($D$3/12) -> 0 | ... AOP24: =(AOP20+AOP21-AOP23)*($D$3/12) -> 2373.576
B25: Saldo Final | C25: =IF(AND(C16="Desacumulación",D16="-"),ROUND(C20+C21+C22-C23+C24,2),C20+C21+C22-C23+C24) -> 0 | D25: =IF(AND(D16="Desacumulación",E16="-"),ROUND(D20+D21+D22-D23+D24,2),D20+D21+D22-D23+D24) -> 0 | E25: =IF(AND(E16="Desacumulación",F16="-"),ROUND(E20+E21+E22-E23+E24,2),E20+E21+E22-E23+E24) -> 0 | F25: =IF(AND(F16="Desacumulación",G16="-"),ROUND(F20+F21+F22-F23+F24,2),F20+F21+F22-F23+F24) -> 0 | G25: =IF(AND(G16="Desacumulación",H16="-"),ROUND(G20+G21+G22-G23+G24,2),G20+G21+G22-G23+G24) -> 0 | H25: =IF(AND(H16="Desacumulación",I16="-"),ROUND(H20+H21+H22-H23+H24,2),H20+H21+H22-H23+H24) -> 0 | I25: =IF(AND(I16="Desacumulación",J16="-"),ROUND(I20+I21+I22-I23+I24,2),I20+I21+I22-I23+I24) -> 0 | J25: =IF(AND(J16="Desacumulación",K16="-"),ROUND(J20+J21+J22-J23+J24,2),J20+J21+J22-J23+J24) -> 0 | ... AOP25: =IF(AND(AOP16="Desacumulación",AOQ16="-"),ROUND(AOP20+AOP21+AOP22-AOP23+AOP24,2),AOP20+AOP21+AOP22-AOP23+AOP24) -> 2850664.8
B28: Gráficas
B30: Desacumulación
C31: 12 | D31: 12 | E31: 12 | F31: 12 | G31: 12 | H31: 12 | I31: 12 | J31: 12 | K31: 12 | L31: 12 | M31: 12 | N31: 12 | O31: 12 | P31: 12 | Q31: 12 | R31: 12 | S31: 12 | T31: 12 | U31: 12 | V31: 12 | W31: 12 | X31: 12 | Y31: 12 | Z31: 12 | AA31: 12
B32: Edad | C32: =Desacumulación!D9 -> 60 | D32: =IFERROR(IF(C32+1>=Desacumulación!$D$10,"",C32+1),"") -> 61 | E32: =IFERROR(IF(D32+1>=Desacumulación!$D$10,"",D32+1),"") -> 62 | F32: =IFERROR(IF(E32+1>=Desacumulación!$D$10,"",E32+1),"") -> 63 | G32: =IFERROR(IF(F32+1>=Desacumulación!$D$10,"",F32+1),"") -> 64 | H32: =IFERROR(IF(G32+1>=Desacumulación!$D$10,"",G32+1),"") -> 65 | I32: =IFERROR(IF(H32+1>=Desacumulación!$D$10,"",H32+1),"") -> 66 | J32: =IFERROR(IF(I32+1>=Desacumulación!$D$10,"",I32+1),"") -> 67 | K32: =IFERROR(IF(J32+1>=Desacumulación!$D$10,"",J32+1),"") -> 68 | ... AA32: =IFERROR(IF(Z32+1>=Desacumulación!$D$10,"",Z32+1),"") -> 84
B33: Saldo Inicial | C33: =Desacumulación!I4 -> 2541787.3 | D33: =IF(D32="","",C34) -> 2549846.2 | E33: =IF(E32="","",D34) -> 2557986.1 | F33: =IF(F32="","",E34) -> 2566207.8 | G33: =IF(G32="","",F34) -> 2574512.1 | H33: =IF(H32="","",G34) -> 2582899.9 | I33: =IF(I32="","",H34) -> 2591371.8 | J33: =IF(J32="","",I34) -> 2599928.9 | K33: =IF(K32="","",J34) -> 2608572 | ... AA33: =IF(AA32="","",Z34) -> 2759283.9
B34: Saldo Final | C34: =IF(C32="","",SUMIFS(Desacumulación!$C$25:$AOP$25,Desacumulación!$C$17:$AOP$17,C32,Desacumulación!$C$18:$AOP$18,C31)) -> 2549846.2 | D34: =IF(D32="","",SUMIFS(Desacumulación!$C$25:$AOP$25,Desacumulación!$C$17:$AOP$17,D32,Desacumulación!$C$18:$AOP$18,D31)) -> 2557986.1 | E34: =IF(E32="","",SUMIFS(Desacumulación!$C$25:$AOP$25,Desacumulación!$C$17:$AOP$17,E32,Desacumulación!$C$18:$AOP$18,E31)) -> 2566207.8 | F34: =IF(F32="","",SUMIFS(Desacumulación!$C$25:$AOP$25,Desacumulación!$C$17:$AOP$17,F32,Desacumulación!$C$18:$AOP$18,F31)) -> 2574512.1 | G34: =IF(G32="","",SUMIFS(Desacumulación!$C$25:$AOP$25,Desacumulación!$C$17:$AOP$17,G32,Desacumulación!$C$18:$AOP$18,G31)) -> 2582899.9 | H34: =IF(H32="","",SUMIFS(Desacumulación!$C$25:$AOP$25,Desacumulación!$C$17:$AOP$17,H32,Desacumulación!$C$18:$AOP$18,H31)) -> 2591371.8 | I34: =IF(I32="","",SUMIFS(Desacumulación!$C$25:$AOP$25,Desacumulación!$C$17:$AOP$17,I32,Desacumulación!$C$18:$AOP$18,I31)) -> 2599928.9 | J34: =IF(J32="","",SUMIFS(Desacumulación!$C$25:$AOP$25,Desacumulación!$C$17:$AOP$17,J32,Desacumulación!$C$18:$AOP$18,J31)) -> 2608572 | ... AA34: =IF(AA32="","",SUMIFS(Desacumulación!$C$25:$AOP$25,Desacumulación!$C$17:$AOP$17,AA32,Desacumulación!$C$18:$AOP$18,AA31)) -> 2769527.9

Sheet Objetivos
C2: Inputs | F2: Resultados
B3: Tasa | C3: ='Cálculos y Supuestos Edo.Res'!C4 -> 0.01 | F3: Ahorro Inicio de Aportaciones (M) | H3: =IF(C7=0,"N/A",SUMIFS(D20:AOQ20,D15:AOQ15,C8,D16:AOQ16,1)) -> 0
B4: Aportación Inicial | C4: ='Patrimonio Financiero'!AP200 -> 400000 | F4: Ahorro Inicio de Jubilación | H4: =SUMIFS(D20:AOQ20,D15:AOQ15,C9,D16:AOQ16,1)+SUMIFS(D21:AOQ21,D15:AOQ15,C9,D16:AOQ16,1) -> 1774127.4
B5: Edad de Aportación Inicial | C5: =EdadActual -> 50 | F5: Años de Jubilación | H5: =(C10-C9) -> 30
B6: Aportaciones (A) | C6: ='Patrimonio Financiero'!AP196 -> 150000 | F6: Meses de Jubilación | H6: =H5*12 -> 360
B7: Aportaciones (M) | C7: ='Patrimonio Financiero'!AE196 -> 15000 | D7: Azul si aportaciones = 0 | F7: Mensualidad Deseada | H7: ='Cálculos y Supuestos Edo.Res'!G46 -> 1448.4412
B8: Edad Inicio de Aportaciones (M) | C8: =EdadActual -> 50 | D8: Azul si aportaciones = 0 | F8: Mensualidades Retiro | H8: =PMT(($C$3/12),H6,H4,0,1)*-1 -> 5701.5436 | I8: Rojo < Mensualidad Deseada | Verde > Mensualidad Deseada
B9: Edad Inicio de Retiro | C9: =InicioDesacumulacion -> 60 | D9: Max = Edad de Defunción
B10: Edad Defunción | C10: =FinRecursos -> 90 | D10: Min = Edad de Retiro | Max = 90 | F10: Ahorro Fecha de Defunción | H10: =AOE25 -> 2394522.3
RD11: 40 | ADD11: .
B12: Aportación Inicial | D12: =IF(AND(D16=1,D15=$C$5),"Aportación Inicial","-") -> - | E12: =IF(AND(E16=1,E15=$C$5),"Aportación Inicial","-") -> - | F12: =IF(AND(F16=1,F15=$C$5),"Aportación Inicial","-") -> - | G12: =IF(AND(G16=1,G15=$C$5),"Aportación Inicial","-") -> - | H12: =IF(AND(H16=1,H15=$C$5),"Aportación Inicial","-") -> - | I12: =IF(AND(I16=1,I15=$C$5),"Aportación Inicial","-") -> - | J12: =IF(AND(J16=1,J15=$C$5),"Aportación Inicial","-") -> - | K12: =IF(AND(K16=1,K15=$C$5),"Aportación Inicial","-") -> - | ... AOQ12: =IF(AND(AOQ16=1,AOQ15=$C$5),"Aportación Inicial","-") -> -
B13: Acumulación | D13: =IF(AND(IF(D15>=$C$8,1,0),IF(D15<$C$9,1,0)),"Acumulación","-") -> - | E13: =IF(AND(IF(E15>=$C$8,1,0),IF(E15<$C$9,1,0)),"Acumulación","-") -> - | F13: =IF(AND(IF(F15>=$C$8,1,0),IF(F15<$C$9,1,0)),"Acumulación","-") -> - | G13: =IF(AND(IF(G15>=$C$8,1,0),IF(G15<$C$9,1,0)),"Acumulación","-") -> - | H13: =IF(AND(IF(H15>=$C$8,1,0),IF(H15<$C$9,1,0)),"Acumulación","-") -> - | I13: =IF(AND(IF(I15>=$C$8,1,0),IF(I15<$C$9,1,0)),"Acumulación","-") -> - | J13: =IF(AND(IF(J15>=$C$8,1,0),IF(J15<$C$9,1,0)),"Acumulación","-") -> - | K13: =IF(AND(IF(K15>=$C$8,1,0),IF(K15<$C$9,1,0)),"Acumulación","-") -> - | ... AOQ13: =IF(AND(IF(AOQ15>=$C$8,1,0),IF(AOQ15<$C$9,1,0)),"Acumulación","-") -> -
B14: Desacumulación | D14: =IF(AND(D15>=$C$9,D15<$C$10),"Desacumulación","-") -> - | E14: =IF(AND(E15>=$C$9,E15<$C$10),"Desacumulación","-") -> - | F14: =IF(AND(F15>=$C$9,F15<$C$10),"Desacumulación","-") -> - | G14: =IF(AND(G15>=$C$9,G15<$C$10),"Desacumulación","-") -> - | H14: =IF(AND(H15>=$C$9,H15<$C$10),"Desacumulación","-") -> - | I14: =IF(AND(I15>=$C$9,I15<$C$10),"Desacumulación","-") -> - | J14: =IF(AND(J15>=$C$9,J15<$C$10),"Desacumulación","-") -> - | K14: =IF(AND(K15>=$C$9,K15<$C$10),"Desacumulación","-") -> - | ... AOQ14: =IF(AND(AOQ15>=$C$9,AOQ15<$C$10),"Desacumulación","-") -> -
B15: Edad | D15: 1 | E15: =D15 -> 1 | F15: =E15 -> 1 | G15: =F15 -> 1 | H15: =G15 -> 1 | I15: =H15 -> 1 | J15: =I15 -> 1 | K15: =J15 -> 1 | L15: =K15 -> 1 | ... O15: =N15 -> 1 | P15: =D15+1 -> 2 | Q15: =E15+1 -> 2 | R15: =F15+1 -> 2 | S15: =G15+1 -> 2 | T15: =H15+1 -> 2 | U15: =I15+1 -> 2 | V15: =J15+1 -> 2 | W15: =K15+1 -> 2 | ... AOQ15: =AOE15+1 -> 90
B16: Mes | D16: 1 | E16: =D16+1 -> 2 | F16: =E16+1 -> 3 | G16: =F16+1 -> 4 | H16: =G16+1 -> 5 | I16: =H16+1 -> 6 | J16: =I16+1 -> 7 | K16: =J16+1 -> 8 | L16: =K16+1 -> 9 | ... O16: =N16+1 -> 12 | P16: =D16 -> 1 | Q16: =E16 -> 2 | R16: =F16 -> 3 | S16: =G16 -> 4 | T16: =H16 -> 5 | U16: =I16 -> 6 | V16: =J16 -> 7 | W16: =K16 -> 8 | ... AOQ16: =AOE16 -> 12
B17: Contador | D17: 1 | E17: =D17+1 -> 2 | F17: =E17+1 -> 3 | G17: =F17+1 -> 4 | H17: =G17+1 -> 5 | I17: =H17+1 -> 6 | J17: =I17+1 -> 7 | K17: =J17+1 -> 8 | L17: =K17+1 -> 9 | ... AOQ17: =AOP17+1 -> 1080
B18: Objetivos | D18: =IF(D15>=$C$5,1,0) -> 0 | E18: =IF(E15>=$C$5,1,0) -> 0 | F18: =IF(F15>=$C$5,1,0) -> 0 | G18: =IF(G15>=$C$5,1,0) -> 0 | H18: =IF(H15>=$C$5,1,0) -> 0 | I18: =IF(I15>=$C$5,1,0) -> 0 | J18: =IF(J15>=$C$5,1,0) -> 0 | K18: =IF(K15>=$C$5,1,0) -> 0 | ... AOQ18: =IF(AOQ15>=$C$5,1,0) -> 1
B20: Saldo Inicial | D20: 0 | E20: =D25 -> 0 | F20: =E25 -> 0 | G20: =F25 -> 0 | H20: =G25 -> 0 | I20: =H25 -> 0 | J20: =I25 -> 0 | K20: =J25 -> 0 | L20: =K25 -> 0 | ... AOQ20: =AOP25 -> 2416563.8
B21: Aportación Inicial | D21: =IF(D12="Aportación Inicial",$C$4,0) -> 0 | E21: =IF(E12="Aportación Inicial",$C$4,0) -> 0 | F21: =IF(F12="Aportación Inicial",$C$4,0) -> 0 | G21: =IF(G12="Aportación Inicial",$C$4,0) -> 0 | H21: =IF(H12="Aportación Inicial",$C$4,0) -> 0 | I21: =IF(I12="Aportación Inicial",$C$4,0) -> 0 | J21: =IF(J12="Aportación Inicial",$C$4,0) -> 0 | K21: =IF(K12="Aportación Inicial",$C$4,0) -> 0 | ... AOQ21: =IF(AOQ12="Aportación Inicial",$C$4,0) -> 0
B22: Aportaciones Mensuales | D22: =IF(D13="Acumulación",$C$7,0)++IF(AND(D13="Acumulación",D16=1),$C$6,0) -> 0 | E22: =IF(E13="Acumulación",$C$7,0)++IF(AND(E13="Acumulación",E16=1),$C$6,0) -> 0 | F22: =IF(F13="Acumulación",$C$7,0)++IF(AND(F13="Acumulación",F16=1),$C$6,0) -> 0 | G22: =IF(G13="Acumulación",$C$7,0)++IF(AND(G13="Acumulación",G16=1),$C$6,0) -> 0 | H22: =IF(H13="Acumulación",$C$7,0)++IF(AND(H13="Acumulación",H16=1),$C$6,0) -> 0 | I22: =IF(I13="Acumulación",$C$7,0)++IF(AND(I13="Acumulación",I16=1),$C$6,0) -> 0 | J22: =IF(J13="Acumulación",$C$7,0)++IF(AND(J13="Acumulación",J16=1),$C$6,0) -> 0 | K22: =IF(K13="Acumulación",$C$7,0)++IF(AND(K13="Acumulación",K16=1),$C$6,0) -> 0 | ... AOQ22: =IF(AOQ13="Acumulación",$C$7,0)++IF(AND(AOQ13="Acumulación",AOQ16=1),$C$6,0) -> 0
B23: Retiros de Objetivos | D23: =D28+D35+D42+D49+D56 -> 0 | E23: =E28+E35+E42+E49+E56 -> 0 | F23: =F28+F35+F42+F49+F56 -> 0 | G23: =G28+G35+G42+G49+G56 -> 0 | H23: =H28+H35+H42+H49+H56 -> 0 | I23: =I28+I35+I42+I49+I56 -> 0 | J23: =J28+J35+J42+J49+J56 -> 0 | K23: =K28+K35+K42+K49+K56 -> 0 | ... AOQ23: =AOQ28+AOQ35+AOQ42+AOQ49+AOQ56 -> 0
B24: Intereses | D24: =(D20+D21+D22-D23)*($C$3/12) -> 0 | E24: =(E20+E21+E22-E23)*($C$3/12) -> 0 | F24: =(F20+F21+F22-F23)*($C$3/12) -> 0 | G24: =(G20+G21+G22-G23)*($C$3/12) -> 0 | H24: =(H20+H21+H22-H23)*($C$3/12) -> 0 | I24: =(I20+I21+I22-I23)*($C$3/12) -> 0 | J24: =(J20+J21+J22-J23)*($C$3/12) -> 0 | K24: =(K20+K21+K22-K23)*($C$3/12) -> 0 | ... AOQ24: =(AOQ20+AOQ21+AOQ22-AOQ23)*($C$3/12) -> 2013.8032
B25: Saldo Final | D25: =IF(AND(D14="Desacumulación",E14="-"),ROUND(D20+D21+D22-D23+D24,2),D20+D21+D22-D23+D24) -> 0 | E25: =IF(AND(E14="Desacumulación",F14="-"),ROUND(E20+E21+E22-E23+E24,2),E20+E21+E22-E23+E24) -> 0 | F25: =IF(AND(F14="Desacumulación",G14="-"),ROUND(F20+F21+F22-F23+F24,2),F20+F21+F22-F23+F24) -> 0 | G25: =IF(AND(G14="Desacumulación",H14="-"),ROUND(G20+G21+G22-G23+G24,2),G20+G21+G22-G23+G24) -> 0 | H25: =IF(AND(H14="Desacumulación",I14="-"),ROUND(H20+H21+H22-H23+H24,2),H20+H21+H22-H23+H24) -> 0 | I25: =IF(AND(I14="Desacumulación",J14="-"),ROUND(I20+I21+I22-I23+I24,2),I20+I21+I22-I23+I24) -> 0 | J25: =IF(AND(J14="Desacumulación",K14="-"),ROUND(J20+J21+J22-J23+J24,2),J20+J21+J22-J23+J24) -> 0 | K25: =IF(AND(K14="Desacumulación",L14="-"),ROUND(K20+K21+K22-K23+K24,2),K20+K21+K22-K23+K24) -> 0 | ... AOQ25: =IF(AND(AOQ14="Desacumulación",AOR14="-"),ROUND(AOQ20+AOQ21+AOQ22-AOQ23+AOQ24,2),AOQ20+AOQ21+AOQ22-AOQ23+AOQ24) -> 2418577.6
RD26: Acumulacion | RE26: Acumulacion | RF26: Acumulacion | RG26: Acumulacion | RH26: Acumulacion | RI26: Acumulacion | RJ26: Acumulacion | RK26: Acumulacion | RL26: Acumulacion | RM26: Acumulacion | RN26: Acumulacion | RO26: Acumulacion | RP26: Acumulacion | RQ26: Acumulacion | RR26: Acumulacion | RS26: Acumulacion | RT26: Acumulacion | RU26: Acumulacion | RV26: Acumulacion | RW26: Acumulacion | RX26: Acumulacion | RY26: Acumulacion | RZ26: Acumulacion | SA26: Acumulacion | SB26: Acumulacion | SC26: Acumulacion | SD26: Acumulacion | SE26: Acumulacion | SF26: Acumulacion | SG26: Acumulacion | SH26: Acumulacion | SI26: Acumulacion | SJ26: Acumulacion | SK26: Acumulacion | SL26: Acumulacion | SM26: Acumulacion | SN26: Acumulacion | SO26: Acumulacion | SP26: Acumulacion | SQ26: Acumulacion | SR26: Acumulacion | SS26: Acumulacion | ST26: Acumulacion | SU26: Acumulacion | SV26: Acumulacion | SW26: Acumulacion | SX26: Acumulacion | SY26: Acumulacion | SZ26: Acumulacion | TA26: Acumulacion | TB26: Acumulacion | TC26: Acumulacion | TD26: Acumulacion | TE26: Acumulacion | TF26: Acumulacion | TG26: Acumulacion | TH26: Acumulacion | TI26: Acumulacion | TJ26: Acumulacion | TK26: Acumulacion | TL26: Acumulacion | TM26: Acumulacion | TN26: Acumulacion | TO26: Acumulacion | TP26: Acumulacion | TQ26: Acumulacion | TR26: Acumulacion | TS26: Acumulacion | TT26: Acumulacion | TU26: Acumulacion | TV26: Acumulacion | TW26: Acumulacion | TX26: Acumulacion | TY26: Acumulacion | TZ26: Acumulacion | UA26: Acumulacion | UB26: Acumulacion | UC26: Acumulacion | UD26: Acumulacion | UE26: Acumulacion | UF26: Acumulacion | UG26: Acumulacion | UH26: Acumulacion | UI26: Acumulacion | UJ26: Acumulacion | UK26: Acumulacion | UL26: Acumulacion | UM26: Acumulacion | UN26: Acumulacion | UO26: Acumulacion | UP26: Acumulacion | UQ26: Acumulacion | UR26: Acumulacion | US26: Acumulacion | UT26: Acumulacion | UU26: Acumulacion | UV26: Acumulacion | UW26: Acumulacion | UX26: Acumulacion | UY26: Acumulacion | UZ26: Acumulacion | VA26: Acumulacion | VB26: Acumulacion | VC26: Acumulacion | VD26: Acumulacion | VE26: Acumulacion | VF26: Acumulacion | VG26: Acumulacion | VH26: Acumulacion | VI26: Acumulacion | VJ26: Acumulacion | VK26: Acumulacion | VL26: Acumulacion | VM26: Acumulacion | VN26: Acumulacion | VO26: Acumulacion | VP26: Acumulacion | VQ26: Acumulacion | VR26: Acumulacion | VS26: Acumulacion | VT26: Acumulacion | VU26: Acumulacion | VV26: Acumulacion | VW26: Acumulacion | VX26: Acumulacion | VY26: Acumulacion | VZ26: Acumulacion | WA26: Acumulacion | WB26: Acumulacion | WC26: Acumulacion | WD26: Acumulacion | WE26: Acumulacion | WF26: Acumulacion | WG26: Acumulacion | WH26: Acumulacion | WI26: Acumulacion | WJ26: Acumulacion | WK26: Acumulacion | WL26: Acumulacion | WM26: Acumulacion | WN26: Acumulacion | WO26: Acumulacion | WP26: Acumulacion | WQ26: Acumulacion | WR26: Acumulacion | WS26: Acumulacion | WT26: Acumulacion | WU26: Acumulacion | WV26: Acumulacion | WW26: Acumulacion | WX26: Acumulacion | WY26: Acumulacion | WZ26: Acumulacion | XA26: Acumulacion | XB26: Acumulacion | XC26: Acumulacion | XD26: Acumulacion | XE26: Acumulacion | XF26: Acumulacion | XG26: Acumulacion | XH26: Acumulacion | XI26: Acumulacion | XJ26: Acumulacion | XK26: Acumulacion | XL26: Acumulacion | XM26: Acumulacion | XN26: Acumulacion | XO26: Acumulacion | XP26: Acumulacion | XQ26: Acumulacion | XR26: Acumulacion | XS26: Acumulacion | XT26: Acumulacion | XU26: Acumulacion | XV26: Acumulacion | XW26: Acumulacion | XX26: Acumulacion | XY26: Acumulacion | XZ26: Acumulacion | YA26: Acumulacion | YB26: Acumulacion | YC26: Acumulacion | YD26: Acumulacion | YE26: Acumulacion | YF26: Acumulacion | YG26: Acumulacion | YH26: Acumulacion | YI26: Acumulacion | YJ26: Acumulacion | YK26: Acumulacion | YL26: Acumulacion | YM26: Acumulacion | YN26: Acumulacion | YO26: Acumulacion | YP26: Acumulacion | YQ26: Acumulacion | YR26: Acumulacion | YS26: Acumulacion | YT26: Acumulacion | YU26: Acumulacion | YV26: Acumulacion | YW26: Acumulacion | YX26: Acumulacion | YY26: Acumulacion | YZ26: Acumulacion | ZA26: Acumulacion | ZB26: Acumulacion | ZC26: Acumulacion | ZD26: Acumulacion | ZE26: Acumulacion | ZF26: Acumulacion | ZG26: Acumulacion | ZH26: Acumulacion | ZI26: Acumulacion | ZJ26: Acumulacion | ZK26: Acumulacion | ZL26: Acumulacion | ZM26: Acumulacion | ZN26: Acumulacion | ZO26: Acumulacion | ZP26: Acumulacion | ZQ26: Acumulacion | ZR26: Acumulacion | ZS26: Acumulacion | ZT26: Acumulacion | ZU26: Acumulacion | ZV26: Acumulacion | ZW26: Acumulacion | ZX26: Acumulacion | ZY26: Acumulacion | ZZ26: Acumulacion | AAA26: Acumulacion | AAB26: Acumulacion | AAC26: Acumulacion | AAD26: Acumulacion | AAE26: Acumulacion | AAF26: Acumulacion | AAG26: Acumulacion | AAH26: Acumulacion | AAI26: Acumulacion | AAJ26: Acumulacion | AAK26: Acumulacion | AAL26: Acumulacion | AAM26: Acumulacion | AAN26: Acumulacion | AAO26: Acumulacion | AAP26: Acumulacion | AAQ26: Acumulacion | AAR26: Acumulacion | AAS26: Acumulacion | AAT26: Acumulacion | AAU26: Acumulacion | AAV26: Acumulacion | AAW26: Acumulacion | AAX26: Acumulacion | AAY26: Acumulacion | AAZ26: Acumulacion | ABA26: Acumulacion | ABB26: Acumulacion | ABC26: Acumulacion | ABD26: Acumulacion | ABE26: Acumulacion | ABF26: Acumulacion | ABG26: Acumulacion | ABH26: Acumulacion | ABI26: Acumulacion | ABJ26: Acumulacion | ABK26: Acumulacion | ABL26: Acumulacion | ABM26: Acumulacion | ABN26: Acumulacion | ABO26: Acumulacion | ABP26: Acumulacion | ABQ26: Acumulacion | ABR26: Acumulacion | ABS26: Acumulacion | ABT26: Acumulacion | ABU26: Acumulacion | ABV26: Acumulacion | ABW26: Acumulacion | ABX26: Acumulacion | ABY26: Acumulacion | ABZ26: Acumulacion | ACA26: Acumulacion | ACB26: Acumulacion | ACC26: Acumulacion | ACD26: Acumulacion | ACE26: Acumulacion | ACF26: Acumulacion | ACG26: Acumulacion | ACH26: Acumulacion | ACI26: Acumulacion | ACJ26: Acumulacion | ACK26: Acumulacion | ACL26: Acumulacion | ACM26: Acumulacion | ACN26: Acumulacion | ACO26: Acumulacion | ACP26: Acumulacion | ACQ26: Acumulacion
B27: ='Patrimonio Financiero'!BH200 -> Objetivo 1 | C27: ='Patrimonio Financiero'!CB200 -> 1000000 | D27: =$C27 -> 1000000 | E27: =$C27 -> 1000000 | F27: =$C27 -> 1000000 | G27: =$C27 -> 1000000 | H27: =$C27 -> 1000000 | I27: =$C27 -> 1000000 | J27: =$C27 -> 1000000 | K27: =$C27 -> 1000000 | ... AOQ27: =$C27 -> 1000000
B28: Retiro | C28: =SUM(D28:AOQ28) -> 1000000 | D28: 0 | E28: =IF(SUM($D28:D28)>0,0,IF(D$25>D27,D27,0)) -> 0 | F28: =IF(SUM($D28:E28)>0,0,IF(E$25>E27,E27,0)) -> 0 | G28: =IF(SUM($D28:F28)>0,0,IF(F$25>F27,F27,0)) -> 0 | H28: =IF(SUM($D28:G28)>0,0,IF(G$25>G27,G27,0)) -> 0 | I28: =IF(SUM($D28:H28)>0,0,IF(H$25>H27,H27,0)) -> 0 | J28: =IF(SUM($D28:I28)>0,0,IF(I$25>I27,I27,0)) -> 0 | K28: =IF(SUM($D28:J28)>0,0,IF(J$25>J27,J27,0)) -> 0 | L28: =IF(SUM($D28:K28)>0,0,IF(K$25>K27,K27,0)) -> 0 | ... AOQ28: =IF(SUM($D28:AOP28)>0,0,IF(AOP$25>AOP27,AOP27,0)) -> 0
B29: Periodo | C29: =SUM(D29:AOQ29) -> 609 | D29: =IF(D28>0,D$17,0) -> 0 | E29: =IF(E28>0,E$17,0) -> 0 | F29: =IF(F28>0,F$17,0) -> 0 | G29: =IF(G28>0,G$17,0) -> 0 | H29: =IF(H28>0,H$17,0) -> 0 | I29: =IF(I28>0,I$17,0) -> 0 | J29: =IF(J28>0,J$17,0) -> 0 | K29: =IF(K28>0,K$17,0) -> 0 | ... AOQ29: =IF(AOQ28>0,AOQ$17,0) -> 0
B30: Numero de periodos | C30: =SUM(D30:AOQ30) -> 20 | D30: 0 | E30: =IF(E28>0,SUM($D$18:D18),0) -> 0 | F30: =IF(F28>0,SUM($D$18:E18),0) -> 0 | G30: =IF(G28>0,SUM($D$18:F18),0) -> 0 | H30: =IF(H28>0,SUM($D$18:G18),0) -> 0 | I30: =IF(I28>0,SUM($D$18:H18),0) -> 0 | J30: =IF(J28>0,SUM($D$18:I18),0) -> 0 | K30: =IF(K28>0,SUM($D$18:J18),0) -> 0 | L30: =IF(L28>0,SUM($D$18:K18),0) -> 0 | ... AOQ30: =IF(AOQ28>0,SUM($D$18:AOP18),0) -> 0
B31: Plazo | C31: =IFERROR(MAX(IF(MAX(C30,0)=0,"Saldo Insuficiente",MAX(C30,0)),0),"Saldo Insuficiente") -> 20
B33: ='Patrimonio Financiero'!BH202 -> Objetivo 2 | C33: ='Patrimonio Financiero'!CB202 -> 900000 | D33: =$C33 -> 900000 | E33: =$C33 -> 900000 | F33: =$C33 -> 900000 | G33: =$C33 -> 900000 | H33: =$C33 -> 900000 | I33: =$C33 -> 900000 | J33: =$C33 -> 900000 | K33: =$C33 -> 900000 | ... AOQ33: =$C33 -> 900000
B34: Condición | D34: 0 | E34: =IF(E28>0,D25-E28,0) -> 0 | F34: =IF(F28>0,E25-F28,0) -> 0 | G34: =IF(G28>0,F25-G28,0) -> 0 | H34: =IF(H28>0,G25-H28,0) -> 0 | I34: =IF(I28>0,H25-I28,0) -> 0 | J34: =IF(J28>0,I25-J28,0) -> 0 | K34: =IF(K28>0,J25-K28,0) -> 0 | L34: =IF(L28>0,K25-L28,0) -> 0 | ... AOQ34: =IF(AOQ28>0,AOP25-AOQ28,0) -> 0
B35: Retiro | C35: =SUM(D35:AOQ35) -> 900000 | D35: 0 | E35: =IF(SUM($D$28:D28)=0,0,IF(IF(E34>0,E34-(IF(SUM($D35:D35)>0,0,IF(D$25>D33,D33,0))),0)<0,0,(IF(SUM($D35:D35)>0,0,IF(D$25>D33,D33,0))))) -> 0 | F35: =IF(SUM($D$28:E28)=0,0,IF(IF(F34>0,F34-(IF(SUM($D35:E35)>0,0,IF(E$25>E33,E33,0))),0)<0,0,(IF(SUM($D35:E35)>0,0,IF(E$25>E33,E33,0))))) -> 0 | G35: =IF(SUM($D$28:F28)=0,0,IF(IF(G34>0,G34-(IF(SUM($D35:F35)>0,0,IF(F$25>F33,F33,0))),0)<0,0,(IF(SUM($D35:F35)>0,0,IF(F$25>F33,F33,0))))) -> 0 | H35: =IF(SUM($D$28:G28)=0,0,IF(IF(H34>0,H34-(IF(SUM($D35:G35)>0,0,IF(G$25>G33,G33,0))),0)<0,0,(IF(SUM($D35:G35)>0,0,IF(G$25>G33,G33,0))))) -> 0 | I35: =IF(SUM($D$28:H28)=0,0,IF(IF(I34>0,I34-(IF(SUM($D35:H35)>0,0,IF(H$25>H33,H33,0))),0)<0,0,(IF(SUM($D35:H35)>0,0,IF(H$25>H33,H33,0))))) -> 0 | J35: =IF(SUM($D$28:I28)=0,0,IF(IF(J34>0,J34-(IF(SUM($D35:I35)>0,0,IF(I$25>I33,I33,0))),0)<0,0,(IF(SUM($D35:I35)>0,0,IF(I$25>I33,I33,0))))) -> 0 | K35: =IF(SUM($D$28:J28)=0,0,IF(IF(K34>0,K34-(IF(SUM($D35:J35)>0,0,IF(J$25>J33,J33,0))),0)<0,0,(IF(SUM($D35:J35)>0,0,IF(J$25>J33,J33,0))))) -> 0 | L35: =IF(SUM($D$28:K28)=0,0,IF(IF(L34>0,L34-(IF(SUM($D35:K35)>0,0,IF(K$25>K33,K33,0))),0)<0,0,(IF(SUM($D35:K35)>0,0,IF(K$25>K33,K33,0))))) -> 0 | ... AOQ35: =IF(SUM($D$28:AOP28)=0,0,IF(IF(AOQ34>0,AOQ34-(IF(SUM($D35:AOP35)>0,0,IF(AOP$25>AOP33,AOP33,0))),0)<0,0,(IF(SUM($D35:AOP35)>0,0,IF(AOP$25>AOP33,AOP33,0))))) -> 0
B36: Periodo | C36: =SUM(D36:AOQ36) -> 638 | D36: =IF(D35>0,D$17,0) -> 0 | E36: =IF(E35>0,E$17,0) -> 0 | F36: =IF(F35>0,F$17,0) -> 0 | G36: =IF(G35>0,G$17,0) -> 0 | H36: =IF(H35>0,H$17,0) -> 0 | I36: =IF(I35>0,I$17,0) -> 0 | J36: =IF(J35>0,J$17,0) -> 0 | K36: =IF(K35>0,K$17,0) -> 0 | ... AOQ36: =IF(AOQ35>0,AOQ$17,0) -> 0
B37: Numero de periodos | C37: =SUM(D37:AOQ37) -> 49 | D37: 0 | E37: =IF(E35>0,SUM($D$18:D18),0) -> 0 | F37: =IF(F35>0,SUM($D$18:E18),0) -> 0 | G37: =IF(G35>0,SUM($D$18:F18),0) -> 0 | H37: =IF(H35>0,SUM($D$18:G18),0) -> 0 | I37: =IF(I35>0,SUM($D$18:H18),0) -> 0 | J37: =IF(J35>0,SUM($D$18:I18),0) -> 0 | K37: =IF(K35>0,SUM($D$18:J18),0) -> 0 | L37: =IF(L35>0,SUM($D$18:K18),0) -> 0 | ... AOQ37: =IF(AOQ35>0,SUM($D$18:AOP18),0) -> 0
B38: Plazo | C38: =IFERROR(MAX(IF(AND(MAX(IF(C36=C29,C37,C37-C30),0)=0,C33>0),"Saldo Insuficiente",IF(C36=C29,C37,C37-C30)),0),"Saldo Insuficiente") -> 29
B40: ='Patrimonio Financiero'!BH204 -> Objetivo 3 | C40: ='Patrimonio Financiero'!CB204 -> 100000 | D40: =$C40 -> 100000 | E40: =$C40 -> 100000 | F40: =$C40 -> 100000 | G40: =$C40 -> 100000 | H40: =$C40 -> 100000 | I40: =$C40 -> 100000 | J40: =$C40 -> 100000 | K40: =$C40 -> 100000 | ... AOQ40: =$C40 -> 100000
B41: Condición | D41: =IF(D28+D35>0,C25-D28-D35,0) -> 0 | E41: =IF(E28+E35>0,D25-E28-E35,0) -> 0 | F41: =IF(F28+F35>0,E25-F28-F35,0) -> 0 | G41: =IF(G28+G35>0,F25-G28-G35,0) -> 0 | H41: =IF(H28+H35>0,G25-H28-H35,0) -> 0 | I41: =IF(I28+I35>0,H25-I28-I35,0) -> 0 | J41: =IF(J28+J35>0,I25-J28-J35,0) -> 0 | K41: =IF(K28+K35>0,J25-K28-K35,0) -> 0 | ... AOQ41: =IF(AOQ28+AOQ35>0,AOP25-AOQ28-AOQ35,0) -> 0
B42: Retiro | C42: =SUM(D42:AOQ42) -> 100000 | D42: 0 | E42: =IF(SUM($D$35:D35)=0,0,IF(IF(E41>0,E41-(IF(SUM($D42:D42)>0,0,IF(D$25>D40,D40,0))),0)<0,0,(IF(SUM($D42:D42)>0,0,IF(D$25>D40,D40,0))))) -> 0 | F42: =IF(SUM($D$35:E35)=0,0,IF(IF(F41>0,F41-(IF(SUM($D42:E42)>0,0,IF(E$25>E40,E40,0))),0)<0,0,(IF(SUM($D42:E42)>0,0,IF(E$25>E40,E40,0))))) -> 0 | G42: =IF(SUM($D$35:F35)=0,0,IF(IF(G41>0,G41-(IF(SUM($D42:F42)>0,0,IF(F$25>F40,F40,0))),0)<0,0,(IF(SUM($D42:F42)>0,0,IF(F$25>F40,F40,0))))) -> 0 | H42: =IF(SUM($D$35:G35)=0,0,IF(IF(H41>0,H41-(IF(SUM($D42:G42)>0,0,IF(G$25>G40,G40,0))),0)<0,0,(IF(SUM($D42:G42)>0,0,IF(G$25>G40,G40,0))))) -> 0 | I42: =IF(SUM($D$35:H35)=0,0,IF(IF(I41>0,I41-(IF(SUM($D42:H42)>0,0,IF(H$25>H40,H40,0))),0)<0,0,(IF(SUM($D42:H42)>0,0,IF(H$25>H40,H40,0))))) -> 0 | J42: =IF(SUM($D$35:I35)=0,0,IF(IF(J41>0,J41-(IF(SUM($D42:I42)>0,0,IF(I$25>I40,I40,0))),0)<0,0,(IF(SUM($D42:I42)>0,0,IF(I$25>I40,I40,0))))) -> 0 | K42: =IF(SUM($D$35:J35)=0,0,IF(IF(K41>0,K41-(IF(SUM($D42:J42)>0,0,IF(J$25>J40,J40,0))),0)<0,0,(IF(SUM($D42:J42)>0,0,IF(J$25>J40,J40,0))))) -> 0 | L42: =IF(SUM($D$35:K35)=0,0,IF(IF(L41>0,L41-(IF(SUM($D42:K42)>0,0,IF(K$25>K40,K40,0))),0)<0,0,(IF(SUM($D42:K42)>0,0,IF(K$25>K40,K40,0))))) -> 0 | ... AOQ42: =IF(SUM($D$35:AOP35)=0,0,IF(IF(AOQ41>0,AOQ41-(IF(SUM($D42:AOP42)>0,0,IF(AOP$25>AOP40,AOP40,0))),0)<0,0,(IF(SUM($D42:AOP42)>0,0,IF(AOP$25>AOP40,AOP40,0))))) -> 0
B43: Periodo | C43: =SUM(D43:AOQ43) -> 645 | D43: =IF(D42>0,D$17,0) -> 0 | E43: =IF(E42>0,E$17,0) -> 0 | F43: =IF(F42>0,F$17,0) -> 0 | G43: =IF(G42>0,G$17,0) -> 0 | H43: =IF(H42>0,H$17,0) -> 0 | I43: =IF(I42>0,I$17,0) -> 0 | J43: =IF(J42>0,J$17,0) -> 0 | K43: =IF(K42>0,K$17,0) -> 0 | ... AOQ43: =IF(AOQ42>0,AOQ$17,0) -> 0
B44: Numero de periodos | C44: =SUM(D44:AOQ44) -> 56 | D44: 0 | E44: =IF(E42>0,SUM($D$18:D18),0) -> 0 | F44: =IF(F42>0,SUM($D$18:E18),0) -> 0 | G44: =IF(G42>0,SUM($D$18:F18),0) -> 0 | H44: =IF(H42>0,SUM($D$18:G18),0) -> 0 | I44: =IF(I42>0,SUM($D$18:H18),0) -> 0 | J44: =IF(J42>0,SUM($D$18:I18),0) -> 0 | K44: =IF(K42>0,SUM($D$18:J18),0) -> 0 | L44: =IF(L42>0,SUM($D$18:K18),0) -> 0 | ... AOQ44: =IF(AOQ42>0,SUM($D$18:AOP18),0) -> 0
B45: Plazo | C45: =IFERROR(MAX(IF(AND(MAX(IF(C43=C36,C44,C44-C37),0)=0,C40>0),"Saldo Insuficiente",IF(C43=C36,C44,C44-C37)),0),"Saldo Insuficiente") -> 7
B47: ='Patrimonio Financiero'!BH206 -> Objetivo 4 | C47: ='Patrimonio Financiero'!CB206 -> 5000000 | D47: =$C47 -> 5000000 | E47: =$C47 -> 5000000 | F47: =$C47 -> 5000000 | G47: =$C47 -> 5000000 | H47: =$C47 -> 5000000 | I47: =$C47 -> 5000000 | J47: =$C47 -> 5000000 | K47: =$C47 -> 5000000 | ... AOQ47: =$C47 -> 5000000
B48: Condición | D48: =IF(D28+D35+D42>0,C25-D28-D35-D42,0) -> 0 | E48: =IF(E28+E35+E42>0,D25-E28-E35-E42,0) -> 0 | F48: =IF(F28+F35+F42>0,E25-F28-F35-F42,0) -> 0 | G48: =IF(G28+G35+G42>0,F25-G28-G35-G42,0) -> 0 | H48: =IF(H28+H35+H42>0,G25-H28-H35-H42,0) -> 0 | I48: =IF(I28+I35+I42>0,H25-I28-I35-I42,0) -> 0 | J48: =IF(J28+J35+J42>0,I25-J28-J35-J42,0) -> 0 | K48: =IF(K28+K35+K42>0,J25-K28-K35-K42,0) -> 0 | ... AOQ48: =IF(AOQ28+AOQ35+AOQ42>0,AOP25-AOQ28-AOQ35-AOQ42,0) -> 0
B49: Retiro | C49: =SUM(D49:AOQ49) -> 0 | D49: 0 | E49: =IF(SUM($D$42:D42)=0,0,IF(IF(E48>0,E48-(IF(SUM($D49:D49)>0,0,IF(D$25>D47,D47,0))),0)<0,0,(IF(SUM($D49:D49)>0,0,IF(D$25>D47,D47,0))))) -> 0 | F49: =IF(SUM($D$42:E42)=0,0,IF(IF(F48>0,F48-(IF(SUM($D49:E49)>0,0,IF(E$25>E47,E47,0))),0)<0,0,(IF(SUM($D49:E49)>0,0,IF(E$25>E47,E47,0))))) -> 0 | G49: =IF(SUM($D$42:F42)=0,0,IF(IF(G48>0,G48-(IF(SUM($D49:F49)>0,0,IF(F$25>F47,F47,0))),0)<0,0,(IF(SUM($D49:F49)>0,0,IF(F$25>F47,F47,0))))) -> 0 | H49: =IF(SUM($D$42:G42)=0,0,IF(IF(H48>0,H48-(IF(SUM($D49:G49)>0,0,IF(G$25>G47,G47,0))),0)<0,0,(IF(SUM($D49:G49)>0,0,IF(G$25>G47,G47,0))))) -> 0 | I49: =IF(SUM($D$42:H42)=0,0,IF(IF(I48>0,I48-(IF(SUM($D49:H49)>0,0,IF(H$25>H47,H47,0))),0)<0,0,(IF(SUM($D49:H49)>0,0,IF(H$25>H47,H47,0))))) -> 0 | J49: =IF(SUM($D$42:I42)=0,0,IF(IF(J48>0,J48-(IF(SUM($D49:I49)>0,0,IF(I$25>I47,I47,0))),0)<0,0,(IF(SUM($D49:I49)>0,0,IF(I$25>I47,I47,0))))) -> 0 | K49: =IF(SUM($D$42:J42)=0,0,IF(IF(K48>0,K48-(IF(SUM($D49:J49)>0,0,IF(J$25>J47,J47,0))),0)<0,0,(IF(SUM($D49:J49)>0,0,IF(J$25>J47,J47,0))))) -> 0 | L49: =IF(SUM($D$42:K42)=0,0,IF(IF(L48>0,L48-(IF(SUM($D49:K49)>0,0,IF(K$25>K47,K47,0))),0)<0,0,(IF(SUM($D49:K49)>0,0,IF(K$25>K47,K47,0))))) -> 0 | ... AOQ49: =IF(SUM($D$42:AOP42)=0,0,IF(IF(AOQ48>0,AOQ48-(IF(SUM($D49:AOP49)>0,0,IF(AOP$25>AOP47,AOP47,0))),0)<0,0,(IF(SUM($D49:AOP49)>0,0,IF(AOP$25>AOP47,AOP47,0))))) -> 0
B50: Periodo | C50: =SUM(D50:AOQ50) -> 0 | D50: =IF(D49>0,D$17,0) -> 0 | E50: =IF(E49>0,E$17,0) -> 0 | F50: =IF(F49>0,F$17,0) -> 0 | G50: =IF(G49>0,G$17,0) -> 0 | H50: =IF(H49>0,H$17,0) -> 0 | I50: =IF(I49>0,I$17,0) -> 0 | J50: =IF(J49>0,J$17,0) -> 0 | K50: =IF(K49>0,K$17,0) -> 0 | ... AOQ50: =IF(AOQ49>0,AOQ$17,0) -> 0
B51: Numero de periodos | C51: =SUM(D51:AOQ51) -> 0 | D51: 0 | E51: =IF(E49>0,SUM($D$18:D18),0) -> 0 | F51: =IF(F49>0,SUM($D$18:E18),0) -> 0 | G51: =IF(G49>0,SUM($D$18:F18),0) -> 0 | H51: =IF(H49>0,SUM($D$18:G18),0) -> 0 | I51: =IF(I49>0,SUM($D$18:H18),0) -> 0 | J51: =IF(J49>0,SUM($D$18:I18),0) -> 0 | K51: =IF(K49>0,SUM($D$18:J18),0) -> 0 | L51: =IF(L49>0,SUM($D$18:K18),0) -> 0 | ... AOQ51: =IF(AOQ49>0,SUM($D$18:AOP18),0) -> 0
B52: Plazo | C52: =IFERROR(MAX(IF(AND(MAX(IF(C50=C43,C51,C51-C44),0)=0,C47>0),"Saldo Insuficiente",IF(C50=C43,C51,C51-C44)),0),"Saldo Insuficiente") -> Saldo Insuficiente
B54: ='Patrimonio Financiero'!BH208 -> Objetivo 5 | C54: ='Patrimonio Financiero'!CB208 -> 2500000 | D54: =$C54 -> 2500000 | E54: =$C54 -> 2500000 | F54: =$C54 -> 2500000 | G54: =$C54 -> 2500000 | H54: =$C54 -> 2500000 | I54: =$C54 -> 2500000 | J54: =$C54 -> 2500000 | K54: =$C54 -> 2500000 | ... AOQ54: =$C54 -> 2500000
B55: Condición | D55: =IF(D28+D35+D42+D49>0,C25-D28-D35-D42-D49,0) -> 0 | E55: =IF(E28+E35+E42+E49>0,D25-E28-E35-E42-E49,0) -> 0 | F55: =IF(F28+F35+F42+F49>0,E25-F28-F35-F42-F49,0) -> 0 | G55: =IF(G28+G35+G42+G49>0,F25-G28-G35-G42-G49,0) -> 0 | H55: =IF(H28+H35+H42+H49>0,G25-H28-H35-H42-H49,0) -> 0 | I55: =IF(I28+I35+I42+I49>0,H25-I28-I35-I42-I49,0) -> 0 | J55: =IF(J28+J35+J42+J49>0,I25-J28-J35-J42-J49,0) -> 0 | K55: =IF(K28+K35+K42+K49>0,J25-K28-K35-K42-K49,0) -> 0 | ... AOQ55: =IF(AOQ28+AOQ35+AOQ42+AOQ49>0,AOP25-AOQ28-AOQ35-AOQ42-AOQ49,0) -> 0
B56: Retiro | C56: =SUM(D56:AOQ56) -> 0 | D56: 0 | E56: =IF(SUM($D$49:D49)=0,0,IF(IF(E55>0,E55-(IF(SUM($D56:D56)>0,0,IF(D$25>D54,D54,0))),0)<0,0,(IF(SUM($D56:D56)>0,0,IF(D$25>D54,D54,0))))) -> 0 | F56: =IF(SUM($D$49:E49)=0,0,IF(IF(F55>0,F55-(IF(SUM($D56:E56)>0,0,IF(E$25>E54,E54,0))),0)<0,0,(IF(SUM($D56:E56)>0,0,IF(E$25>E54,E54,0))))) -> 0 | G56: =IF(SUM($D$49:F49)=0,0,IF(IF(G55>0,G55-(IF(SUM($D56:F56)>0,0,IF(F$25>F54,F54,0))),0)<0,0,(IF(SUM($D56:F56)>0,0,IF(F$25>F54,F54,0))))) -> 0 | H56: =IF(SUM($D$49:G49)=0,0,IF(IF(H55>0,H55-(IF(SUM($D56:G56)>0,0,IF(G$25>G54,G54,0))),0)<0,0,(IF(SUM($D56:G56)>0,0,IF(G$25>G54,G54,0))))) -> 0 | I56: =IF(SUM($D$49:H49)=0,0,IF(IF(I55>0,I55-(IF(SUM($D56:H56)>0,0,IF(H$25>H54,H54,0))),0)<0,0,(IF(SUM($D56:H56)>0,0,IF(H$25>H54,H54,0))))) -> 0 | J56: =IF(SUM($D$49:I49)=0,0,IF(IF(J55>0,J55-(IF(SUM($D56:I56)>0,0,IF(I$25>I54,I54,0))),0)<0,0,(IF(SUM($D56:I56)>0,0,IF(I$25>I54,I54,0))))) -> 0 | K56: =IF(SUM($D$49:J49)=0,0,IF(IF(K55>0,K55-(IF(SUM($D56:J56)>0,0,IF(J$25>J54,J54,0))),0)<0,0,(IF(SUM($D56:J56)>0,0,IF(J$25>J54,J54,0))))) -> 0 | L56: =IF(SUM($D$49:K49)=0,0,IF(IF(L55>0,L55-(IF(SUM($D56:K56)>0,0,IF(K$25>K54,K54,0))),0)<0,0,(IF(SUM($D56:K56)>0,0,IF(K$25>K54,K54,0))))) -> 0 | ... AOQ56: =IF(SUM($D$49:AOP49)=0,0,IF(IF(AOQ55>0,AOQ55-(IF(SUM($D56:AOP56)>0,0,IF(AOP$25>AOP54,AOP54,0))),0)<0,0,(IF(SUM($D56:AOP56)>0,0,IF(AOP$25>AOP54,AOP54,0))))) -> 0
B57: Periodo | C57: =SUM(D57:AOQ57) -> 0 | D57: =IF(D56>0,D$17,0) -> 0 | E57: =IF(E56>0,E$17,0) -> 0 | F57: =IF(F56>0,F$17,0) -> 0 | G57: =IF(G56>0,G$17,0) -> 0 | H57: =IF(H56>0,H$17,0) -> 0 | I57: =IF(I56>0,I$17,0) -> 0 | J57: =IF(J56>0,J$17,0) -> 0 | K57: =IF(K56>0,K$17,0) -> 0 | ... AOQ57: =IF(AOQ56>0,AOQ$17,0) -> 0
B58: Numero de periodos | C58: =SUM(D58:AOQ58) -> 0 | D58: 0 | E58: =IF(E56>0,SUM($D$18:D18),0) -> 0 | F58: =IF(F56>0,SUM($D$18:E18),0) -> 0 | G58: =IF(G56>0,SUM($D$18:F18),0) -> 0 | H58: =IF(H56>0,SUM($D$18:G18),0) -> 0 | I58: =IF(I56>0,SUM($D$18:H18),0) -> 0 | J58: =IF(J56>0,SUM($D$18:I18),0) -> 0 | K58: =IF(K56>0,SUM($D$18:J18),0) -> 0 | L58: =IF(L56>0,SUM($D$18:K18),0) -> 0 | ... AOQ58: =IF(AOQ56>0,SUM($D$18:AOP18),0) -> 0
B59: Plazo | C59: =IFERROR(MAX(IF(AND(MAX(IF(C57=C50,C58,C58-C51),0)=0,C54>0),"Saldo Insuficiente",IF(C57=C50,C58,C58-C51)),0),"Saldo Insuficiente") -> Saldo Insuficiente

Sheet Auxiliar
B2: Catálogos Entrevista | G2: Hoja de Cliente
B4: Edad de Retiro | D4: Género | F4: 2 | G4: =IF('Cálculos y Supuestos Edo.Res'!H10<=10%,IF('Cálculos y Supuestos Edo.Res'!C23>'Cálculos y Supuestos Edo.Res'!C25,"Tu nivel de gastos está excedido en GASTOS BÁSICOS"),IF('Cálculos y Supuestos Edo.Res'!C25>'Cálculos y Supuestos Edo.Res'!C23,"Tu nivel de gastos está excedido en OBLIGACIONES","")) | P4: =IF(G4="","NO BORRAR","") -> NO BORRAR | R4: Edad Venta de Activos
B5: =IF('Entrevista Patrimonio F.'!E9+1>80,"",'Entrevista Patrimonio F.'!E9+1) -> 51 | D5: Hombre | F5: 3 | G5: Para gráfica Ingresos vs. Gastos | P5: =IF(G5="","NO BORRAR","") | R5: =IF(EdaddeRetiro+1>80,"",EdaddeRetiro) -> 60
B6: =IF(B5<>"",IF(B5+1>80,"",B5+1),"") -> 52 | D6: Mujer | I6: Obligaciones | J6: Gastos Básicos | K6: Ahorro | R6: =IF(R5<>"",IF(R5+1>89,"",R5+1),"") -> 61
B7: =IF(B6<>"",IF(B6+1>80,"",B6+1),"") -> 53 | D7: Otro | G7: Actual | I7: ='Cálculos y Supuestos Edo.Res'!D25 -> 0.18181818 | J7: ='Cálculos y Supuestos Edo.Res'!D23 -> 0.36363636 | K7: ='Cálculos y Supuestos Edo.Res'!H10 -> 0.45454545 | R7: =IF(R6<>"",IF(R6+1>89,"",R6+1),"") -> 62
B8: =IF(B7<>"",IF(B7+1>80,"",B7+1),"") -> 54 | D8: Prefiero no contestar | G8: Objetivo mínimo de ahorro | I8: 0.5 | J8: 0.4 | K8: 0.1 | R8: =IF(R7<>"",IF(R7+1>89,"",R7+1),"") -> 63
B9: =IF(B8<>"",IF(B8+1>80,"",B8+1),"") -> 55 | F9: 4 | G9: ="Actualmente tienes cubierto "&TEXT('Cálculos y Supuestos Edo.Res'!G15,"###.#0")&" meses de tus gastos básicos. "&IF('Cálculos y Supuestos Edo.Res'!G15>=4,"Tu reserva está EXCEDIDA",IF('Cálculos y Supuestos Edo.Res'!G15<3,"Es necesario incrementar tu reserva.","Tienes un nivel de reserva suficiente.")) -> Actualmente tienes cubierto 5.0 meses de tus gastos básicos. Tu reserva está EXCEDIDA | P9: =IF(G9="","NO BORRAR","") | R9: =IF(R8<>"",IF(R8+1>89,"",R8+1),"") -> 64
B10: =IF(B9<>"",IF(B9+1>80,"",B9+1),"") -> 56 | F10: 5 | G10: =CONCATENATE('Cálculos y Supuestos Edo.Res'!G16," ",'Cálculos y Supuestos Edo.Res'!G19) -> Excedido 50000 | P10: =IF(G10="","NO BORRAR","") | R10: =IF(R9<>"",IF(R9+1>89,"",R9+1),"") -> 65
B11: =IF(B10<>"",IF(B10+1>80,"",B10+1),"") -> 57 | D11: Ocupación Actual | F11: 6 | G11: ="Para cubrir 3 meses de tus gastos = "&TEXT('Cálculos y Supuestos Edo.Res'!G14,"$###,###,###") -> Para cubrir 3 meses de tus gastos = $120,000 | P11: =IF(G11="","NO BORRAR","") | R11: =IF(R10<>"",IF(R10+1>89,"",R10+1),"") -> 66
B12: =IF(B11<>"",IF(B11+1>80,"",B11+1),"") -> 58 | D12: Asalariado | F12: 7 | G12: ="Considerando tu patrimonio financiero actual, puedes cubrir tus gastos totales anuales por "&TEXT('Cálculos y Supuestos Edo.Res'!G23,"#0.##")&" años." -> Considerando tu patrimonio financiero actual, puedes cubrir tus gastos totales anuales por 2.92 años. | P12: =IF(G12="","NO BORRAR","") | R12: =IF(R11<>"",IF(R11+1>89,"",R11+1),"") -> 67
B13: =IF(B12<>"",IF(B12+1>80,"",B12+1),"") -> 59 | D13: Independiente | F13: 8 | G13: ="Tienes tus gastos cubiertos hasta los " &ROUND('Cálculos y Supuestos Edo.Res'!G27,0)&" años de edad." -> Tienes tus gastos cubiertos hasta los 53 años de edad. | P13: =IF(G13="","NO BORRAR","") | R13: =IF(R12<>"",IF(R12+1>89,"",R12+1),"") -> 68
B14: =IF(B13<>"",IF(B13+1>80,"",B13+1),"") -> 60 | D14: Empresario | F14: 9 | G14: =IF('Cálculos y Supuestos Edo.Res'!G23<1,"POR DEBAJO DEL PROMEDIO",IF(AND('Cálculos y Supuestos Edo.Res'!G23>=1,'Cálculos y Supuestos Edo.Res'!G23<3),"POR ARRIBA DEL PROMEDIO",IF(AND('Cálculos y Supuestos Edo.Res'!G23>=3,'Cálculos y Supuestos Edo.Res'!G23<5),"RICO","ACAUDALADO"))) -> POR ARRIBA DEL PROMEDIO | P14: =IF(G14="","NO BORRAR","") | R14: =IF(R13<>"",IF(R13+1>89,"",R13+1),"") -> 69
B15: =IF(B14<>"",IF(B14+1>80,"",B14+1),"") -> 61 | F15: 10 | G15: ="Te encuentras en un nivel "&G14&". "&" "&G16 -> Te encuentras en un nivel POR ARRIBA DEL PROMEDIO. Incrementa tu riqueza para alcanzar alguna meta personal. | P15: =IF(G15="","NO BORRAR","") | R15: =IF(R14<>"",IF(R14+1>89,"",R14+1),"") -> 70
B16: =IF(B15<>"",IF(B15+1>80,"",B15+1),"") -> 62 | F16: 11 | G16: =IF(G14="POR DEBAJO DEL PROMEDIO","Incrementa tu riqueza para cubrir al menos un año de tus gastos básicos.",IF(OR(G14="POR ARRIBA DEL PROMEDIO",G14="RICO",G14="ACAUDALADO"),"Incrementa tu riqueza para alcanzar alguna meta personal.","")) -> Incrementa tu riqueza para alcanzar alguna meta personal. | P16: =IF(G16="","NO BORRAR","") | R16: =IF(R15<>"",IF(R15+1>89,"",R15+1),"") -> 71
B17: =IF(B16<>"",IF(B16+1>80,"",B16+1),"") -> 63 | D17: Sí/No | F17: 12 | G17: Gastos totales al año | P17: =IF(G17="","NO BORRAR","") | R17: =IF(R16<>"",IF(R16+1>89,"",R16+1),"") -> 72
B18: =IF(B17<>"",IF(B17+1>80,"",B17+1),"") -> 64 | D18: Sí | F18: 13 | G18: =IF(G14="POR DEBAJO DEL PROMEDIO","Meta al menos 1 año de gastos :"&TEXT(J18,"$###,###,###"),IF(OR(G14="POR ARRIBA DEL PROMEDIO",G14="RICO",G14="ACAUDALADO"),"Alcanza una meta personal","")) -> Alcanza una meta personal | J18: ='Cálculos y Supuestos Edo.Res'!C26*12 -> 720000 | P18: =IF(G18="","NO BORRAR","") | R18: =IF(R17<>"",IF(R17+1>89,"",R17+1),"") -> 73
B19: =IF(B18<>"",IF(B18+1>80,"",B18+1),"") -> 65 | D19: No | F19: 14 | G19: Para gráfica Nivel de Riqueza | P19: =IF(G19="","NO BORRAR","") | R19: =IF(R18<>"",IF(R18+1>89,"",R18+1),"") -> 74
B20: =IF(B19<>"",IF(B19+1>80,"",B19+1),"") -> 66 | H20: Por debajo | I20: Por arriba | J20: Rico | K20: Acaudalado | R20: =IF(R19<>"",IF(R19+1>89,"",R19+1),"") -> 75
B21: =IF(B20<>"",IF(B20+1>80,"",B20+1),"") -> 67 | G21: Referencia | H21: 1 | I21: 2 | J21: 1 | K21: 1 | P21: =IF(G21="","NO BORRAR","") | R21: =IF(R20<>"",IF(R20+1>89,"",R20+1),"") -> 76
B22: =IF(B21<>"",IF(B21+1>80,"",B21+1),"") -> 68 | D22: Periodicidad | G22: Mi nivel | H22: =MIN('Cálculos y Supuestos Edo.Res'!G23,5) -> 2.9166667 | P22: =IF(G22="","NO BORRAR","") | R22: =IF(R21<>"",IF(R21+1>89,"",R21+1),"") -> 77
B23: =IF(B22<>"",IF(B22+1>80,"",B22+1),"") -> 69 | D23: Mensual | F23: 15 | G23: Para gráfica mensualidad retiro sin Capital humano ni rentas | P23: =IF(G23="","NO BORRAR","") | R23: =IF(R22<>"",IF(R22+1>89,"",R22+1),"") -> 78
B24: =IF(B23<>"",IF(B23+1>80,"",B23+1),"") -> 70 | D24: Trimestral | H24: Afore | I24: Voluntario | J24: Ley 73 | R24: =IF(R23<>"",IF(R23+1>89,"",R23+1),"") -> 79
B25: =IF(B24<>"",IF(B24+1>80,"",B24+1),"") -> 71 | D25: Semestral | G25: Calidad de vida | H25: ='Cálculos y Supuestos Edo.Res'!C13 -> 50000 | R25: =IF(R24<>"",IF(R24+1>89,"",R24+1),"") -> 80
B26: =IF(B25<>"",IF(B25+1>80,"",B25+1),"") -> 72 | D26: Anual | G26: Mis esquemas | H26: =+'Cálculos y Supuestos Edo.Res'!G30 -> 3551.5588 | I26: ='Cálculos y Supuestos Edo.Res'!G31 -> 0 | J26: =+'Cálculos y Supuestos Edo.Res'!G32 -> 35000 | R26: =IF(R25<>"",IF(R25+1>89,"",R25+1),"") -> 81
B27: =IF(B26<>"",IF(B26+1>80,"",B26+1),"") -> 73 | F27: 16 | G27: ="Total de mensualidad en retiro: "&TEXT('Cálculos y Supuestos Edo.Res'!G33,"$ ###,###,###") -> Total de mensualidad en retiro: $ 38,552 | P27: =IF(G27="","NO BORRAR","") | R27: =IF(R26<>"",IF(R26+1>89,"",R26+1),"") -> 82
B28: =IF(B27<>"",IF(B27+1>80,"",B27+1),"") -> 74 | F28: 17 | G28: ="Tienes un avance del "&TEXT('Cálculos y Supuestos Edo.Res'!G34,"##%")&" de tu calidad de vida en edad de retiro." -> Tienes un avance del 77% de tu calidad de vida en edad de retiro. | P28: =IF(G28="","NO BORRAR","") | R28: =IF(R27<>"",IF(R27+1>89,"",R27+1),"") -> 83
B29: =IF(B28<>"",IF(B28+1>80,"",B28+1),"") -> 75 | F29: 18 | G29: ="Total de ingreso mensual en retiro :" -> Total de ingreso mensual en retiro : | I29: ='Cálculos y Supuestos Edo.Res'!G44 -> 48551.559 | P29: =IF(G29="","NO BORRAR","") | R29: =IF(R28<>"",IF(R28+1>89,"",R28+1),"") -> 84
B30: =IF(B29<>"",IF(B29+1>80,"",B29+1),"") -> 76 | F30: 19 | G30: =IF('Cálculos y Supuestos Edo.Res'!G53<-100,"DÉFICIT",IF('Cálculos y Supuestos Edo.Res'!G53>100,"SUPERÁVIT",IF(ABS('Cálculos y Supuestos Edo.Res'!G53)<=100,"EQUILIBRIO"))) -> SUPERÁVIT | P30: =IF(G30="","NO BORRAR","") | R30: =IF(R29<>"",IF(R29+1>89,"",R29+1),"") -> 85
B31: =IF(B30<>"",IF(B30+1>80,"",B30+1),"") -> 77 | F31: 20 | G31: =IF('Cálculos y Supuestos Edo.Res'!G44<'Cálculos y Supuestos Edo.Res'!C13,"Tendrías un faltante mensual de:",IF('Cálculos y Supuestos Edo.Res'!G44>='Cálculos y Supuestos Edo.Res'!C13,"Tu calidad de vida está cubierta")) -> Tendrías un faltante mensual de: | I31: =IF('Cálculos y Supuestos Edo.Res'!G44<'Cálculos y Supuestos Edo.Res'!C13,'Cálculos y Supuestos Edo.Res'!G44-'Cálculos y Supuestos Edo.Res'!C13,"") -> -1448.4412 | P31: =IF(G31="","NO BORRAR","") | R31: =IF(R30<>"",IF(R30+1>89,"",R30+1),"") -> 86
B32: =IF(B31<>"",IF(B31+1>80,"",B31+1),"") -> 78 | F32: 21 | G32: ="Tienes un avance del "&TEXT(K32,"##%")&" de tu calidad de vida en edad de retiro." -> Tienes un avance del 97% de tu calidad de vida en edad de retiro. | K32: =I29/'Cálculos y Supuestos Edo.Res'!C13 -> 0.97103118 | P32: =IF(G32="","NO BORRAR","") | R32: =IF(R31<>"",IF(R31+1>89,"",R31+1),"") -> 87
B33: =IF(B32<>"",IF(B32+1>80,"",B32+1),"") -> 79 | F33: 22 | G33: ="Si ahorras durante "&TEXT('Cálculos y Supuestos Edo.Res'!C8-'Cálculos y Supuestos Edo.Res'!C7,"#0")&" años (años hasta tu edad de retiro) puedes incrementar tus posibilidades al momento del retiro." -> Si ahorras durante 10 años (años hasta tu edad de retiro) puedes incrementar tus posibilidades al momento del retiro. | P33: =IF(G33="","NO BORRAR","") | R33: =IF(R32<>"",IF(R32+1>89,"",R32+1),"") -> 88
B34: =IF(B33<>"",IF(B33+1>80,"",B33+1),"") -> 80 | F34: 23 | G34: No es imperante que cuentes con un Seguro de Vida. | P34: =IF(G34="","NO BORRAR","") | R34: =IF(R33<>"",IF(R33+1>89,"",R33+1),"") -> 89
B35: =IF(B34<>"",IF(B34+1>80,"",B34+1),"") | F35: 24 | G35: =IF(OR('Cálculos y Supuestos Edo.Res'!C11="No",'Cálculos y Supuestos Edo.Res'!G66=0),G34,IF('Cálculos y Supuestos Edo.Res'!H10>=10%,"Protege a tus dependientes por una suma que cubra al menos "&TEXT('Cálculos y Supuestos Edo.Res'!G66,"#0.0")&" años de tus gastos básicos, para alcanzar una protección de 3 años.","Es importante que primero mejores tu capacidad de ahorro.")) -> Protege a tus dependientes por una suma que cubra al menos 0.1 años de tus gastos básicos, para alcanzar una protección de 3 años. | P35: =IF(G35="","NO BORRAR","") | R35: =IF(R34<>"",IF(R34+1>89,"",R34+1),"")
B36: =IF(B35<>"",IF(B35+1>80,"",B35+1),"") | F36: 25 | G36: ="Es importante que cuentes con SGMM por una suma asegurada de al menos: "&TEXT('Cálculos y Supuestos Edo.Res'!G69,"$###,###,###") -> Es importante que cuentes con SGMM por una suma asegurada de al menos: TBD | P36: =IF(G36="","NO BORRAR","") | R36: =IF(R35<>"",IF(R35+1>89,"",R35+1),"")
B37: =IF(B36<>"",IF(B36+1>80,"",B36+1),"") | F37: 26 | G37: =IF('Cálculos y Supuestos Edo.Res'!C17>0,"Protege tu propiedad por al menos una suma asegurada de:","") -> Protege tu propiedad por al menos una suma asegurada de: | P37: =IF(G37="","NO BORRAR","") | R37: =IF(R36<>"",IF(R36+1>89,"",R36+1),"")
B38: =IF(B37<>"",IF(B37+1>80,"",B37+1),"") | R38: =IF(R37<>"",IF(R37+1>89,"",R37+1),"")
B39: =IF(B38<>"",IF(B38+1>80,"",B38+1),"") | R39: =IF(R38<>"",IF(R38+1>89,"",R38+1),"")
B40: =IF(B39<>"",IF(B39+1>80,"",B39+1),"") | R40: =IF(R39<>"",IF(R39+1>89,"",R39+1),"")
B41: =IF(B40<>"",IF(B40+1>80,"",B40+1),"") | R41: =IF(R40<>"",IF(R40+1>89,"",R40+1),"")
B42: =IF(B41<>"",IF(B41+1>80,"",B41+1),"") | R42: =IF(R41<>"",IF(R41+1>89,"",R41+1),"")
B43: =IF(B42<>"",IF(B42+1>80,"",B42+1),"") | R43: =IF(R42<>"",IF(R42+1>89,"",R42+1),"")
B44: =IF(B43<>"",IF(B43+1>80,"",B43+1),"") | R44: =IF(R43<>"",IF(R43+1>89,"",R43+1),"")
B45: =IF(B44<>"",IF(B44+1>80,"",B44+1),"") | R45: =IF(R44<>"",IF(R44+1>89,"",R44+1),"")
B46: =IF(B45<>"",IF(B45+1>80,"",B45+1),"") | R46: =IF(R45<>"",IF(R45+1>89,"",R45+1),"")
B47: =IF(B46<>"",IF(B46+1>80,"",B46+1),"") | R47: =IF(R46<>"",IF(R46+1>89,"",R46+1),"")
B48: =IF(B47<>"",IF(B47+1>80,"",B47+1),"") | R48: =IF(R47<>"",IF(R47+1>89,"",R47+1),"")
B49: =IF(B48<>"",IF(B48+1>80,"",B48+1),"") | R49: =IF(R48<>"",IF(R48+1>89,"",R48+1),"")
B50: =IF(B49<>"",IF(B49+1>80,"",B49+1),"") | R50: =IF(R49<>"",IF(R49+1>89,"",R49+1),"")
B53: Reserva de Corto Plazo
B54: Actigob
B55: Actimed
B57: Acumulación
B58: Renta Fija Local
B59: Altern
B60: Actdual
B61: Maximo
B62: Actigana+
B63: Actigana+2
B64: Renta Fija en USD | D64: *Tomar rendimientos en pesos
B65: Acticob
B66: Escala
B67: Renta Variable Indizados
B68: Activar
B69: Acti500
B71: Retiro
B72: Act2025
B73: Act2030
B74: Act2035
B75: Act2040
B76: Act4560

Sheet Patrimonio Financiero
CQ3: Formato: PF-01
CQ4: Versión 1.0
CQ5: mayo-2025
CD7: ='Entrevista Patrimonio F.'!O2 -> 46083
E8: Planeación Financiera
E9: Nombre: | L9: ='Entrevista Patrimonio F.'!E7 -> JUAN PEREZ | BQ9: Asesor:
E11: Edad: | M11: ='Entrevista Patrimonio F.'!E9 -> 50 | BQ11: Correo:
BQ13: Teléfono:
E14: DIAGNÓSTICO PATRIMONIO FINANCIERO
E17: I) VALOR DINERO EN EL TIEMPO
E18: (Liquidez Invertida + Portafolio de Inversión)
CL25: Promedio histórico de un portafolio con mayor proporción equity americana Duplica la inversión cada 5 años
CL37: Promedio histórico 20 años de un portafolio balanceado equity americano y deuda mexicana Duplica la inversión cada 6 años
CL51: Promedio histórico de un portafolio con mayor proporción en deuda mexicana Duplica la inversión cada 9 años
CL59: *Rendimientos pasados no garantizan rendimientos futuros
E65: II) ANÁLISIS DE TÚ PATRIMONIO FINANCIERO
E67: RESERVA CORTO PLAZO | AN67: RIQUEZA (ACUMULACIÓN) | BW67: RETIRO
E69: Tu reserva de corto plazo debe cubrir al menos 3 meses de tus gastos básicos. Será tu bolsa para eventualidades y objetivos de corto plazo. | AN69: =Auxiliar!G12 -> Considerando tu patrimonio financiero actual, puedes cubrir tus gastos totales anuales por 2.92 años. | BW69: Considerando únicamente tus saldos ACTUALES en esquema de retiro, tus ingresos mensuales estarían conformados por:
E74: Mi reserva actual | AN74: =Auxiliar!G13 -> Tienes tus gastos cubiertos hasta los 53 años de edad. | BW74: Saldo en esquemas de retiro | CT74: ='Cálculos y Supuestos Edo.Res'!G35 -> 1000000
E75: (Saldo en débito e inversiones líquidas) | X75: ='Cálculos y Supuestos Edo.Res'!C29 -> 200000 | BW75: (Saldo en afore y esquemas voluntarios)
AN77: Patrimonio financiero actual | BG77: ='Cálculos y Supuestos Edo.Res'!G22 -> 2100000
E78: Mis gastos básicos mensuales | X78: ='Cálculos y Supuestos Edo.Res'!C23 -> 40000 | AN78: (Inversiones + Seguros)
E80: Reserva deseable | X80: ='Cálculos y Supuestos Edo.Res'!G14 -> 120000 | AN80: Gastos totales al año | BG80: =Auxiliar!J18 -> 720000
E81: (Gastos básicos x 3)
E83: Bolsa de Emergencia: | X83: =X75-X80 -> 80000
X84: ='Cálculos y Supuestos Edo.Res'!G16 -> Excedido | BW84: =Auxiliar!G27 -> Total de mensualidad en retiro: $ 38,552
E101: III) TU PATRIMONIO FINANCIERO ACTUAL A LO LARGO DE TU CICLO DE VIDA
E104: Calidad vida objetivo: | AI104: ='Cálculos y Supuestos Edo.Res'!C13 -> 50000
E105: Gasto mensual deseado en retiro
E107: Total esquemas de retiro: | AI107: ='Cálculos y Supuestos Edo.Res'!G33 -> 38551.559
E109: Otros Ingresos: | AI109: =SUM('Cálculos y Supuestos Edo.Res'!C17:C18) -> 10000
E112: =Auxiliar!G29 -> Total de ingreso mensual en retiro : | AI112: =Auxiliar!I29 -> 48551.559
E114: =Auxiliar!G31 -> Tendrías un faltante mensual de: | AI114: =Auxiliar!I31 -> -1448.4412
E116: =Auxiliar!G33 -> Si ahorras durante 10 años (años hasta tu edad de retiro) puedes incrementar tus posibilidades al momento del retiro. | BC116: La suma de tu capital humano por acumular, más tus recursos financieros totales es el monto total que dispondrás para hacer frente a la etapa del retiro.
E119: Aportación mensual necesaria para alcanzar tu calidad de vida en edad de retiro: | BD119: Patrimonio Financiero Actual: | CO119: ='Cálculos y Supuestos Edo.Res'!G51 -> 2300000
AI121: ='Cálculos y Supuestos Edo.Res'!G54 -> 0 | BD121: Ahorro potencial acumulado: | CO121: ='Cálculos y Supuestos Edo.Res'!G50 -> 0
BD123: Total actual para etapa de desacumulación: | CO123: ='Cálculos y Supuestos Edo.Res'!G52 -> 2300000
E124: Capacidad de Ahorro | AI124: ='Cálculos y Supuestos Edo.Res'!G10 -> 50000 | BD124: (valor presente)
E126: Aportación (M) a mi Patrimonio Financiero: | AI126: 0 | BD126: Total requerido para etapa de retiro: | CO126: ='Cálculos y Supuestos Edo.Res'!G49 -> 407492.96
BD127: (valor presente)
E128: Con estas aportaciones, alcanzarás un ahorro acumulado de: | AI128: ='Cálculos y Supuestos Edo.Res'!G50 -> 0
BH129: Considerando tu calidad de vida esperada y el total acumulado para hacer frente al retiro, tendrás un:
BS132: =Auxiliar!G30 -> SUPERÁVIT | CA132: ='Cálculos y Supuestos Edo.Res'!G53 -> 1892507
E136: Disposición Mensual: | S136: =Desacumulación!I7 -> 1448.4412
R161: Patrimonio Financiero: | AG161: ='Cálculos y Supuestos Edo.Res'!H51 -> 2541787.3 | BA161: Ahorro Potencial: | BL161: ='Cálculos y Supuestos Edo.Res'!H50 -> 0 | CF161: Total: | CJ161: =AG161+BL161 -> 2541787.3
E165: IV. PROTECCIÓN PATRIMONIAL
I167: SEGURO DE VIDA + EXCESO | BJ167: PROTEGE TU PROPIEDAD
I169: =Auxiliar!G35 -> Protege a tus dependientes por una suma que cubra al menos 0.1 años de tus gastos básicos, para alcanzar una protección de 3 años. | BJ169: =Auxiliar!G37 -> Protege tu propiedad por al menos una suma asegurada de:
BT173: Suma Asegurada
M174: Suma Asegurada | AB174: Costo Prima Anual
BM179: *Valor estimado de la propiedad en función de la renta
L180: *Si ya cuentas con un seguro de vida considera una extensión
E185: V. OBJETIVOS Y PLAN DE ACCIÓN
E187: METAS OBJETIVOS PERSONALES | BH187: CORTO PLAZO (MENOR A 1 AÑO)
E188: Tu capacidad de ahorro actual es: | AN188: ='Cálculos y Supuestos Edo.Res'!G10 -> 50000 | BH188: ¿Tienes otros objetivos de CP independiente de la bolsa de emergencia?
E190: Aportación (Patrimonio Financiero): | AN190: =AI126 -> 0 | BH190: Objetivo | CB190: Meta | CR190: Plazo (meses)
E192: Tu flujo disponible para destinar a objetivos: | AN192: =MAX(AN188-AN190,0) -> 50000 | BH192: Imprevistos y Mer | CB192: 290000 | CR192: =IFERROR(((NPER(('Cálculos y Supuestos Edo.Res'!C4)/12,AE196,CB192,0,1)*-1)),0) -> 19.171386
E194: Superavit actual disponible para destinar a objetivos: | AN194: =IF(CO119>CO126,CO126-CO119,0)*-1 -> 1892507
E195: *De tus saldos en activos financieros excluyendo retiro | BH195: MEDIANO Y LARGO PLAZO (ACUMULACIÓN)
E196: ¿Cuánto destinarás a estos objetivos? | AE196: 15000 | AP196: 150000 | BH196: ¿Tienes otros objetivos de mediano y largo plazo?
AE197: Mensual | AP197: Anual
BH198: Objetivo | CB198: Meta | CR198: Plazo (años)
AP200: 400000 | BH200: Objetivo 1 | CB200: 1000000 | CR200: =IFERROR(Objetivos!C31/12,Objetivos!C31) -> 1.6666667
AP201: Con Superavit
BH202: Objetivo 2 | CB202: 900000 | CR202: =IFERROR(Objetivos!C38/12,Objetivos!C38) -> 2.4166667
BH204: Objetivo 3 | CB204: 100000 | CR204: =IFERROR(Objetivos!C45/12,Objetivos!C45) -> 0.58333333
BH206: Objetivo 4 | CB206: 5000000 | CR206: =IFERROR(Objetivos!C52/12,Objetivos!C52) -> Saldo Insuficiente
BH208: Objetivo 5 | CB208: 2500000 | CR208: =IFERROR(Objetivos!C59/12,Objetivos!C59) -> Saldo Insuficiente
BH210: Objetivos de Personales | CQ210: =MAX(CB200+CB202+CB204+CB206+CB208,0)+MAX(CB192,0) -> 9790000
BH212: Alcanzarás todos tus objetivos a los: | CT212: ='Entrevista Patrimonio F.'!E9+SUM(CR200:DA208) -> 54.666667
BH213: *Tu edad de retiro: | BS213: ='Entrevista Patrimonio F.'!G36 -> 60

Sheet Entrevista Balance
C3: GENERALES DE CLIENTE | F3: PATRIMONIO NO FINANCIERO
C4: Nombre o alias: | D4: JUAN PEREZ | F4: ¿Cuál es el valor de tu casa?
C6: Edad Actual | D6: 50 | F6: ¿Cuál es el valor de tus inmuebles en renta? | G6: 1000000
C8: Ocupación actual | D8: Asalariado | F8: ¿Cuál es el valor de tus inmuebles no productivos? (Tierra y propiedades no en renta) | G8: 0
C10: Dependientes Económicos | D10: Sí | F10: Saldo pendiente en hipoteca | G10: 0
F12: ¿Cuál es el valor en negocios que tienes? (equity) | G12: 0
C14: PATRIMONIO FINANCIERO | F14: ¿Cuál es la herencia que dispondrás? | G14: 0
C15: ¿Cuál es el monto de tus los ahorros de los que puedes disponer de forma inmediata? | D15: 0
C17: ¿A cuánto asciende tu saldo en otras inversiones financieras? | D17: 6000000 | F17: OBLIGACIONES PENDIENTES (LIQUIDAR)
C19: ¿Cuál es el monto contratado otros planes de seguro de acumulación? | D19: 0 | F19: Saldo pendiente en planes de retiro | G19: 0
F21: Compromisos futuros | G21: 1000000
C23: ESQUEMAS DE RETIRO
C24: ¿Cuál es el saldo de tu cuenta de Afore? | D24: 0 | F24: INGRESOS / OBLIGACIONES MENSUALES
C26: ¿Cuál es el saldo en tu PPR? | D26: 0 | F26: ¿A cuánto ascienden tus gastos hoy? | G26: 300000
C28: ¿Cuál es el saldo en Plan privado de pensión? | D28: 0 | F28: ¿Cuál es tu capacidad de Ahorro? | G28: 50000
C30: ¿Cuál es el saldo otros planes de seguro para el retiro? | D30: 0 | F30: ¿Cuál es tu ingreso mensual por propiedades en rentas? | G30: 20000
C32: ¿Cuál es tu mensualidad aproximada por la Ley 73? | D32: 0 | F32: ¿Cuál es el monto mensual de otros ingresos? | G32: 0
C34: ¿A qué edad planeas retirarte? | D34: 60
C36: ¿Cuánto deseas percibir mensualmente en tu edad de retiro? | D36: 50000

Sheet Cálculos y Supuestos Balance
H2: Auxiliares Gráficas y Textos
B3: Tasa Real | C3: 0.01
B4: Edad de Defunción | C4: 90 | H4: III) TU PATRIMONIO FINANCIERO ACTUAL A LO LARGO DE TU CICLO DE VIDA
B5: Cap Rate Propiedades | C5: 0.05 | H5: ="Si ahorras durante "&TEXT(EdaddeRetiro-EdadActual,"#0")&" años (años hasta tu edad de retiro) puedes incrementar tus posibilidades al momento del retiro." -> Si ahorras durante 10 años (años hasta tu edad de retiro) puedes incrementar tus posibilidades al momento del retiro. | Y5: Disponible del Ingreso Activo | Z5: =CapacidaddeAhorro-Z6 -> 30000 | AA5: =1-AA6 -> 0.6 | AB5: se genera de tu fuente principal de ingresos | AV5: Edad de Retiro | AX5: Género
B6: Costo Seguro de Vida por Millón | C6: 7000 | Y6: Ingresos Pasivos Disponible | Z6: =MIN(Z7+Z8,CapacidaddeAhorro) -> 20000 | AA6: ='Cálculos y Supuestos Balance'!Z6/CapacidaddeAhorro -> 0.4 | AB6: se genera gracias a los Activos Productivos | AV6: =IF(EdadActual+1>80,"",EdadActual+1) -> 51 | AX6: Hombre
Y7: Ingresos por Rentas | Z7: =Rentas -> 20000 | AA7: =IFERROR(('Cálculos y Supuestos Balance'!Z7*12)/(Balance!V12),0) -> 0.24 | AB7: Rentabilidad anual correspondiente a tus activos excepto negocio | AV7: =IF(AV6<>"",IF(AV6+1>80,"",AV6+1),"") -> 52 | AX7: Mujer
B8: Cálculos | Y8: Ingresos por Negocios | Z8: =OtrosIngresos -> 0 | AA8: =IFERROR(('Cálculos y Supuestos Balance'!Z8*12)/Balance!V18,0) -> 0 | AB8: Rentabilidad anual del negocio | AV8: =IF(AV7<>"",IF(AV7+1>80,"",AV7+1),"") -> 53 | AX8: Otro
AV9: =IF(AV8<>"",IF(AV8+1>80,"",AV8+1),"") -> 54 | AX9: Prefiero no contestar
B10: Saldo en Esquemas de Retiro | C10: =Afore+PPR+PlanPrivadodePensión+OtrosPlanesdeSegurosparaRetiro -> 0 | Y10: Fuentes Flujo Disponible | AV10: =IF(AV9<>"",IF(AV9+1>80,"",AV9+1),"") -> 55
B11: Mensualidad Afore | C11: =PMT(1%/12,(EdaddeDefunción-MAX(60,EdaddeRetiro))*12,((Afore*(1+1%/12)^((MAX(60,EdaddeRetiro)-EdadActual)*12))),0,1)*-1 -> 0 | Y11: Ingreso Total | Z11: ='Entrevista Balance'!G26+CapacidaddeAhorro -> 350000 | AA11: =Z11/SUM($Z$12:$Z$14) -> 1 | AV11: =IF(AV10<>"",IF(AV10+1>80,"",AV10+1),"") -> 56
B12: Mensualidad Pensión Voluntaria | C12: =PMT(1%/12,(EdaddeDefunción-MAX(60,EdaddeRetiro))*12,(((PPR+PlanPrivadodePensión+OtrosPlanesdeSegurosparaRetiro)*(1+1%/12)^((MAX(60,EdaddeRetiro)-EdadActual)*12))),0,1)*-1 -> 0 | Y12: Total Gasto | Z12: ='Entrevista Balance'!G26 -> 300000 | AA12: =Z12/SUM($Z$12:$Z$14) -> 0.85714286 | AV12: =IF(AV11<>"",IF(AV11+1>80,"",AV11+1),"") -> 57
B13: Pension Estimada | C13: =MLey73 -> 0 | Y13: Disponible Ingreso Activo | Z13: =Z5 -> 30000 | AA13: =Z13/SUM($Z$12:$Z$14) -> 0.085714286 | AV13: =IF(AV12<>"",IF(AV12+1>80,"",AV12+1),"") -> 58
B14: Mensualidad Actual | C14: =C11+C12+C13 -> 0 | Y14: Disponible Ingreso Pasivo | Z14: =Z6 -> 20000 | AA14: =Z14/SUM($Z$12:$Z$14) -> 0.057142857 | AV14: =IF(AV13<>"",IF(AV13+1>80,"",AV13+1),"") -> 59
AV15: =IF(AV14<>"",IF(AV14+1>80,"",AV14+1),"") -> 60
B16: Mensualidad por otros ingresos | C16: =Rentas+OtrosIngresos -> 20000 | AV16: =IF(AV15<>"",IF(AV15+1>80,"",AV15+1),"") -> 61
AV17: =IF(AV16<>"",IF(AV16+1>80,"",AV16+1),"") -> 62
B18: Pasivo del Retiro al inicio de la jubilación | C18: =MensualidaddeseadaenelRetiro-C14-C16 -> 30000 | D18: Para acumular con capital humano | AV18: =IF(AV17<>"",IF(AV17+1>80,"",AV17+1),"") -> 63
AV19: =IF(AV18<>"",IF(AV18+1>80,"",AV18+1),"") -> 64 | AX19: Ocupación Actual
B20: Número de periodos desacumulación | C20: =( EdaddeDefunción - EdaddeRetiro ) * 12 -> 360 | S20: Gráfica Regla del 72 | Y20: Gráfica Balance | AV20: =IF(AV19<>"",IF(AV19+1>80,"",AV19+1),"") -> 65 | AX20: Asalariado
B21: Tipo | C21: =1 / ( 1 + TasaReal / 12 ) -> 0.99916736 | S21: Monto Invertido | T21: =ReservaCortoPlazo+Acumulación -> 6000000 | Y21: Activos Financieros | Z21: =Balance!E25 -> 6000000 | AV21: =IF(AV20<>"",IF(AV20+1>80,"",AV20+1),"") -> 66 | AX21: Independiente
B22: Patrimonio Financiero Actual Total | C22: =ReservaCortoPlazo + Acumulación -> 6000000 | Y22: Activos No Financieros | Z22: =Balance!V25 -> 1000000 | AV22: =IF(AV21<>"",IF(AV21+1>80,"",AV21+1),"") -> 67 | AX22: Empresario
B23: Número de periodos acumulación | C23: =( EdaddeRetiro - EdadActual ) *12 -> 120 | T23: 0.08 | U23: 0.12 | V23: 0.14 | AV23: =IF(AV22<>"",IF(AV22+1>80,"",AV22+1),"") -> 68
S24: =EdadActual -> 50 | T24: =1*Montoaproximadodeinversión -> 6000000 | U24: =1*Montoaproximadodeinversión -> 6000000 | V24: =1*Montoaproximadodeinversión -> 6000000 | Y24: Obligaciones | Z24: =Balance!AM25 -> 1000000 | AV24: =IF(AV23<>"",IF(AV23+1>80,"",AV23+1),"") -> 69 | AX24: Sí/No
B25: Esquemas de Retiro | S25: =S24+1 -> 51 | Y25: Patrimonio Neto | Z25: =Balance!BD25 -> 6000000 | AV25: =IF(AV24<>"",IF(AV24+1>80,"",AV24+1),"") -> 70 | AX25: Sí
B26: Valor Actual en planes privados de Retiro | C26: =( ( (PPR+PlanPrivadodePensión+OtrosPlanesdeSegurosparaRetiro)* ( 1 + TasaReal / 12 ) ^ ( ( MAX(60,EdaddeRetiro) - EdadActual ) * 12 ) ) ) -> 0 | S26: =S25+1 -> 52 | AV26: =IF(AV25<>"",IF(AV25+1>80,"",AV25+1),"") -> 71 | AX26: No
B27: Saldo en Planes privados de Retiro VF | C27: =( C26 * ( 1 + TasaReal / 12 ) ^ ( ( MAX(60,EdaddeRetiro) - EdadActual ) * 12 ) ) -> 0 | S27: =S26+1 -> 53 | AV27: =IF(AV26<>"",IF(AV26+1>80,"",AV26+1),"") -> 72
B28: Valor Actual Esquemas de Pension | C28: =( ( (Afore)* ( 1 + TasaReal / 12 ) ^ ( ( MAX(60,EdaddeRetiro) - EdadActual ) * 12 ) ) ) -> 0 | S28: =S27+1 -> 54 | Y28: Gráfica Conformación del Patrimonio Total | AV28: =IF(AV27<>"",IF(AV27+1>80,"",AV27+1),"") -> 73 | AX28: Periodicidad
B29: Saldo en Esquemas de Pensión VF | C29: =( ValorActualEsquemasdePension * ( 1 + TasaReal / 12 ) ^ ( ( MAX(60,EdaddeRetiro) - EdadActual ) * 12 ) ) -> 0 | S29: =S28+1 -> 55 | V29: =2*Montoaproximadodeinversión -> 12000000 | X29: Ret | Y29: Retiro | Z29: =Balance!E18 -> 0 | AA29: =Z29/SUM($Z$29:$Z$33) -> 0 | AV29: =IF(AV28<>"",IF(AV28+1>80,"",AV28+1),"") -> 74 | AX29: Mensual
S30: =S29+1 -> 56 | U30: =2*Montoaproximadodeinversión -> 12000000 | X30: ANFP | Y30: Activos No Financieros Productivos | Z30: =Balance!V12+Balance!V18 -> 1000000 | AA30: =Z30/SUM($Z$29:$Z$33) -> 0.14285714 | AV30: =IF(AV29<>"",IF(AV29+1>80,"",AV29+1),"") -> 75 | AX30: Trimestral
B31: Fondo necesario al inicio del retiro | C31: =AN71 -> 9327212 | S31: =S30+1 -> 57 | X31: ANFI | Y31: Activos No Financieros Improductivos | Z31: =Balance!V25-Z30 -> 0 | AA31: =Z31/SUM($Z$29:$Z$33) -> 0 | AV31: =IF(AV30<>"",IF(AV30+1>80,"",AV30+1),"") -> 76 | AX31: Semestral
S32: =S31+1 -> 58 | X32: Ac | Y32: Acumulación | Z32: =Balance!E12+Balance!E15 -> 6000000 | AA32: =Z32/SUM($Z$29:$Z$33) -> 0.85714286 | AV32: =IF(AV31<>"",IF(AV31+1>80,"",AV31+1),"") -> 77 | AX32: Anual
B33: Patrimonio Actual | C33: =Balance!E25 -> 6000000 | S33: =S32+1 -> 59 | T33: =2*Montoaproximadodeinversión -> 12000000 | X33: Liq | Y33: Liquidez | Z33: =Balance!E9 -> 0 | AA33: =Z33/SUM($Z$29:$Z$33) -> 0 | AV33: =IF(AV32<>"",IF(AV32+1>80,"",AV32+1),"") -> 78
B34: Patrimonio Financiero Actual Total VF | C34: =( PatrimonioFinancieroActualTotal * ( 1 + TasaReal / 12 ) ^ ( ( EdaddeRetiro - EdadActual ) * 12 ) ) + ( PlanesdeSeguroAcumulación1 * ( 1 + TasaReal / 12 ) ^ ( ( EdaddeRetiro - ( EdadActual ) ) * 12 ) ) -> 6630749.4 | S34: =S33+1 -> 60 | V34: =4*Montoaproximadodeinversión -> 24000000 | AV34: =IF(AV33<>"",IF(AV33+1>80,"",AV33+1),"") -> 79
B35: Patrimonio Actual Total VF | C35: =PatrimonioFinancieroActualTotalVF -> 6630749.4 | D35: Crecimiento del patrimonio financiero actual | S35: =S34+1 -> 61 | AV35: =IF(AV34<>"",IF(AV34+1>80,"",AV34+1),"") -> 80
S36: =S35+1 -> 62 | U36: =4*Montoaproximadodeinversión -> 24000000 | AV36: =IF(AV35<>"",IF(AV35+1>80,"",AV35+1),"")
B37: Obligaciones Actuales | C37: =Balance!AM25 -> 1000000 | S37: =S36+1 -> 63 | AV37: =IF(AV36<>"",IF(AV36+1>80,"",AV36+1),"")
B38: Obligaciones VF | C38: =C37 -> 1000000 | S38: =S37+1 -> 64 | AV38: =IF(AV37<>"",IF(AV37+1>80,"",AV37+1),"")
S39: =S38+1 -> 65 | V39: =8*Montoaproximadodeinversión -> 48000000 | Y39: Índice de solvencia | Z39: =MAX(((Balance!V25+Balance!E25-Balance!V21-Balance!E18)-(Balance!AM9+Balance!AM12+Balance!AM15))/(Balance!V25+Balance!E25-Balance!V21-Balance!E18),0) -> 0.85714286 | AA39: =MAX(Z41:Z45) -> 0.85714286 | AB39: =VLOOKUP(AA39,$Z$41:$AA$45,2,0) -> Tienes un nivel de solvencia excelente que te permite apalancarte en tus activos para seguir creciendo tu patrimonio. | AD39: (activos totales - saldos de retiro - obligaciones) / activos totales | AV39: =IF(AV38<>"",IF(AV38+1>80,"",AV38+1),"")
B40: Patrimonio Financiero Neto al Momento del Retiro | C40: =C35-C38 -> 5630749.4 | S40: =S39+1 -> 66 | Y40: Gráfica Índice de solvencia | AV40: =IF(AV39<>"",IF(AV39+1>80,"",AV39+1),"")
S41: =S40+1 -> 67 | Y41: Baja | Z41: =IF(AND(Z39>0%,Z39<=30%),Z39,0) -> 0 | AA41: Tienes un nivel de solvencia bajo. Incrementalo para poder apalancarte en tus activos y seguir creciendo tu patrimonio | AV41: =IF(AV40<>"",IF(AV40+1>80,"",AV40+1),"")
B42: Calidad de Vida en Retiro sin Capital Humano y Sin Ingresos por Ventas | C42: =PMT(1%/12,(EdaddeDefunción-EdaddeRetiro)*12,((C40*(1+1%/12)^((EdaddeRetiro-EdadActual)*12))),0,1)*-1 -> 19997.937 | S42: =S41+1 -> 68 | T42: =4*Montoaproximadodeinversión -> 24000000 | U42: =8*Montoaproximadodeinversión -> 48000000 | Y42: Suficiente | Z42: =IF(AND(Z39>30%,Z39<=50%),Z39,0) -> 0 | AA42: Tienes un nivel de solvencia suficiente. Incrementalo para poder apalancarte en tus activos y seguir creciendo tu patrimonio | AV42: =IF(AV41<>"",IF(AV41+1>80,"",AV41+1),"")
S43: =S42+1 -> 69 | Y43: Alta | Z43: =IF(AND(Z39>50%,Z39<=70%),Z39,0) -> 0 | AA43: Tienes un nivel de solvencia alto que te permite apalancarte en tus activos para seguir creciendo tu patrimonio. | AV43: =IF(AV42<>"",IF(AV42+1>80,"",AV42+1),"")
B44: Ingreso por Venta de Casa Propia | C44: =Balance!N126 -> 2000000 | S44: =S43+1 -> 70 | Y44: Excelente | Z44: =IF(Z39>70%,Z39,0) -> 0.85714286 | AA44: Tienes un nivel de solvencia excelente que te permite apalancarte en tus activos para seguir creciendo tu patrimonio. | AV44: =IF(AV43<>"",IF(AV43+1>80,"",AV43+1),"")
B45: Edad de Venta | C45: =Balance!U124 -> 77 | D45: años | S45: =S44+1 -> 71 | V45: =16*Montoaproximadodeinversión -> 96000000 | Y45: Faltante | Z45: =1-Z39 -> 0.14285714 | AA45: No tienes solvencia | AV45: =IF(AV44<>"",IF(AV44+1>80,"",AV44+1),"")
B46: Venta Si = 1 / No = 0 | C46: =IF(Balance!H124="Sí",1,0) -> 0 | S46: =S45+1 -> 72 | AV46: =IF(AV45<>"",IF(AV45+1>80,"",AV45+1),"")
B47: Saldo Inicio de Retiro por venta de Casa Propia | C47: =C44 / (1 + TasaReal)^(C45-EdaddeRetiro)*C46 -> 0 | S47: =S46+1 -> 73 | AV47: =IF(AV46<>"",IF(AV46+1>80,"",AV46+1),"")
B48: Ingreso por Venta de Tierra | C48: =Balance!AL126 -> 0 | S48: =S47+1 -> 74 | U48: =16*Montoaproximadodeinversión -> 96000000 | AV48: =IF(AV47<>"",IF(AV47+1>80,"",AV47+1),"")
B49: Edad de Venta | C49: =Balance!AS124 -> 65 | D49: años | S49: =S48+1 -> 75 | AV49: =IF(AV48<>"",IF(AV48+1>80,"",AV48+1),"")
B50: Venta Si = 1 / No = 0 | C50: =IF(Balance!AE124="Sí",1,0) -> 1 | S50: =S49+1 -> 76 | V50: =32*Montoaproximadodeinversión -> 192000000 | AV50: =IF(AV49<>"",IF(AV49+1>80,"",AV49+1),"")
B51: Saldo Inicio de Retiro por venta de Tierra | C51: =C48 / (1 + TasaReal)^(C49-EdaddeRetiro)*C50 -> 0 | S51: =S50+1 -> 77 | T51: =8*Montoaproximadodeinversión -> 48000000 | AV51: =IF(AV50<>"",IF(AV50+1>80,"",AV50+1),"")
B52: Ingreso por Venta de Inmuebles en Renta | C52: =Balance!BL126 -> 1000000 | S52: =S51+1 -> 78
B53: Edad de Venta | C53: =Balance!BS124 -> 66 | D53: años | S53: =S52+1 -> 79
B54: Venta Si = 1 / No = 0 | C54: =IF(Balance!BC124="Sí",1,0) -> 0 | S54: =S53+1 -> 80 | U54: =32*Montoaproximadodeinversión -> 192000000
B55: Saldo Inicio de Retiro por venta de Inmuebles en Renta | C55: =C52 / (1 + TasaReal)^(C53-EdaddeRetiro)*C54 -> 0 | S55: =S54+1 -> 81 | V55: =64*Montoaproximadodeinversión -> 384000000 | Y55: Gráfica Potencial Apalancamiento
B56: Ingreso por Venta de Negocio | C56: =Balance!CH126 -> 0 | S56: =S55+1 -> 82 | Z56: Índice de Apalancamiento | AA56: Potencial Apalancamiento | AB56: Potencial Apalancamiento
B57: Edad de Venta | C57: =Balance!CO124 -> 60 | D57: años | S57: =S56+1 -> 83 | Y57: Serie 1 | Z57: =Balance!BW22-Balance!E18-Balance!V21-AA57-AB57 -> 3500000 | AA57: =Balance!AM25 -> 1000000 | AB57: =Balance!Y74 -> 2500000
B58: Venta Si = 1 / No = 0 | C58: =IF(Balance!CC124="Sí",1,0) -> 0 | S58: =S57+1 -> 84 | Y58: Serie 2 | Z58: 0 | AA58: 0 | AB58: ='Potencial del balance'!D40 -> 3500000
B59: Saldo Inicio de Retiro por venta de Negocio | C59: =C56 / (1 + TasaReal)^(C57-EdaddeRetiro)*C58 -> 0 | S59: =S58+1 -> 85
B60: Ingreso x Herencia | C60: ='Entrevista Balance'!G14 -> 0 | S60: =S59+1 -> 86 | T60: =16*Montoaproximadodeinversión -> 96000000 | U60: =64*Montoaproximadodeinversión -> 384000000 | V60: =128*Montoaproximadodeinversión -> 768000000
B61: Edad en que se recibe | C61: 70 | D61: años | S61: =S60+1 -> 87 | Y61: Cálculos para Fondo necesario al inicio del retiro | AB61: Pasivo Mensual Total Retiro: | AC61: =C18 -> 30000
B62: Venta Si = 1 / No = 0 | C62: =IF(C60>0,1,0) -> 0 | S62: =S61+1 -> 88
B63: Saldo Inicio de Retiro por Herencia | C63: =C60 / (1 + TasaReal)^(C61-EdaddeRetiro)*C62 -> 0 | S63: =S62+1 -> 89 | X63: Orden | Y63: Activo | Z63: Venta Si = 1 / No = 0 | AA63: Edad de Venta | AB63: Ingreso Obtenido | AC63: Nuevo Pasivo | AE63: Orden ajustado | AF63: Valor Vendido | AG63: Nuevo Pasivo | AH63: Inicio Tramo | AI63: Fin Tramo | AJ63: Numero de Años | AK63: Periodos para inicio | AL63: Numero de Periodos | AM63: Pasivo del Tramo | AN63: Requerido x Tramo | AO63: Periodo Inicio | AP63: Periodo Fin | AQ63: Pasivo del Periodo
S64: =S63+1 -> 90 | X64: =_xlfn.RANK.EQ(AA64,$AA$64:$AA$69,1) -> 1 | Y64: Venta Casa Propia | Z64: =C46 -> 0 | AA64: =Balance!U124*Z64 -> 0 | AB64: =Balance!N126*Z64 -> 0 | AC64: =Balance!O128*Z64 -> 0 | AE64: 0 | AF64: 0 | AG64: 0 | AH64: =MAX(EdaddeRetiro,60) -> 60 | AI64: =IF(AH65>0,AH65,IF(AND(AH65=0,AH66>0),AH66,IF(AND(AH65=0,AH66=0,AH67>0),AH67,IF(AND(AH65=0,AH66=0,AH67=0,AH68>0),AH68,IF(AND(AH65=0,AH66=0,AH67=0,AH68=0,AH69>0),AH69,IF(AND(AH65=0,AH66=0,AH67=0,AH68=0,AH69=0,AH70>0),AH70,EdaddeDefunción)))))) -> 65 | AJ64: =MAX(IF(AH64=0,0,1*AI64-AH64),0) -> 5 | AK64: =MAX((AH64-EdaddeRetiro)*12,0) -> 0 | AL64: =AJ64*12 -> 60 | AM64: =AC61 -> 30000 | AN64: =IFERROR( AM64 * ((1 - (1 + (TasaReal/12))^(-AL64)) / (TasaReal/12)) * (1 + (TasaReal/12))^-AK64,0) -> 1755027.7 | AO64: =MAX(EdaddeRetiro,60) -> 60 | AP64: =IF(AN64>0,AI64,0) -> 65 | AQ64: =IF(AN64>0,AM64,0) -> 30000
B65: Saldo a Inicio de Retiro por Nuevos Ingresos | C65: =C47+C51+C55+C59+C63 -> 0 | S65: =S64+1 -> 91 | V65: =256*Montoaproximadodeinversión -> 1536000000 | X65: =_xlfn.RANK.EQ(AA65,$AA$64:$AA$69,1) -> 6 | Y65: Venta Tierra | Z65: =C50 -> 1 | AA65: =Balance!AS124*Z65 -> 65 | AB65: =Balance!AL126*Z65 -> 0 | AC65: 0 | AE65: 1 | AF65: =SUMIF($X$64:$X$68,AE65,$AB$64:$AB$69) -> 0 | AG65: =SUMIF($X$64:$X$69,AE65,$AC$64:$AC$69) -> 0 | AH65: =IFERROR(VLOOKUP(AE65,$X$64:$AA$69,4,0),0) -> 0 | AI65: =IF(AH66>0,AH66,IF(AND(AH66=0,AH67>0),AH67,IF(AND(AH66=0,AH67=0,AH68>0),AH68,IF(AND(AH66=0,AH67=0,AH68=0,AH69>0),AH69,IF(AND(AH66=0,AH67=0,AH68=0,AH69=0,AH70>0),AH70,EdaddeDefunción))))) -> 65 | AJ65: =MAX(IF(AH65=0,0,1*AI65-AH65),0) -> 0 | AK65: =MAX((AH65-EdaddeRetiro)*12,0) -> 0 | AL65: =AJ65*12 -> 0 | AM65: =AM64+AG65 -> 30000 | AN65: =IFERROR( AM65 * ((1 - (1 + (TasaReal/12))^(-AL65)) / (TasaReal/12)) * (1 + (TasaReal/12))^-AK65,0) -> 0 | AO65: =IF(AN65>0,AH65,0) -> 0 | AP65: =IF(AN65>0,AI65,0) -> 0 | AQ65: =IF(AN65>0,AM65,0) -> 0
S66: =S65+1 -> 92 | U66: =128*Montoaproximadodeinversión -> 768000000 | X66: =_xlfn.RANK.EQ(AA66,$AA$64:$AA$69,1) -> 1 | Y66: Venta Inmuebles en Renta | Z66: =C54 -> 0 | AA66: =Balance!BS124*Z66 -> 0 | AB66: =Balance!BL126*Z66 -> 0 | AC66: =Balance!BL128*Z66 -> 0 | AE66: 2 | AF66: =SUMIF($X$64:$X$68,AE66,$AB$64:$AB$69) -> 0 | AG66: =SUMIF($X$64:$X$69,AE66,$AC$64:$AC$69) -> 0 | AH66: =IFERROR(VLOOKUP(AE66,$X$64:$AA$69,4,0),0) -> 0 | AI66: =IF(AH67>0,AH67,IF(AND(AH67=0,AH68>0),AH68,IF(AND(AH67=0,AH68=0,AH69>0),AH69,IF(AND(AH67=0,AH68=0,AH69=0,AH70>0),AH70,EdaddeDefunción)))) -> 65 | AJ66: =MAX(IF(AH66=0,0,1*AI66-AH66),0) -> 0 | AK66: =MAX((AH66-EdaddeRetiro)*12,0) -> 0 | AL66: =AJ66*12 -> 0 | AM66: =AM65+AG66 -> 30000 | AN66: =IFERROR( AM66 * ((1 - (1 + (TasaReal/12))^(-AL66)) / (TasaReal/12)) * (1 + (TasaReal/12))^-AK66,0) -> 0 | AO66: =IF(AN66>0,AH66,0) -> 0 | AP66: =IF(AN66>0,AI66,0) -> 0 | AQ66: =IF(AN66>0,AM66,0) -> 0
B67: Capital Disponible a Inicio del Retiro | C67: =C40+C65 -> 5630749.4 | S67: =S66+1 -> 93 | X67: =_xlfn.RANK.EQ(AA67,$AA$64:$AA$69,1) -> 1 | Y67: Venta Negocio | Z67: =C58 -> 0 | AA67: =Balance!CO124*Z67 -> 0 | AB67: =Balance!CH126*Z67 -> 0 | AC67: =Balance!CH128*Z67 -> 0 | AE67: 3 | AF67: =SUMIF($X$64:$X$68,AE67,$AB$64:$AB$69) -> 0 | AG67: =SUMIF($X$64:$X$69,AE67,$AC$64:$AC$69) -> 0 | AH67: =IFERROR(VLOOKUP(AE67,$X$64:$AA$69,4,0),0) -> 0 | AI67: =IF(AH68>0,AH68,IF(AND(AH68=0,AH69>0),AH69,IF(AND(AH68=0,AH69=0,AH70>0),AH70,EdaddeDefunción))) -> 65 | AJ67: =MAX(IF(AH67=0,0,1*AI67-AH67),0) -> 0 | AK67: =MAX((AH67-EdaddeRetiro)*12,0) -> 0 | AL67: =AJ67*12 -> 0 | AM67: =AM66+AG67 -> 30000 | AN67: =IFERROR( AM67 * ((1 - (1 + (TasaReal/12))^(-AL67)) / (TasaReal/12)) * (1 + (TasaReal/12))^-AK67,0) -> 0 | AO67: =IF(AN67>0,AH67,0) -> 0 | AP67: =IF(AN67>0,AI67,0) -> 0 | AQ67: =IF(AN67>0,AM67,0) -> 0
S68: =S67+1 -> 94 | X68: =_xlfn.RANK.EQ(AA68,$AA$64:$AA$69,1) -> 1 | Y68: Herencia | Z68: =C62 -> 0 | AA68: =C61*Z68 -> 0 | AB68: =C60*Z68 -> 0 | AC68: 0 | AE68: 4 | AF68: =SUMIF($X$64:$X$68,AE68,$AB$64:$AB$69) -> 0 | AG68: =SUMIF($X$64:$X$69,AE68,$AC$64:$AC$69) -> 0 | AH68: =IFERROR(VLOOKUP(AE68,$X$64:$AA$69,4,0),0) -> 0 | AI68: =IF(AH69>0,AH69,IF(AND(AH69=0,AH70>0),AH70,EdaddeDefunción)) -> 65 | AJ68: =MAX(IF(AH68=0,0,1*AI68-AH68),0) -> 0 | AK68: =MAX((AH68-EdaddeRetiro)*12,0) -> 0 | AL68: =AJ68*12 -> 0 | AM68: =AM67+AG68 -> 30000 | AN68: =IFERROR( AM68 * ((1 - (1 + (TasaReal/12))^(-AL68)) / (TasaReal/12)) * (1 + (TasaReal/12))^-AK68,0) -> 0 | AO68: =IF(AN68>0,AH68,0) -> 0 | AP68: =IF(AN68>0,AI68,0) -> 0 | AQ68: =IF(AN68>0,AM68,0) -> 0
B69: DÉFICIT/SUPERAVIT a inicio del retiro | C69: =C67-C31 -> -3696462.6 | S69: =S68+1 -> 95 | T69: =32*Montoaproximadodeinversión -> 192000000 | X69: =_xlfn.RANK.EQ(AA69,$AA$64:$AA$69,1) -> 1 | Y69: Retiro Anticipado | Z69: =IF(EdaddeRetiro<60,1,0) -> 0 | AA69: =EdaddeRetiro*Z69 -> 0 | AB69: 0 | AC69: =C14*Z69 -> 0 | AE69: 5 | AF69: =SUMIF($X$64:$X$68,AE69,$AB$64:$AB$69) -> 0 | AG69: =SUMIF($X$64:$X$69,AE69,$AC$64:$AC$69) -> 0 | AH69: =IFERROR(VLOOKUP(AE69,$X$64:$AA$69,4,0),0) -> 0 | AI69: =IF(AH70>0,AH70,EdaddeDefunción) -> 65 | AJ69: =MAX(IF(AH69=0,0,1*AI69-AH69),0) -> 0 | AK69: =MAX((AH69-EdaddeRetiro)*12,0) -> 0 | AL69: =AJ69*12 -> 0 | AM69: =AM68+AG69 -> 30000 | AN69: =IFERROR( AM69 * ((1 - (1 + (TasaReal/12))^(-AL69)) / (TasaReal/12)) * (1 + (TasaReal/12))^-AK69,0) -> 0 | AO69: =IF(AN69>0,AH69,0) -> 0 | AP69: =IF(AN69>0,AI69,0) -> 0 | AQ69: =IF(AN69>0,AM69,0) -> 0
S70: =S69+1 -> 96 | V70: =512*Montoaproximadodeinversión -> 3072000000 | AE70: 6 | AF70: =SUMIF($X$64:$X$68,AE70,$AB$64:$AB$69) -> 0 | AG70: =SUMIF($X$64:$X$69,AE70,$AC$64:$AC$69) -> 0 | AH70: =IFERROR(VLOOKUP(AE70,$X$64:$AA$69,4,0),0) -> 65 | AI70: =EdaddeDefunción -> 90 | AJ70: =MAX(IF(AH70=0,0,1*AI70-AH70),0) -> 25 | AK70: =MAX((AH70-EdaddeRetiro)*12,0) -> 60 | AL70: =AJ70*12 -> 300 | AM70: =AM69+AG70 -> 30000 | AN70: =IFERROR( AM70 * ((1 - (1 + (TasaReal/12))^(-AL70)) / (TasaReal/12)) * (1 + (TasaReal/12))^-AK70,0) -> 7572184.3 | AO70: =IF(AN70>0,AH70,0) -> 65 | AP70: =IF(AN70>0,AI70,0) -> 90 | AQ70: =IF(AN70>0,AM70,0) -> 30000
B71: Aportación mensual necesaria | C71: =MAX(-C69 * (TasaReal/12) / ((1 + (TasaReal/12))^(Númerodeperiodosacumulación) - 1),0) -> 29302.151 | S71: =S70+1 -> 97 | AN71: =SUM(AN64:AN70) -> 9327212
S72: =S71+1 -> 98 | U72: =256*Montoaproximadodeinversión -> 1536000000
S73: =S72+1 -> 99
B74: Seguros | S74: =S73+1 -> 100 | Z74: =EdaddeRetiro -> 60 | AA74: =EdaddeRetiro+1 -> 61 | AB74: =EdaddeRetiro+2 -> 62 | AC74: =EdaddeRetiro+3 -> 63 | AD74: =EdaddeRetiro+4 -> 64 | AE74: =EdaddeRetiro+5 -> 65 | AF74: =EdaddeRetiro+6 -> 66 | AG74: =EdaddeRetiro+7 -> 67 | AH74: =EdaddeRetiro+8 -> 68 | AI74: =EdaddeRetiro+9 -> 69 | AJ74: =EdaddeRetiro+10 -> 70 | AK74: =EdaddeRetiro+11 -> 71 | AL74: =EdaddeRetiro+12 -> 72 | AM74: =EdaddeRetiro+13 -> 73 | AN74: =EdaddeRetiro+14 -> 74 | AO74: =EdaddeRetiro+15 -> 75 | AP74: =EdaddeRetiro+16 -> 76 | AQ74: =EdaddeRetiro+17 -> 77 | AR74: =EdaddeRetiro+18 -> 78 | AS74: =EdaddeRetiro+19 -> 79 | AT74: =EdaddeRetiro+20 -> 80 | AU74: =EdaddeRetiro+21 -> 81 | AV74: =EdaddeRetiro+22 -> 82 | AW74: =EdaddeRetiro+23 -> 83 | AX74: =EdaddeRetiro+24 -> 84 | AY74: =EdaddeRetiro+25 -> 85 | AZ74: =EdaddeRetiro+26 -> 86 | BA74: =EdaddeRetiro+27 -> 87 | BB74: =EdaddeRetiro+28 -> 88 | BC74: =EdaddeRetiro+29 -> 89 | BD74: =EdaddeRetiro+30 -> 90 | BE74: =EdaddeRetiro+31 -> 91 | BF74: =EdaddeRetiro+32 -> 92 | BG74: =EdaddeRetiro+33 -> 93 | BH74: =EdaddeRetiro+34 -> 94 | BI74: =EdaddeRetiro+35 -> 95 | BJ74: =EdaddeRetiro+36 -> 96 | BK74: =EdaddeRetiro+37 -> 97 | BL74: =EdaddeRetiro+38 -> 98 | BM74: =EdaddeRetiro+39 -> 99
B75: Seguro de Vida | S75: =S74+1 -> 101 | V75: =1024*Montoaproximadodeinversión -> 6144000000 | Y75: Venta Casa Propia | Z75: =IF(AND(Balance!$U$124='Cálculos y Supuestos Balance'!Z74,Balance!$H$124="Sí"),Balance!$N$126,0) -> 0 | AA75: =IF(AND(Balance!$U$124='Cálculos y Supuestos Balance'!AA74,Balance!$H$124="Sí"),Balance!$N$126,0) -> 0 | AB75: =IF(AND(Balance!$U$124='Cálculos y Supuestos Balance'!AB74,Balance!$H$124="Sí"),Balance!$N$126,0) -> 0 | AC75: =IF(AND(Balance!$U$124='Cálculos y Supuestos Balance'!AC74,Balance!$H$124="Sí"),Balance!$N$126,0) -> 0 | AD75: =IF(AND(Balance!$U$124='Cálculos y Supuestos Balance'!AD74,Balance!$H$124="Sí"),Balance!$N$126,0) -> 0 | AE75: =IF(AND(Balance!$U$124='Cálculos y Supuestos Balance'!AE74,Balance!$H$124="Sí"),Balance!$N$126,0) -> 0 | AF75: =IF(AND(Balance!$U$124='Cálculos y Supuestos Balance'!AF74,Balance!$H$124="Sí"),Balance!$N$126,0) -> 0 | AG75: =IF(AND(Balance!$U$124='Cálculos y Supuestos Balance'!AG74,Balance!$H$124="Sí"),Balance!$N$126,0) -> 0 | ... BM75: =IF(AND(Balance!$U$124='Cálculos y Supuestos Balance'!BM74,Balance!$H$124="Sí"),Balance!$N$126,0) -> 0
B76: Meses de Reserva Acumulación | C76: =(Balance!E12/'Entrevista Balance'!G26)/12 -> 1.6666667 | S76: =S75+1 -> 102 | Y76: Venta Tierra | Z76: =IF(AND(Balance!$AS$124='Cálculos y Supuestos Balance'!Z74,Balance!$AE$124="Sí"),Balance!$AL$126,0) -> 0 | AA76: =IF(AND(Balance!$AS$124='Cálculos y Supuestos Balance'!AA74,Balance!$AE$124="Sí"),Balance!$AL$126,0) -> 0 | AB76: =IF(AND(Balance!$AS$124='Cálculos y Supuestos Balance'!AB74,Balance!$AE$124="Sí"),Balance!$AL$126,0) -> 0 | AC76: =IF(AND(Balance!$AS$124='Cálculos y Supuestos Balance'!AC74,Balance!$AE$124="Sí"),Balance!$AL$126,0) -> 0 | AD76: =IF(AND(Balance!$AS$124='Cálculos y Supuestos Balance'!AD74,Balance!$AE$124="Sí"),Balance!$AL$126,0) -> 0 | AE76: =IF(AND(Balance!$AS$124='Cálculos y Supuestos Balance'!AE74,Balance!$AE$124="Sí"),Balance!$AL$126,0) -> 0 | AF76: =IF(AND(Balance!$AS$124='Cálculos y Supuestos Balance'!AF74,Balance!$AE$124="Sí"),Balance!$AL$126,0) -> 0 | AG76: =IF(AND(Balance!$AS$124='Cálculos y Supuestos Balance'!AG74,Balance!$AE$124="Sí"),Balance!$AL$126,0) -> 0 | ... BM76: =IF(AND(Balance!$AS$124='Cálculos y Supuestos Balance'!BM74,Balance!$AE$124="Sí"),Balance!$AL$126,0) -> 0
B77: ¿Tienes seguro de vida actualmente? | C77: =DependientesEconómicos -> Sí | S77: =S76+1 -> 103 | Y77: Venta Inmuebles en Renta | Z77: =IF(AND(Balance!$BS$124='Cálculos y Supuestos Balance'!Z74,Balance!$BC$124="Sí"),Balance!$BL$126,0) -> 0 | AA77: =IF(AND(Balance!$BS$124='Cálculos y Supuestos Balance'!AA74,Balance!$BC$124="Sí"),Balance!$BL$126,0) -> 0 | AB77: =IF(AND(Balance!$BS$124='Cálculos y Supuestos Balance'!AB74,Balance!$BC$124="Sí"),Balance!$BL$126,0) -> 0 | AC77: =IF(AND(Balance!$BS$124='Cálculos y Supuestos Balance'!AC74,Balance!$BC$124="Sí"),Balance!$BL$126,0) -> 0 | AD77: =IF(AND(Balance!$BS$124='Cálculos y Supuestos Balance'!AD74,Balance!$BC$124="Sí"),Balance!$BL$126,0) -> 0 | AE77: =IF(AND(Balance!$BS$124='Cálculos y Supuestos Balance'!AE74,Balance!$BC$124="Sí"),Balance!$BL$126,0) -> 0 | AF77: =IF(AND(Balance!$BS$124='Cálculos y Supuestos Balance'!AF74,Balance!$BC$124="Sí"),Balance!$BL$126,0) -> 0 | AG77: =IF(AND(Balance!$BS$124='Cálculos y Supuestos Balance'!AG74,Balance!$BC$124="Sí"),Balance!$BL$126,0) -> 0 | ... BM77: =IF(AND(Balance!$BS$124='Cálculos y Supuestos Balance'!BM74,Balance!$BC$124="Sí"),Balance!$BL$126,0) -> 0
B78: Dependientes Economicos | C78: =IF(C77="No",0,1) -> 1 | S78: =S77+1 -> 104 | T78: =64*Montoaproximadodeinversión -> 384000000 | U78: =512*Montoaproximadodeinversión -> 3072000000 | Y78: Venta Negocio | Z78: =IF(AND(Balance!$CO$124='Cálculos y Supuestos Balance'!Z74,Balance!$CC$124="Sí"),Balance!$CH$126,0) -> 0 | AA78: =IF(AND(Balance!$CO$124='Cálculos y Supuestos Balance'!AA74,Balance!$CC$124="Sí"),Balance!$CH$126,0) -> 0 | AB78: =IF(AND(Balance!$CO$124='Cálculos y Supuestos Balance'!AB74,Balance!$CC$124="Sí"),Balance!$CH$126,0) -> 0 | AC78: =IF(AND(Balance!$CO$124='Cálculos y Supuestos Balance'!AC74,Balance!$CC$124="Sí"),Balance!$CH$126,0) -> 0 | AD78: =IF(AND(Balance!$CO$124='Cálculos y Supuestos Balance'!AD74,Balance!$CC$124="Sí"),Balance!$CH$126,0) -> 0 | AE78: =IF(AND(Balance!$CO$124='Cálculos y Supuestos Balance'!AE74,Balance!$CC$124="Sí"),Balance!$CH$126,0) -> 0 | AF78: =IF(AND(Balance!$CO$124='Cálculos y Supuestos Balance'!AF74,Balance!$CC$124="Sí"),Balance!$CH$126,0) -> 0 | AG78: =IF(AND(Balance!$CO$124='Cálculos y Supuestos Balance'!AG74,Balance!$CC$124="Sí"),Balance!$CH$126,0) -> 0 | ... BM78: =IF(AND(Balance!$CO$124='Cálculos y Supuestos Balance'!BM74,Balance!$CC$124="Sí"),Balance!$CH$126,0) -> 0
B79: Nivel Riqueza | C79: =C76 -> 1.6666667 | S79: =S78+1 -> 105 | Y79: Herencia | Z79: =IF(AND($C$62=1,Z74=$C$61),$C$60,0) -> 0 | AA79: =IF(AND($C$62=1,AA74=$C$61),$C$60,0) -> 0 | AB79: =IF(AND($C$62=1,AB74=$C$61),$C$60,0) -> 0 | AC79: =IF(AND($C$62=1,AC74=$C$61),$C$60,0) -> 0 | AD79: =IF(AND($C$62=1,AD74=$C$61),$C$60,0) -> 0 | AE79: =IF(AND($C$62=1,AE74=$C$61),$C$60,0) -> 0 | AF79: =IF(AND($C$62=1,AF74=$C$61),$C$60,0) -> 0 | AG79: =IF(AND($C$62=1,AG74=$C$61),$C$60,0) -> 0 | ... BM79: =IF(AND($C$62=1,BM74=$C$61),$C$60,0) -> 0
B80: Cobertura Sugerida | C80: =MAX(IF(C79<3,3-C79,5-C79)*C78,0) -> 1.3333333 | D80: Gastos | Y80: Pasivo Mensual x año | Z80: =IF(AND(Z74>=$AO$64,Z74<$AP$64),$AQ$64,IF(AND(Z74>=$AO$65,Z74<$AP$65),$AQ$65,IF(AND(Z74>=$AO$66,Z74<$AP$66),$AQ$66,IF(AND(Z74>=$AO$67,Z74<$AP$67),$AQ$67,IF(AND(Z74>=$AO$68,Z74<$AP$68),$AQ$68,IF(AND(Z74>=$AO$69,Z74<$AP$69),$AQ$69,IF(AND(Z74>=$AO$70,Z74<$AP$70),$AQ$70,0))))))) -> 30000 | AA80: =IF(AND(AA74>=$AO$64,AA74<$AP$64),$AQ$64,IF(AND(AA74>=$AO$65,AA74<$AP$65),$AQ$65,IF(AND(AA74>=$AO$66,AA74<$AP$66),$AQ$66,IF(AND(AA74>=$AO$67,AA74<$AP$67),$AQ$67,IF(AND(AA74>=$AO$68,AA74<$AP$68),$AQ$68,IF(AND(AA74>=$AO$69,AA74<$AP$69),$AQ$69,IF(AND(AA74>=$AO$70,AA74<$AP$70),$AQ$70,0))))))) -> 30000 | AB80: =IF(AND(AB74>=$AO$64,AB74<$AP$64),$AQ$64,IF(AND(AB74>=$AO$65,AB74<$AP$65),$AQ$65,IF(AND(AB74>=$AO$66,AB74<$AP$66),$AQ$66,IF(AND(AB74>=$AO$67,AB74<$AP$67),$AQ$67,IF(AND(AB74>=$AO$68,AB74<$AP$68),$AQ$68,IF(AND(AB74>=$AO$69,AB74<$AP$69),$AQ$69,IF(AND(AB74>=$AO$70,AB74<$AP$70),$AQ$70,0))))))) -> 30000 | AC80: =IF(AND(AC74>=$AO$64,AC74<$AP$64),$AQ$64,IF(AND(AC74>=$AO$65,AC74<$AP$65),$AQ$65,IF(AND(AC74>=$AO$66,AC74<$AP$66),$AQ$66,IF(AND(AC74>=$AO$67,AC74<$AP$67),$AQ$67,IF(AND(AC74>=$AO$68,AC74<$AP$68),$AQ$68,IF(AND(AC74>=$AO$69,AC74<$AP$69),$AQ$69,IF(AND(AC74>=$AO$70,AC74<$AP$70),$AQ$70,0))))))) -> 30000 | AD80: =IF(AND(AD74>=$AO$64,AD74<$AP$64),$AQ$64,IF(AND(AD74>=$AO$65,AD74<$AP$65),$AQ$65,IF(AND(AD74>=$AO$66,AD74<$AP$66),$AQ$66,IF(AND(AD74>=$AO$67,AD74<$AP$67),$AQ$67,IF(AND(AD74>=$AO$68,AD74<$AP$68),$AQ$68,IF(AND(AD74>=$AO$69,AD74<$AP$69),$AQ$69,IF(AND(AD74>=$AO$70,AD74<$AP$70),$AQ$70,0))))))) -> 30000 | AE80: =IF(AND(AE74>=$AO$64,AE74<$AP$64),$AQ$64,IF(AND(AE74>=$AO$65,AE74<$AP$65),$AQ$65,IF(AND(AE74>=$AO$66,AE74<$AP$66),$AQ$66,IF(AND(AE74>=$AO$67,AE74<$AP$67),$AQ$67,IF(AND(AE74>=$AO$68,AE74<$AP$68),$AQ$68,IF(AND(AE74>=$AO$69,AE74<$AP$69),$AQ$69,IF(AND(AE74>=$AO$70,AE74<$AP$70),$AQ$70,0))))))) -> 30000 | AF80: =IF(AND(AF74>=$AO$64,AF74<$AP$64),$AQ$64,IF(AND(AF74>=$AO$65,AF74<$AP$65),$AQ$65,IF(AND(AF74>=$AO$66,AF74<$AP$66),$AQ$66,IF(AND(AF74>=$AO$67,AF74<$AP$67),$AQ$67,IF(AND(AF74>=$AO$68,AF74<$AP$68),$AQ$68,IF(AND(AF74>=$AO$69,AF74<$AP$69),$AQ$69,IF(AND(AF74>=$AO$70,AF74<$AP$70),$AQ$70,0))))))) -> 30000 | AG80: =IF(AND(AG74>=$AO$64,AG74<$AP$64),$AQ$64,IF(AND(AG74>=$AO$65,AG74<$AP$65),$AQ$65,IF(AND(AG74>=$AO$66,AG74<$AP$66),$AQ$66,IF(AND(AG74>=$AO$67,AG74<$AP$67),$AQ$67,IF(AND(AG74>=$AO$68,AG74<$AP$68),$AQ$68,IF(AND(AG74>=$AO$69,AG74<$AP$69),$AQ$69,IF(AND(AG74>=$AO$70,AG74<$AP$70),$AQ$70,0))))))) -> 30000 | ... BM80: =IF(AND(BM74>=$AO$64,BM74<$AP$64),$AQ$64,IF(AND(BM74>=$AO$65,BM74<$AP$65),$AQ$65,IF(AND(BM74>=$AO$66,BM74<$AP$66),$AQ$66,IF(AND(BM74>=$AO$67,BM74<$AP$67),$AQ$67,IF(AND(BM74>=$AO$68,BM74<$AP$68),$AQ$68,IF(AND(BM74>=$AO$69,BM74<$AP$69),$AQ$69,IF(AND(BM74>=$AO$70,BM74<$AP$70),$AQ$70,0))))))) -> 0
B81: Monto de Cobertura Sugerido | C81: =C80*'Entrevista Balance'!G26*12 -> 4800000 | Y81: Saldo Inicial | Z81: =Balance!CA133+Z75+Z76+Z77+Z78+Z79 -> 9327193 | AA81: =Z82+AA75+AA76+AA77+AA78+AA79 -> 9058937.7 | AB81: =AA82+AB75+AB76+AB77+AB78+AB79 -> 8787987.4 | AC81: =AB82+AC75+AC76+AC77+AC78+AC79 -> 8514315.2 | AD81: =AC82+AD75+AD76+AD77+AD78+AD79 -> 8237893.7 | AE81: =AD82+AE75+AE76+AE77+AE78+AE79 -> 7958695.3 | AF81: =AE82+AF75+AF76+AF77+AF78+AF79 -> 7676692.1 | AG81: =AF82+AG75+AG76+AG77+AG78+AG79 -> 7391855.9 | AH81: =AG82+AH75+AH76+AH77+AH78+AH79 -> 7104158.2 | ... BM81: =BL82+BM75+BM76+BM77+BM78+BM79 -> -11506.295
B82: Seguro de Vida Costo Anual | C82: =IF(C80=0,0,INDEX($BS$94:$CB$102,MATCH(1,$BP$94:$BP$102,0),MATCH(1,$BS$91:$CB$91,0))) -> 75265 | Y82: Saldo Final | Z82: =(Z81 * (1 + (TasaReal/12))^12) - ( ( Z80 ) * ( (1 + (TasaReal/12))^12 - 1) / (TasaReal/12) * (1 + (TasaReal/12))) -> 9058937.7 | AA82: =(AA81 * (1 + (TasaReal/12))^12) - ( ( AA80 ) * ( (1 + (TasaReal/12))^12 - 1) / (TasaReal/12) * (1 + (TasaReal/12))) -> 8787987.4 | AB82: =(AB81 * (1 + (TasaReal/12))^12) - ( ( AB80 ) * ( (1 + (TasaReal/12))^12 - 1) / (TasaReal/12) * (1 + (TasaReal/12))) -> 8514315.2 | AC82: =(AC81 * (1 + (TasaReal/12))^12) - ( ( AC80 ) * ( (1 + (TasaReal/12))^12 - 1) / (TasaReal/12) * (1 + (TasaReal/12))) -> 8237893.7 | AD82: =(AD81 * (1 + (TasaReal/12))^12) - ( ( AD80 ) * ( (1 + (TasaReal/12))^12 - 1) / (TasaReal/12) * (1 + (TasaReal/12))) -> 7958695.3 | AE82: =(AE81 * (1 + (TasaReal/12))^12) - ( ( AE80 ) * ( (1 + (TasaReal/12))^12 - 1) / (TasaReal/12) * (1 + (TasaReal/12))) -> 7676692.1 | AF82: =(AF81 * (1 + (TasaReal/12))^12) - ( ( AF80 ) * ( (1 + (TasaReal/12))^12 - 1) / (TasaReal/12) * (1 + (TasaReal/12))) -> 7391855.9 | AG82: =(AG81 * (1 + (TasaReal/12))^12) - ( ( AG80 ) * ( (1 + (TasaReal/12))^12 - 1) / (TasaReal/12) * (1 + (TasaReal/12))) -> 7104158.2 | ... BM82: =(BM81 * (1 + (TasaReal/12))^12) - ( ( BM80 ) * ( (1 + (TasaReal/12))^12 - 1) / (TasaReal/12) * (1 + (TasaReal/12))) -> -11621.887
B83: Seguro de Propietario
B84: Monto de Cobertura Sugerido | C84: =IFERROR(VLOOKUP(1,$R$111:$S$128,2,0),0) -> 0
B85: Seguro de Vida Costo Anual | C85: =IFERROR(VLOOKUP(1,$R$111:$T$128,3,0),0) -> 0 | Y85: Indicador Nuevo Pasivo por Casa Propia | Z85: =IF(SUM($Z75:Z$75)>0,1,0) -> 0 | AA85: =IF(SUM($Z75:AA$75)>0,1,0) -> 0 | AB85: =IF(SUM($Z75:AB$75)>0,1,0) -> 0 | AC85: =IF(SUM($Z75:AC$75)>0,1,0) -> 0 | AD85: =IF(SUM($Z75:AD$75)>0,1,0) -> 0 | AE85: =IF(SUM($Z75:AE$75)>0,1,0) -> 0 | AF85: =IF(SUM($Z75:AF$75)>0,1,0) -> 0 | AG85: =IF(SUM($Z75:AG$75)>0,1,0) -> 0 | ... BM85: =IF(SUM($Z75:BM$75)>0,1,0) -> 0
B86: Seguro de Arrendatario | Y86: Indicador Nuevo Pasivo por Inmuebles en Renta | Z86: =IF(SUM($Z77:Z$77)>0,1,0) -> 0 | AA86: =IF(SUM($Z77:AA$77)>0,1,0) -> 0 | AB86: =IF(SUM($Z77:AB$77)>0,1,0) -> 0 | AC86: =IF(SUM($Z77:AC$77)>0,1,0) -> 0 | AD86: =IF(SUM($Z77:AD$77)>0,1,0) -> 0 | AE86: =IF(SUM($Z77:AE$77)>0,1,0) -> 0 | AF86: =IF(SUM($Z77:AF$77)>0,1,0) -> 0 | AG86: =IF(SUM($Z77:AG$77)>0,1,0) -> 0 | ... BM86: =IF(SUM($Z77:BM$77)>0,1,0) -> 0
B87: Monto de Cobertura Sugerido | C87: =IFERROR(VLOOKUP(1,$R$133:$S$150,2,0),0) -> 1500000 | Y87: Indicador Nuevo Pasivo por Negocio | Z87: =IF(SUM($Z$78:Z78)>0,1,0) -> 0 | AA87: =IF(SUM($Z$78:AA78)>0,1,0) -> 0 | AB87: =IF(SUM($Z$78:AB78)>0,1,0) -> 0 | AC87: =IF(SUM($Z$78:AC78)>0,1,0) -> 0 | AD87: =IF(SUM($Z$78:AD78)>0,1,0) -> 0 | AE87: =IF(SUM($Z$78:AE78)>0,1,0) -> 0 | AF87: =IF(SUM($Z$78:AF78)>0,1,0) -> 0 | AG87: =IF(SUM($Z$78:AG78)>0,1,0) -> 0 | ... BM87: =IF(SUM($Z$78:BM78)>0,1,0) -> 0
B88: Seguro de Vida Costo Anual | C88: =IFERROR(VLOOKUP(1,$R$133:$T$150,3,0),0) -> 2221.35
Y90: Comportamiento de Flujos
Z91: =Z74 -> 60 | AA91: =AA74 -> 61 | AB91: =AB74 -> 62 | AC91: =AC74 -> 63 | AD91: =AD74 -> 64 | AE91: =AE74 -> 65 | AF91: =AF74 -> 66 | AG91: =AG74 -> 67 | ... BM91: =BM74 -> 99 | BP91: Indicador | BS91: =IF(AND(SumaAseguradadeSegurodeVida<=BS92),1,0) -> 0 | BT91: =IF(AND(SumaAseguradadeSegurodeVida<=BT92,SumaAseguradadeSegurodeVida>=BS92),1,0) -> 0 | BU91: =IF(AND(SumaAseguradadeSegurodeVida<=BU92,SumaAseguradadeSegurodeVida>=BT92),1,0) -> 0 | BV91: =IF(AND(SumaAseguradadeSegurodeVida<=BV92,SumaAseguradadeSegurodeVida>=BU92),1,0) -> 0 | BW91: =IF(AND(SumaAseguradadeSegurodeVida<=BW92,SumaAseguradadeSegurodeVida>=BV92),1,0) -> 0 | BX91: =IF(AND(SumaAseguradadeSegurodeVida<=BX92,SumaAseguradadeSegurodeVida>=BW92),1,0) -> 0 | BY91: =IF(AND(SumaAseguradadeSegurodeVida<=BY92,SumaAseguradadeSegurodeVida>=BX92),1,0) -> 0 | BZ91: =IF(AND(SumaAseguradadeSegurodeVida<=BZ92,SumaAseguradadeSegurodeVida>=BY92),1,0) -> 0 | CA91: =IF(AND(SumaAseguradadeSegurodeVida<=CA92,SumaAseguradadeSegurodeVida>=BZ92),1,0) -> 0 | CB91: =IF(AND(SumaAseguradadeSegurodeVida>=CA92),1,0) -> 1
Y92: Esquemas de Pensión | Z92: =IF(Z91<90,IF(Z91<60,0,$C$11+$C$13),0) -> 0 | AA92: =IF(AA91<90,IF(AA91<60,0,$C$11+$C$13),0) -> 0 | AB92: =IF(AB91<90,IF(AB91<60,0,$C$11+$C$13),0) -> 0 | AC92: =IF(AC91<90,IF(AC91<60,0,$C$11+$C$13),0) -> 0 | AD92: =IF(AD91<90,IF(AD91<60,0,$C$11+$C$13),0) -> 0 | AE92: =IF(AE91<90,IF(AE91<60,0,$C$11+$C$13),0) -> 0 | AF92: =IF(AF91<90,IF(AF91<60,0,$C$11+$C$13),0) -> 0 | AG92: =IF(AG91<90,IF(AG91<60,0,$C$11+$C$13),0) -> 0 | ... BM92: =IF(BM91<90,IF(BM91<60,0,$C$11+$C$13),0) -> 0 | BQ92: Suma Asegurada | BS92: 500000 | BT92: 1000000 | BU92: 1500000 | BV92: 2000000 | BW92: 2500000 | BX92: 3000000 | BY92: 3500000 | BZ92: 4000000 | CA92: 4500000 | CB92: 5000000
Y93: Esquemas de Pensión Voluntarios | Z93: =IF(Z91<90,IF(Z91<60,0,$C$12),0) -> 0 | AA93: =IF(AA91<90,IF(AA91<60,0,$C$12),0) -> 0 | AB93: =IF(AB91<90,IF(AB91<60,0,$C$12),0) -> 0 | AC93: =IF(AC91<90,IF(AC91<60,0,$C$12),0) -> 0 | AD93: =IF(AD91<90,IF(AD91<60,0,$C$12),0) -> 0 | AE93: =IF(AE91<90,IF(AE91<60,0,$C$12),0) -> 0 | AF93: =IF(AF91<90,IF(AF91<60,0,$C$12),0) -> 0 | AG93: =IF(AG91<90,IF(AG91<60,0,$C$12),0) -> 0 | ... BM93: =IF(BM91<90,IF(BM91<60,0,$C$12),0) -> 0 | BQ93: Edad Inicio | BR93: Edad Fin | BS93: Costo Prima Anual
Y94: Patrimonio Financiero | Z94: =IF(Z91<90,MIN(MAX(MIN(Z80,(PMT(TasaReal/12,(1)*12,((Z98*(1+TasaReal/12)^((1)*12))),0,1)*-1)),0),MensualidaddeseadaenelRetiro-(Z92+Z93+Z95+Z96)),0) -> 30000 | AA94: =IF(AA91<90,MIN(MAX(MIN(AA80,(PMT(TasaReal/12,(1)*12,((AA98*(1+TasaReal/12)^((1)*12))),0,1)*-1)),0),MensualidaddeseadaenelRetiro-(AA92+AA93+AA95+AA96)),0) -> 30000 | AB94: =IF(AB91<90,MIN(MAX(MIN(AB80,(PMT(TasaReal/12,(1)*12,((AB98*(1+TasaReal/12)^((1)*12))),0,1)*-1)),0),MensualidaddeseadaenelRetiro-(AB92+AB93+AB95+AB96)),0) -> 30000 | AC94: =IF(AC91<90,MIN(MAX(MIN(AC80,(PMT(TasaReal/12,(1)*12,((AC98*(1+TasaReal/12)^((1)*12))),0,1)*-1)),0),MensualidaddeseadaenelRetiro-(AC92+AC93+AC95+AC96)),0) -> 30000 | AD94: =IF(AD91<90,MIN(MAX(MIN(AD80,(PMT(TasaReal/12,(1)*12,((AD98*(1+TasaReal/12)^((1)*12))),0,1)*-1)),0),MensualidaddeseadaenelRetiro-(AD92+AD93+AD95+AD96)),0) -> 30000 | AE94: =IF(AE91<90,MIN(MAX(MIN(AE80,(PMT(TasaReal/12,(1)*12,((AE98*(1+TasaReal/12)^((1)*12))),0,1)*-1)),0),MensualidaddeseadaenelRetiro-(AE92+AE93+AE95+AE96)),0) -> 30000 | AF94: =IF(AF91<90,MIN(MAX(MIN(AF80,(PMT(TasaReal/12,(1)*12,((AF98*(1+TasaReal/12)^((1)*12))),0,1)*-1)),0),MensualidaddeseadaenelRetiro-(AF92+AF93+AF95+AF96)),0) -> 30000 | AG94: =IF(AG91<90,MIN(MAX(MIN(AG80,(PMT(TasaReal/12,(1)*12,((AG98*(1+TasaReal/12)^((1)*12))),0,1)*-1)),0),MensualidaddeseadaenelRetiro-(AG92+AG93+AG95+AG96)),0) -> 30000 | ... BM94: =IF(BM91<90,MIN(MAX(MIN(BM80,(PMT(TasaReal/12,(1)*12,((BM98*(1+TasaReal/12)^((1)*12))),0,1)*-1)),0),MensualidaddeseadaenelRetiro-(BM92+BM93+BM95+BM96)),0) -> 0 | BP94: =IF(AND(EdadActual>=BQ94,EdadActual<=BR94),1,0) -> 0 | BQ94: 18 | BR94: 29 | BS94: 2352 | BT94: 4293 | BU94: 5898 | BV94: 7502 | BW94: 9107 | BX94: 10712 | BY94: 12316 | BZ94: 13921 | CA94: 15526 | CB94: 17131
Y95: Rentas | Z95: =IF(Z91<90,Rentas-IF(SUM($Z$77:Z77)>0,Balance!$BL$128,0),0) -> 20000 | AA95: =IF(AA91<90,Rentas-IF(SUM($Z$77:AA77)>0,Balance!$BL$128,0),0) -> 20000 | AB95: =IF(AB91<90,Rentas-IF(SUM($Z$77:AB77)>0,Balance!$BL$128,0),0) -> 20000 | AC95: =IF(AC91<90,Rentas-IF(SUM($Z$77:AC77)>0,Balance!$BL$128,0),0) -> 20000 | AD95: =IF(AD91<90,Rentas-IF(SUM($Z$77:AD77)>0,Balance!$BL$128,0),0) -> 20000 | AE95: =IF(AE91<90,Rentas-IF(SUM($Z$77:AE77)>0,Balance!$BL$128,0),0) -> 20000 | AF95: =IF(AF91<90,Rentas-IF(SUM($Z$77:AF77)>0,Balance!$BL$128,0),0) -> 20000 | AG95: =IF(AG91<90,Rentas-IF(SUM($Z$77:AG77)>0,Balance!$BL$128,0),0) -> 20000 | ... BM95: =IF(BM91<90,Rentas-IF(SUM($Z$77:BM77)>0,Balance!$BL$128,0),0) -> 0 | BP95: =IF(AND(EdadActual>=BQ95,EdadActual<=BR95),1,0) -> 0 | BQ95: 30 | BR95: 34 | BS95: 2825 | BT95: 5239 | BU95: 7222 | BV95: 9204 | BW95: 11187 | BX95: 13170 | BY95: 15152 | BZ95: 17135 | CA95: 19117 | CB95: 21100
Y96: Negocio | Z96: =IF(Z91<90,OtrosIngresos-IF(SUM($Z$78:Z78)>0,Balance!$CH$128,0),0) -> 0 | AA96: =IF(AA91<90,OtrosIngresos-IF(SUM($Z$78:AA78)>0,Balance!$CH$128,0),0) -> 0 | AB96: =IF(AB91<90,OtrosIngresos-IF(SUM($Z$78:AB78)>0,Balance!$CH$128,0),0) -> 0 | AC96: =IF(AC91<90,OtrosIngresos-IF(SUM($Z$78:AC78)>0,Balance!$CH$128,0),0) -> 0 | AD96: =IF(AD91<90,OtrosIngresos-IF(SUM($Z$78:AD78)>0,Balance!$CH$128,0),0) -> 0 | AE96: =IF(AE91<90,OtrosIngresos-IF(SUM($Z$78:AE78)>0,Balance!$CH$128,0),0) -> 0 | AF96: =IF(AF91<90,OtrosIngresos-IF(SUM($Z$78:AF78)>0,Balance!$CH$128,0),0) -> 0 | AG96: =IF(AG91<90,OtrosIngresos-IF(SUM($Z$78:AG78)>0,Balance!$CH$128,0),0) -> 0 | ... BM96: =IF(BM91<90,OtrosIngresos-IF(SUM($Z$78:BM78)>0,Balance!$CH$128,0),0) -> 0 | BP96: =IF(AND(EdadActual>=BQ96,EdadActual<=BR96),1,0) -> 0 | BQ96: 35 | BR96: 39 | BS96: 3542 | BT96: 6674 | BU96: 9229 | BV96: 11784 | BW96: 14339 | BX96: 16894 | BY96: 19449 | BZ96: 22004 | CA96: 24559 | CB96: 27115
Y97: Total | Z97: =SUM(Z92:Z96) -> 50000 | AA97: =SUM(AA92:AA96) -> 50000 | AB97: =SUM(AB92:AB96) -> 50000 | AC97: =SUM(AC92:AC96) -> 50000 | AD97: =SUM(AD92:AD96) -> 50000 | AE97: =SUM(AE92:AE96) -> 50000 | AF97: =SUM(AF92:AF96) -> 50000 | AG97: =SUM(AG92:AG96) -> 50000 | ... BM97: =SUM(BM92:BM96) -> 0 | BP97: =IF(AND(EdadActual>=BQ97,EdadActual<=BR97),1,0) -> 0 | BQ97: 40 | BR97: 44 | BS97: 4652 | BT97: 8894 | BU97: 12335 | BV97: 15776 | BW97: 19217 | BX97: 22658 | BY97: 26100 | BZ97: 29541 | CA97: 32982 | CB97: 36423
Y98: Saldo Inicial | Z98: =Balance!CA133+Z75+Z76+Z77+Z78+Z79 -> 9327193 | AA98: =MAX(Z99+AA75+AA76+AA77+AA78+AA79,0) -> 9058937.7 | AB98: =MAX(AA99+AB75+AB76+AB77+AB78+AB79,0) -> 8787987.4 | AC98: =MAX(AB99+AC75+AC76+AC77+AC78+AC79,0) -> 8514315.2 | AD98: =MAX(AC99+AD75+AD76+AD77+AD78+AD79,0) -> 8237893.7 | AE98: =MAX(AD99+AE75+AE76+AE77+AE78+AE79,0) -> 7958695.3 | AF98: =MAX(AE99+AF75+AF76+AF77+AF78+AF79,0) -> 7676692.1 | AG98: =MAX(AF99+AG75+AG76+AG77+AG78+AG79,0) -> 7391855.9 | AH98: =MAX(AG99+AH75+AH76+AH77+AH78+AH79,0) -> 7104158.2 | ... BM98: =MAX(BL99+BM75+BM76+BM77+BM78+BM79,0) -> 0 | BP98: =IF(AND(EdadActual>=BQ98,EdadActual<=BR98),1,0) -> 0 | BQ98: 45 | BR98: 49 | BS98: 6413 | BT98: 12416 | BU98: 17263 | BV98: 22111 | BW98: 26958 | BX98: 31805 | BY98: 36653 | BZ98: 41500 | CA98: 46347 | CB98: 51195
Y99: Saldo Final | Z99: =MAX((Z98 * (1 + (TasaReal/12))^12) - ( ( Z94 ) * ( (1 + (TasaReal/12))^12 - 1) / (TasaReal/12) * (1 + (TasaReal/12))),0) -> 9058937.7 | AA99: =MAX((AA98 * (1 + (TasaReal/12))^12) - ( ( AA94 ) * ( (1 + (TasaReal/12))^12 - 1) / (TasaReal/12) * (1 + (TasaReal/12))),0) -> 8787987.4 | AB99: =MAX((AB98 * (1 + (TasaReal/12))^12) - ( ( AB94 ) * ( (1 + (TasaReal/12))^12 - 1) / (TasaReal/12) * (1 + (TasaReal/12))),0) -> 8514315.2 | AC99: =MAX((AC98 * (1 + (TasaReal/12))^12) - ( ( AC94 ) * ( (1 + (TasaReal/12))^12 - 1) / (TasaReal/12) * (1 + (TasaReal/12))),0) -> 8237893.7 | AD99: =MAX((AD98 * (1 + (TasaReal/12))^12) - ( ( AD94 ) * ( (1 + (TasaReal/12))^12 - 1) / (TasaReal/12) * (1 + (TasaReal/12))),0) -> 7958695.3 | AE99: =MAX((AE98 * (1 + (TasaReal/12))^12) - ( ( AE94 ) * ( (1 + (TasaReal/12))^12 - 1) / (TasaReal/12) * (1 + (TasaReal/12))),0) -> 7676692.1 | AF99: =MAX((AF98 * (1 + (TasaReal/12))^12) - ( ( AF94 ) * ( (1 + (TasaReal/12))^12 - 1) / (TasaReal/12) * (1 + (TasaReal/12))),0) -> 7391855.9 | AG99: =MAX((AG98 * (1 + (TasaReal/12))^12) - ( ( AG94 ) * ( (1 + (TasaReal/12))^12 - 1) / (TasaReal/12) * (1 + (TasaReal/12))),0) -> 7104158.2 | ... BM99: =MAX((BM98 * (1 + (TasaReal/12))^12) - ( ( BM94 ) * ( (1 + (TasaReal/12))^12 - 1) / (TasaReal/12) * (1 + (TasaReal/12))),0) -> 0 | BP99: =IF(AND(EdadActual>=BQ99,EdadActual<=BR99),1,0) -> 1 | BQ99: 50 | BR99: 54 | BS99: 9283 | BT99: 18156 | BU99: 25294 | BV99: 32433 | BW99: 39572 | BX99: 46710 | BY99: 53849 | BZ99: 60988 | CA99: 68126 | CB99: 75265
BP100: =IF(AND(EdadActual>=BQ100,EdadActual<=BR100),1,0) -> 0 | BQ100: 55 | BR100: 59 | BS100: 14090 | BT100: 27769 | BU100: 38745 | BV100: 49722 | BW100: 60698 | BX100: 71674 | BY100: 82651 | BZ100: 93627 | CA100: 104603 | CB100: 115579
BP101: =IF(AND(EdadActual>=BQ101,EdadActual<=BR101),1,0) -> 0 | BQ101: 60 | BR101: 64 | BS101: 22367 | BT101: 44323 | BU101: 61907 | BV101: 79491 | BW101: 97075 | BX101: 114660 | BY101: 132244 | BZ101: 149828 | CA101: 167413 | CB101: 184997
BP102: =IF(AND(EdadActual>=BQ102,EdadActual<=BR102),1,0) -> 0 | BQ102: 65 | BR102: 69 | BS102: 29661 | BT102: 58911 | BU102: 88161 | BV102: 117411 | BW102: 146661 | BX102: 175911 | BY102: 205161 | BZ102: 234411 | CA102: 263661 | CB102: 292911
...

Sheet Balance
D6: I. PATRIMONIO NETO
E8: Ahorro | V8: Casa Propia | AM8: Hipoteca | BD8: Patrimonio Neto
E9: =ReservaCortoPlazo -> 0 | V9: ='Entrevista Balance'!G4 -> 0 | AM9: ='Entrevista Balance'!G10 -> 0 | BD9: =E25+V25-AM25 -> 6000000
E11: Inversiones | V11: Inmuebles en Renta | AM11: Planes de Seguro
E12: =Acumulación -> 6000000 | V12: ='Entrevista Balance'!G6 -> 1000000 | AM12: ='Entrevista Balance'!G19 -> 0
E14: Dotales | V14: Tierra | AM14: Otros compromisos
E15: =PlanesdeSeguroAcumulación1 -> 0 | V15: ='Entrevista Balance'!G8 -> 0 | AM15: ='Entrevista Balance'!G21 -> 1000000
E17: Retiro | V17: Negocio
E18: =OtrosPlanesdeSegurosparaRetiro+Afore+PPR+PlanPrivadodePensión -> 0 | V18: ='Entrevista Balance'!G12 -> 0
V20: Herencia
V21: ='Entrevista Balance'!G14 -> 0 | BW21: Total Activos | CN21: Total Pasivos
BW22: =E25+V25 -> 7000000 | CN22: =AM25 -> 1000000
E24: Patrimonio Financiero | V24: Activos No Financieros | AM24: Obligaciones | BD24: Patrimonio Neto | BW24: Patrimonio Fin. Neto | CN24: Patrimonio Neto
E25: =E9+E12+E15+E18 -> 6000000 | N25: =E25/$BW$22 -> 0.85714286 | V25: =V9+V12+V15+V18+V21 -> 1000000 | AE25: =V25/$BW$22 -> 0.14285714 | AM25: =AM9+AM12+AM15 -> 1000000 | BD25: =BD9 -> 6000000 | BW25: =E25-AM25 -> 5000000 | CN25: =BD25 -> 6000000
D27: Nivel Patrimonio Neto de acuerdo a etapa de vida en función de gastos anuales: | BB27: ='Entrevista Balance'!G26*12 -> 3600000
H28: Insuficiente | X28: Suficiente | AN28: Mejor | BD28: Bien | BT28: Genial | CJ28: Excelente
D30: Índice de Liquidez: | P30: =IF('Patrimonio Neto'!K18=0,"",'Patrimonio Neto'!K18) -> 6
D31: =IF('Patrimonio Neto'!K18>=1,"Suficiente para hacer frente a tus obligaciones.",IF('Patrimonio Neto'!K18=0,"Tu liquidez esta en función de tu calidad de vida deseada y no por tus obligaciones.","Deseable incrementar tu liquidez para cubrir compromisos futuros.")) -> Suficiente para hacer frente a tus obligaciones.
D34: II. FUENTES DE FLUJO DISPONIBLE | BV34: FUENTES DE FLUJO DISPONIBLE
F36: Ingresos Totales | BV36: Ingresos por Rentas | CK36: ='Cálculos y Supuestos Balance'!Z7 -> 20000 | CU36: ='Cálculos y Supuestos Balance'!AA7 -> 0.24
BW37: Rentabilidad anual correspondiente a tus activos excepto negocio
F38: Gastos Totales | AD38: ='Cálculos y Supuestos Balance'!AA12 -> 0.85714286 | BV38: Ingresos por Negocios | CK38: ='Cálculos y Supuestos Balance'!Z8 -> 0 | CU38: ='Cálculos y Supuestos Balance'!AA8 -> 0
BW39: Rentabilidad anual del negocio
F40: Disponible Ingreso Activo | AD40: ='Cálculos y Supuestos Balance'!AA13 -> 0.085714286 | BW40: =IF('Cálculos y Supuestos Balance'!Z6>0,"Los ingresos pasivos son una buena fuente para seguir creciendo tu patrimonio y hacer frente a obligaciones.","Es importante diversificar la fuentes de ingresos para que no solo dependan de una sola actividad.") -> Los ingresos pasivos son una buena fuente para seguir creciendo tu patrimonio y hacer frente a obligaciones.
F42: Disponible Ingreso Pasivo | AD42: ='Cálculos y Supuestos Balance'!AA14 -> 0.057142857
D46: III. PATRIMONIO TOTAL EN FUNCIÓN DE DISPONIBILIDAD
BW47: ="Considerando tu patrimonio financiero actual, puedes cubrir tus gastos totales anuales por " &TRUNC((E25/'Patrimonio Neto'!N1),2)&" años con lo cual, tienes tus gastos cubiertos hasta los " &ROUND('Entrevista Balance'!D6+(E25/'Patrimonio Neto'!N1),0)&" años de edad." -> Considerando tu patrimonio financiero actual, puedes cubrir tus gastos totales anuales por 1.66 años con lo cual, tienes tus gastos cubiertos hasta los 52 años de edad.
F48: Retiro | AD48: ='Cálculos y Supuestos Balance'!AA29 -> 0
F50: Activos No Financieros Productivos | AD50: ='Cálculos y Supuestos Balance'!AA30 -> 0.14285714
F52: Activos No Financieros No Productivos | AD52: ='Cálculos y Supuestos Balance'!AA31 -> 0 | BW52: =IF('Patrimonio Neto'!K18>=1,"","Te recordamos que los activos de retiro no pueden ser utilizados para hacer frente a otras obligaciones. Es recomendable hacer liquidez sobre los activos no productivos para no afectar tu flujo.")
F54: Acumulación | AD54: ='Cálculos y Supuestos Balance'!AA32 -> 0.85714286
F56: Líquidez | AD56: ='Cálculos y Supuestos Balance'!AA33 -> 0
D60: IV. POTENCIAL DEL BALANCE
D61: Solvencia (excluyendo activos de retiro)
BO62: ='Cálculos y Supuestos Balance'!AB39 -> Tienes un nivel de solvencia excelente que te permite apalancarte en tus activos para seguir creciendo tu patrimonio.
D67: Índice de solvencia | P67: ='Cálculos y Supuestos Balance'!Z39 -> 0.85714286
D70: Capacidad de Apalancamiento del Balance | CI70: Préstamo | CP70: 2000000
F72: Apalancamiento Actual | Y72: =AM25 -> 1000000 | BV72: Índice Deuda/Activos
BV73: Índice Actual | CN73: Índice Con Préstamo
F74: Potencial de Apalancamiento: | Y74: =((BW22-E18-V21)*0.5)-AM25 -> 2500000 | BV74: ='Potencial del balance'!D24 -> 0.14285714 | CN74: ='Potencial del balance'!D31 -> 0.33333333
F76: Excedente | Y76: =MAX(Y74-Y72,0) -> 1500000 | BV76: ='Potencial del balance'!I20 -> Elevado | CN76: ='Potencial del balance'!I20 -> Elevado
BV78: ='Potencial del balance'!I21 -> Aceptable | CN78: ='Potencial del balance'!I21 -> Aceptable
D79: =IF('Potencial del balance'!J2="Si","De acuerdo a tu nivel de apalancamiento actual, puedes recurrir a un crédito por "&TEXT('Potencial del balance'!F11,"#,0")&" sobre tus activos financieros.","No cuentas con capacidad de apalancamiento") -> De acuerdo a tu nivel de apalancamiento actual, puedes recurrir a un crédito por 2,142,857 sobre tus activos financieros.
BV80: ='Potencial del balance'!I22 -> Recomendable | CN80: ='Potencial del balance'!I22 -> Recomendable
D82: =IF('Potencial del balance'!J2="Si","De acuerdo a tu nivel de apalancamiento actual, puedes recurrir a un crédito por "&TEXT('Potencial del balance'!F12,"#,0")&" sobre tus activos inmobiliarios.","No cuentas con capacidad de apalancamiento") -> De acuerdo a tu nivel de apalancamiento actual, puedes recurrir a un crédito por 357,143 sobre tus activos inmobiliarios. | BV82: ='Potencial del balance'!I23 -> Muy saludable | CN82: ='Potencial del balance'!I23 -> Muy saludable
D86: V. VALOR EN RIESGO
D88: Impacto en tu Balance | BD88: Impacto en tu Flujo de Efectivo
CR89: Impacto en Ingresos Pasivos
D90: Patrimonio Neto Actual: | T90: =CN25 -> 6000000 | AF90: Solvencia actual: | AO90: =P67 -> 0.85714286 | BT90: Actual | CF90: Resultante
D92: Afectación al Patrimonio: | T92: =V9+V12 -> 1000000 | BD92: Ingresos Disponibles: | BT92: =Rentas + OtrosIngresos -> 20000 | CF92: =BT92-Rentas -> 0 | CR92: =IFERROR((CF92/BT92)-1,0) -> -1
BD93: *Sobre los ingresos pasivos
D94: Patrimonio Neto Resultante: | T94: =T90-T92 -> 5000000 | AF94: Solvencia resultante: | AQ94: =((V25-T92+E25-E18-V21)-(AM9+AM12+AM15))/(V25-T92+E25-E18-V21) -> 0.83333333
D97: VI. PROTECCIÓN PATRIMONIAL
I99: SEGURO DE VIDA + EXCESO | BJ99: PROTEGE TU PROPIEDAD
I101: Protege a tus dependientes por una suma que cubra una protección de 3 años de tus gastos básicos. | BJ101: =IF(COUNTIF('Entrevista Balance'!G4:G8,">0")=1,"Contrata un seguro de hogar por:",IF(COUNTIF('Entrevista Balance'!G4:G8,">0")>1,"Contrata Multi-Seguro de Hogar",IF(COUNTIF('Entrevista Balance'!G4:G8,">0")=0,"No es imperante la contratación de un seguro de hogar",0))) -> Contrata un seguro de hogar por:
BY104: Suma Asegurada | CO104: Costo Prima Anual
M106: Suma Asegurada | AB106: Costo Prima Anual | BJ106: Seguro Propietario
BJ110: Seguro Arrendador
L114: *Si ya cuentas con un seguro de vida considera una extensión | BM114: *Valor estimado de la propiedad en función de la renta
D118: VII. CONSOLIDACIÓN DE FLUJO EN EL RETIRO
D120: Aportación mensual necesaria para alcanzar tu calidad de vida en edad de retiro: | AX120: ='Cálculos y Supuestos Balance'!C71 -> 29302.151 | BO120: Aportación: | BQ120: 29302 | BZ120: *Capacidad de Ahorro: | CL120: ='Entrevista Balance'!G28 -> 50000
D122: Casa Propia | N122: =V9 -> 0 | AA122: Tierra | AL122: =V15 -> 0 | AY122: Inmuebles en Renta | BL122: =V12 -> 1000000 | BY122: Negocio | CH122: =V18 -> 0 | CU122: Herencia
D124: Venta | H124: No | P124: Edad | U124: 77 | AA124: Venta | AE124: Sí | AN124: Edad | AS124: 65 | AY124: Venta | BC124: No | BN124: Edad | BS124: 66 | BY124: Venta | CC124: No | CJ124: Edad | CO124: 60 | CT124: =V21 -> 0
D126: Valor Vendido | N126: 2000000 | AA126: Valor Vendido | AL126: 0 | AY126: Valor Vendido | BL126: 1000000 | BY126: Valor Vendido | CH126: 0 | CU126: Edad | CZ126: =IF(CT124=0,"N/A",'Cálculos y Supuestos Balance'!C61) -> N/A
DB127: =IF(CT124>0,"*Supuesto","")
D128: Nuevo Pasivo | O128: 0 | AY128: Flujo perdido | BL128: =BP129 -> 20000 | BY128: Flujo perdido | CH128: =CL129 -> 0
D129: *Renta | AY129: *Ingresos por Rentas | BP129: ='Entrevista Balance'!G30 -> 20000 | BY129: *Ingresos por Negocios | CL129: ='Entrevista Balance'!G32 -> 0
D133: Patrimonio Financiero: | R133: ='Cálculos y Supuestos Balance'!C35 -> 6630749.4 | AD133: Obligaciones: | AM133: ='Cálculos y Supuestos Balance'!C38 -> 1000000 | AZ133: Capital Humano: | BJ133: =BQ120 * (((1 + (TasaReal/12))^((EdaddeRetiro - EdadActual)*12) - 1) / (TasaReal/12)) -> 3696443.6 | BW133: Total: | CA133: =R133-AM133+BJ133 -> 9327193 | CN133: LEGADO | CT133: ='Cálculos y Supuestos Balance'!BC99+IF(H124="No",N122,N122-N126)+IF(AE124="No",AL122,AL122-AL126)+IF(BC124="No",BL122,BL122-BL126)+IF(CC124="No",CH122,CH122-CH126) -> 1000000
CM135: =IF(AND(CT133>=500000,CT133<=10000000),"Blindaje Patrimonial",IF(CT133>10000000,"Fideicomiso","No aplica producto de legado")) -> Blindaje Patrimonial

Sheet To do list
D6: RECOMENDACIONES CON RESPECTO A SU PATRIMONIO ACTUAL:
D7: 1. Su Patrimonio Neto actual en función de gastos (anuales) es:
H8: Insuficiente | X8: Suficiente | AN8: Mejor | BD8: Bien | BT8: Genial | CJ8: Excelente
CD9: FUENTES DE FLUJO DISPONIBLE
H10: =Balance!BW47 -> Considerando tu patrimonio financiero actual, puedes cubrir tus gastos totales anuales por 1.66 años con lo cual, tienes tus gastos cubiertos hasta los 52 años de edad. | AV10: =IF('Cálculos y Supuestos Balance'!Z6>0,"Los ingresos pasivos son una buena fuente para seguir creciendo tu patrimonio y hacer frente a obligaciones.","Es importante diversificar la fuentes de ingresos para que no solo dependan de una sola actividad.") -> Los ingresos pasivos son una buena fuente para seguir creciendo tu patrimonio y hacer frente a obligaciones.
CD12: Ingresos por Rentas | CS12: ='Cálculos y Supuestos Balance'!Z7 -> 20000
CD14: Ingresos por Negocios | CS14: ='Cálculos y Supuestos Balance'!Z8 -> 0
D19: 2. El nivel de liquidez de su patrimonio es:
D20: =IF('Patrimonio Neto'!K18>=1,"Suficiente para hacer frente a tus obligaciones.",IF('Patrimonio Neto'!K18=0,"Tu liquidez esta en función de tu calidad de vida deseada y no por tus obligaciones.","Deseable incrementar tu liquidez para cubrir compromisos futuros.")) -> Suficiente para hacer frente a tus obligaciones.
D23: 3. Tú nivel de solvencia (excluyendo activos de retiro) es:
E24: ='Cálculos y Supuestos Balance'!AB39 -> Tienes un nivel de solvencia excelente que te permite apalancarte en tus activos para seguir creciendo tu patrimonio. | BB24: =IF('Potencial del balance'!J2="Si","De acuerdo a tu nivel de apalancamiento actual, puedes recurrir a un crédito por "&TEXT('Potencial del balance'!F11,"#,0")&" sobre tus activos financieros.","No cuentas con capacidad de apalancamiento") -> De acuerdo a tu nivel de apalancamiento actual, puedes recurrir a un crédito por 2,142,857 sobre tus activos financieros.
BB27: =IF('Potencial del balance'!J2="Si","De acuerdo a tu nivel de apalancamiento actual, puedes recurrir a un crédito por "&TEXT('Potencial del balance'!F12,"#,0")&" sobre tus activos inmobiliarios.","No cuentas con capacidad de apalancamiento") -> De acuerdo a tu nivel de apalancamiento actual, puedes recurrir a un crédito por 357,143 sobre tus activos inmobiliarios.
D29: Índice de solvencia | P29: ='Cálculos y Supuestos Balance'!Z39 -> 0.85714286
D32: 4. Protección de tu patrimonio:
I34: SEGURO DE VIDA + EXCESO | BJ34: PROTEGE TU PROPIEDAD
I36: Protege a tus dependientes por una suma que cubra una protección de 3 años de tus gastos básicos. | BJ36: =IF(COUNTIF('Entrevista Balance'!G4:G8,">0")=1,"Contrata un seguro de hogar por:",IF(COUNTIF('Entrevista Balance'!G4:G8,">0")>1,"Contrata Multi-Seguro de Hogar",IF(COUNTIF('Entrevista Balance'!G4:G8,">0")=0,"No es imperante la contratación de un seguro de hogar",0))) -> Contrata un seguro de hogar por:
BY39: Suma Asegurada | CO39: Costo Prima Anual
M41: Suma Asegurada | AB41: Costo Prima Anual | BJ41: Seguro Propietario
BJ45: Seguro Arrendador
L49: *Si ya cuentas con un seguro de vida considera una extensión | BM49: *Valor estimado de la propiedad en función de la renta
D53: 5. Excedente al termino de etapa del retiro:
E56: LEGADO | K56: =Balance!CT133 -> 1000000 | AL56: =IF(AND(K56>=500000,K56<=10000000),"Blindaje Patrimonial",IF(K56>10000000,"Fideicomiso","No aplica producto de legado")) -> Blindaje Patrimonial

Sheet Patrimonio Neto
B1: Edad | C1: ='Entrevista Balance'!D6 -> 50 | E1: Patrimonio Neto | F1: =Balance!CN25 -> 6000000 | H1: Gasto total | K1: ='Entrevista Balance'!G26 -> 300000 | M1: Gasto Anual | N1: =K1*12 -> 3600000
A3: Edad | B3: Suficiente | C3: Mejor | D3: Bien | E3: Genial | F3: "On fire" | H3: Edad | J3: Insuficiente | K3: Suficiente | L3: Mejor | M3: Bien | N3: Genial | O3: "On fire"
J4: =IF($F$1<K15,1,0) -> 1 | K4: =IF(AND($F$1>=K15,$F$1<L15),1,0) -> 0 | L4: =IF(AND($F$1>=L15,$F$1<M15),1,0) -> 0 | M4: =IF(AND($F$1>=M15,$F$1<N15),1,0) -> 0 | N4: =IF(AND($F$1>=N15,$F$1<O15),1,0) -> 0 | O4: =IF($F$1>O15,1,0) -> 0
A5: 25 | B5: 0 | C5: 0.1 | D5: 0.25 | E5: 0.4 | F5: 0.5 | H5: 25 | I5: =IF($C$1<H6,1,0) -> 0 | J5: =$N$1*B5 -> 0 | K5: =$N$1*B5 -> 0 | L5: =$N$1*C5 -> 360000 | M5: =$N$1*D5 -> 900000 | N5: =$N$1*E5 -> 1440000 | O5: =$N$1*F5 -> 1800000
A6: 28 | B6: 0 | C6: 0.25 | D6: 0.4 | E6: 0.5 | F6: 1 | H6: 28 | I6: =IF(AND($C$1<H7,$C$1>=H6),1,0) -> 0 | J6: =$N$1*B6 -> 0 | K6: =$N$1*B6 -> 0 | L6: =$N$1*C6 -> 900000 | M6: =$N$1*D6 -> 1440000 | N6: =$N$1*E6 -> 1800000 | O6: =$N$1*F6 -> 3600000
A7: 30 | B7: 0.5 | C7: 0.75 | D7: 1 | E7: 1.5 | F7: 2 | H7: 30 | I7: =IF(AND($C$1<H8,$C$1>=H7),1,0) -> 0 | J7: =$N$1*B7 -> 1800000 | K7: =$N$1*B7 -> 1800000 | L7: =$N$1*C7 -> 2700000 | M7: =$N$1*D7 -> 3600000 | N7: =$N$1*E7 -> 5400000 | O7: =$N$1*F7 -> 7200000
A8: 35 | B8: 1 | C8: 2 | D8: 3 | E8: 4 | F8: 5 | H8: 35 | I8: =IF(AND($C$1<H9,$C$1>=H8),1,0) -> 0 | J8: =$N$1*B8 -> 3600000 | K8: =$N$1*B8 -> 3600000 | L8: =$N$1*C8 -> 7200000 | M8: =$N$1*D8 -> 10800000 | N8: =$N$1*E8 -> 14400000 | O8: =$N$1*F8 -> 18000000
A9: 40 | B9: 2 | C9: 4 | D9: 6 | E9: 8 | F9: 10 | H9: 40 | I9: =IF(AND($C$1<H10,$C$1>=H9),1,0) -> 0 | J9: =$N$1*B9 -> 7200000 | K9: =$N$1*B9 -> 7200000 | L9: =$N$1*C9 -> 14400000 | M9: =$N$1*D9 -> 21600000 | N9: =$N$1*E9 -> 28800000 | O9: =$N$1*F9 -> 36000000
A10: 45 | B10: 3 | C10: 6 | D10: 8 | E10: 10 | F10: 13 | H10: 45 | I10: =IF(AND($C$1<H11,$C$1>=H10),1,0) -> 0 | J10: =$N$1*B10 -> 10800000 | K10: =$N$1*B10 -> 10800000 | L10: =$N$1*C10 -> 21600000 | M10: =$N$1*D10 -> 28800000 | N10: =$N$1*E10 -> 36000000 | O10: =$N$1*F10 -> 46800000
A11: 50 | B11: 4 | C11: 7 | D11: 9 | E11: 12 | F11: 15 | H11: 50 | I11: =IF(AND($C$1<H12,$C$1>=H11),1,0) -> 1 | J11: =$N$1*B11 -> 14400000 | K11: =$N$1*B11 -> 14400000 | L11: =$N$1*C11 -> 25200000 | M11: =$N$1*D11 -> 32400000 | N11: =$N$1*E11 -> 43200000 | O11: =$N$1*F11 -> 54000000
A12: 55 | B12: 5 | C12: 8 | D12: 11 | E12: 14 | F12: 17 | H12: 55 | I12: =IF(AND($C$1<H13,$C$1>=H12),1,0) -> 0 | J12: =$N$1*B12 -> 18000000 | K12: =$N$1*B12 -> 18000000 | L12: =$N$1*C12 -> 28800000 | M12: =$N$1*D12 -> 39600000 | N12: =$N$1*E12 -> 50400000 | O12: =$N$1*F12 -> 61200000
A13: 60+ | B13: 6 | C13: 9 | D13: 13 | E13: 16 | F13: 20 | H13: 60 | I13: =IF(C1>=H13,1,0) -> 0 | J13: =$N$1*B13 -> 21600000 | K13: =$N$1*B13 -> 21600000 | L13: =$N$1*C13 -> 32400000 | M13: =$N$1*D13 -> 46800000 | N13: =$N$1*E13 -> 57600000 | O13: =$N$1*F13 -> 72000000
J15: =VLOOKUP(1,$I$5:J13,2,0) -> 14400000 | K15: =VLOOKUP(1,$I$5:K13,3,0) -> 14400000 | L15: =VLOOKUP(1,$I$5:L13,4,0) -> 25200000 | M15: =VLOOKUP(1,$I$5:M13,5,0) -> 32400000 | N15: =VLOOKUP(1,$I$5:N13,6,0) -> 43200000 | O15: =VLOOKUP(1,$I$5:O13,7,0) -> 54000000
H17: B)Liquidez para hacer frente a obligaciones
H18: Activos Acumulación+Reserva / Obligaciones | K18: =IFERROR((Balance!E9+Balance!E12)/Balance!AM25,0) -> 6 | M18: Arriba de 1 vez suficiente para cubrir compromisos futuros.
M20: Debajo de 1 vez recomendar hacer liquidez para cubrir compromisos futuros

Sheet Potencial del balance
B2: Potencial de Apalancamiento | E2: =Balance!Y74 -> 2500000 | I2: Capacidad de Apalanacamiento | J2: =IF(E2>0,"Si","No") -> Si
B4: Potencial Apalancamiento Total | E4: =Balance!AM25+E2 -> 3500000
B6: Activos Totales | E6: =E7+E8 -> 7000000
B7: Activos (Acumulación) | E7: =Balance!E12 -> 6000000 | F7: =E7/($E$7+$E$8) -> 0.85714286
B8: Activos Inmobiliarios | E8: =Balance!V9+Balance!V12+Balance!V15 -> 1000000 | F8: =1-F7 -> 0.14285714
B11: Crédito Activos Líquidos | E11: =E7*0.6 -> 3600000 | F11: =MIN(E2*F7,E11) -> 2142857.1
B12: Credito Bienes Inmuebles | E12: =E8*0.5 -> 500000 | F12: =MIN(F8*E2,E12) -> 357142.86
B13: Total | E13: =E11+E12 -> 4100000 | F13: =F11+F12 -> 2500000
D19: Sin esquemas pension | G19: Criterios: | K19: Deuda Activo | L19: Deuda + Préstamo
B20: Deuda | D20: =Balance!AM25 -> 1000000 | G20: Superior | H20: 0.5 | I20: Elevado | K20: =IF($D$24>$H$20,1,0) -> 0 | L20: =IF($D$31>$H$20,1,0) -> 0
B21: Activos Totales (sin pension) | D21: =Balance!V9+Balance!V12+Balance!V15+Balance!E9+Balance!E12 -> 7000000 | G21: Por arriba | H21: 0.4 | I21: Aceptable | K21: =IF(AND($D$24<=$H$20,$D$24>$H$21),1,0) -> 0 | L21: =IF(AND($D$31<=$H$20,$D$31>$H$21),1,0) -> 0
G22: Por debajo | H22: 0.3 | I22: Recomendable | K22: =IF(AND($D$24<=$H$21,$D$24>$H$22),1,0) -> 0 | L22: =IF(AND($D$31<=$H$21,$D$31>$H$22),1,0) -> 1
G23: Menor a | H23: 0.1 | I23: Muy saludable | K23: =IF($D$24<=$H$22,1,0) -> 1 | L23: =IF($D$31<=$H$22,1,0) -> 0
B24: Indice Deuda Activo | D24: =D20/D21 -> 0.14285714
B27: Prestamo | D27: =Balance!CP70 -> 2000000
B28: Nuevo nivel de deuda | D28: =D20+D27 -> 3000000
B29: Activos | D29: =D21+D27 -> 9000000
B31: Indice Deuda Activo | D31: =D28/D29 -> 0.33333333
B33: Incremento en activos | D33: =(D29/D21)-1 -> 0.28571429
B39: Índice de Apalancamiento: | D39: =IF(Balance!AM25>0,(Balance!BW22-Balance!E18-Balance!V21)/(Balance!AM9+Balance!AM12+Balance!AM15),0) -> 7
B40: Mínimo seguridad (2x): | D40: =(Balance!BW22-Balance!E18-Balance!V21)*0.5 -> 3500000
